Workbook

Sheet Exploratory Data Analysis
B3: Fintech Application Explortory Data Analysis
B7: Gender Analysis | M7: previous app | O7: Favorite App
B9: Gender | C9: Count | D9: Percentage | O9: easypaisa | P9: sadapay | Q9: nayapay | R9: jazzcash
B10: {=_xlfn.UNIQUE(SINGLE_RESPONSES[Gender])} -> Male | C10: =COUNTIF(SINGLE_RESPONSES[Gender],B10) -> 106 | D10: =C10/150 -> 0.70666667 | N10: easypaisa | P10: =COUNTIFS(SINGLE_RESPONSES!$I2:$I151,'Exploratory Data Analysis'!$N10,SINGLE_RESPONSES!$G2:$G151,'Exploratory Data Analysis'!P$9) -> 7 | Q10: =COUNTIFS(SINGLE_RESPONSES!$I2:$I151,'Exploratory Data Analysis'!$N10,SINGLE_RESPONSES!$G2:$G151,'Exploratory Data Analysis'!Q$9) -> 7 | R10: =COUNTIFS(SINGLE_RESPONSES!$I2:$I151,'Exploratory Data Analysis'!$N10,SINGLE_RESPONSES!$G2:$G151,'Exploratory Data Analysis'!R$9) -> 26
B11: Female | C11: =COUNTIF(SINGLE_RESPONSES[Gender],B11) -> 43 | D11: =C11/150 -> 0.28666667 | N11: sadapay | O11: =COUNTIFS(SINGLE_RESPONSES!$I3:$I152,'Exploratory Data Analysis'!$N11,SINGLE_RESPONSES!$G3:$G152,'Exploratory Data Analysis'!O$9) -> 3 | Q11: =COUNTIFS(SINGLE_RESPONSES!$I3:$I152,'Exploratory Data Analysis'!$N11,SINGLE_RESPONSES!$G3:$G152,'Exploratory Data Analysis'!Q$9) -> 2 | R11: =COUNTIFS(SINGLE_RESPONSES!$I3:$I152,'Exploratory Data Analysis'!$N11,SINGLE_RESPONSES!$G3:$G152,'Exploratory Data Analysis'!R$9) -> 3
B12: Prefer not to say | C12: =COUNTIF(SINGLE_RESPONSES[Gender],B12) -> 1 | D12: =C12/150 -> 0.0066666667 | N12: nayapay | O12: =COUNTIFS(SINGLE_RESPONSES!$I4:$I153,'Exploratory Data Analysis'!$N12,SINGLE_RESPONSES!$G4:$G153,'Exploratory Data Analysis'!O$9) -> 4 | P12: =COUNTIFS(SINGLE_RESPONSES!$I4:$I153,'Exploratory Data Analysis'!$N12,SINGLE_RESPONSES!$G4:$G153,'Exploratory Data Analysis'!P$9) -> 0 | R12: =COUNTIFS(SINGLE_RESPONSES!$I4:$I153,'Exploratory Data Analysis'!$N12,SINGLE_RESPONSES!$G4:$G153,'Exploratory Data Analysis'!R$9) -> 5
N13: jazzcash | O13: =COUNTIFS(SINGLE_RESPONSES!$I5:$I154,'Exploratory Data Analysis'!$N13,SINGLE_RESPONSES!$G5:$G154,'Exploratory Data Analysis'!O$9) -> 20 | P13: =COUNTIFS(SINGLE_RESPONSES!$I5:$I154,'Exploratory Data Analysis'!$N13,SINGLE_RESPONSES!$G5:$G154,'Exploratory Data Analysis'!P$9) -> 9 | Q13: =COUNTIFS(SINGLE_RESPONSES!$I5:$I154,'Exploratory Data Analysis'!$N13,SINGLE_RESPONSES!$G5:$G154,'Exploratory Data Analysis'!Q$9) -> 9
B24: Age Group Analysis | M24: Reasons why people are moving to other apps | N24: Favorite App
N25: easypaisa | O25: jazzcash | P25: sadapay | Q25: nayapay
M26: PULL factors
B27: Index | C27: Age Group | D27: Percentage | E27: Count | M27: Better UX | N27: =COUNTIFS('Reason_to_switch_&_keep_using'!$G:$G,$M27,'Reason_to_switch_&_keep_using'!$D:$D,N$25) -> 4 | O27: =COUNTIFS('Reason_to_switch_&_keep_using'!$G:$G,$M27,'Reason_to_switch_&_keep_using'!$D:$D,O$25) -> 10 | P27: =COUNTIFS('Reason_to_switch_&_keep_using'!$G:$G,$M27,'Reason_to_switch_&_keep_using'!$D:$D,P$25) -> 4 | Q27: =COUNTIFS('Reason_to_switch_&_keep_using'!$G:$G,$M27,'Reason_to_switch_&_keep_using'!$D:$D,Q$25) -> 0
B28: {=_xlfn._xlws.SORT(_xlfn.UNIQUE(SINGLE_RESPONSES[coding]))} -> 1 | C28: 18-29 | D28: =E28/150 -> 0.84666667 | E28: =COUNTIF(SINGLE_RESPONSES[coding],B28) -> 127 | M28: Better Features | N28: =COUNTIFS('Reason_to_switch_&_keep_using'!$G:$G,$M28,'Reason_to_switch_&_keep_using'!$D:$D,N$25) -> 4 | O28: =COUNTIFS('Reason_to_switch_&_keep_using'!$G:$G,$M28,'Reason_to_switch_&_keep_using'!$D:$D,O$25) -> 3 | P28: =COUNTIFS('Reason_to_switch_&_keep_using'!$G:$G,$M28,'Reason_to_switch_&_keep_using'!$D:$D,P$25) -> 1 | Q28: =COUNTIFS('Reason_to_switch_&_keep_using'!$G:$G,$M28,'Reason_to_switch_&_keep_using'!$D:$D,Q$25) -> 2
B29: 2 | C29: 30-41 | D29: =E29/150 -> 0.1 | E29: =COUNTIF(SINGLE_RESPONSES[coding],B29) -> 15 | M29: Performance | N29: =COUNTIFS('Reason_to_switch_&_keep_using'!$G:$G,$M29,'Reason_to_switch_&_keep_using'!$D:$D,N$25) -> 1 | O29: =COUNTIFS('Reason_to_switch_&_keep_using'!$G:$G,$M29,'Reason_to_switch_&_keep_using'!$D:$D,O$25) -> 4 | P29: =COUNTIFS('Reason_to_switch_&_keep_using'!$G:$G,$M29,'Reason_to_switch_&_keep_using'!$D:$D,P$25) -> 0 | Q29: =COUNTIFS('Reason_to_switch_&_keep_using'!$G:$G,$M29,'Reason_to_switch_&_keep_using'!$D:$D,Q$25) -> 0
B30: 3 | C30: 42-54 | D30: =E30/150 -> 0.033333333 | E30: =COUNTIF(SINGLE_RESPONSES[coding],B30) -> 5 | M30: Good Customer Services | N30: =COUNTIFS('Reason_to_switch_&_keep_using'!$G:$G,$M30,'Reason_to_switch_&_keep_using'!$D:$D,N$25) -> 1 | O30: =COUNTIFS('Reason_to_switch_&_keep_using'!$G:$G,$M30,'Reason_to_switch_&_keep_using'!$D:$D,O$25) -> 1 | P30: =COUNTIFS('Reason_to_switch_&_keep_using'!$G:$G,$M30,'Reason_to_switch_&_keep_using'!$D:$D,P$25) -> 1 | Q30: =COUNTIFS('Reason_to_switch_&_keep_using'!$G:$G,$M30,'Reason_to_switch_&_keep_using'!$D:$D,Q$25) -> 0
B31: 4 | C31: 55-64 | D31: =E31/150 -> 0.013333333 | E31: =COUNTIF(SINGLE_RESPONSES[coding],B31) -> 2 | M31: Ecosystem Advantage | N31: =COUNTIFS('Reason_to_switch_&_keep_using'!$G:$G,$M31,'Reason_to_switch_&_keep_using'!$D:$D,N$25) -> 2 | O31: =COUNTIFS('Reason_to_switch_&_keep_using'!$G:$G,$M31,'Reason_to_switch_&_keep_using'!$D:$D,O$25) -> 3 | P31: =COUNTIFS('Reason_to_switch_&_keep_using'!$G:$G,$M31,'Reason_to_switch_&_keep_using'!$D:$D,P$25) -> 0 | Q31: =COUNTIFS('Reason_to_switch_&_keep_using'!$G:$G,$M31,'Reason_to_switch_&_keep_using'!$D:$D,Q$25) -> 0
B32: 5 | C32: 66 and above | D32: =E32/150 -> 0.0066666667 | E32: =COUNTIF(SINGLE_RESPONSES[coding],B32) -> 1 | M32: Greater Trust | N32: =COUNTIFS('Reason_to_switch_&_keep_using'!$G:$G,$M32,'Reason_to_switch_&_keep_using'!$D:$D,N$25) -> 0 | O32: =COUNTIFS('Reason_to_switch_&_keep_using'!$G:$G,$M32,'Reason_to_switch_&_keep_using'!$D:$D,O$25) -> 0 | P32: =COUNTIFS('Reason_to_switch_&_keep_using'!$G:$G,$M32,'Reason_to_switch_&_keep_using'!$D:$D,P$25) -> 0 | Q32: =COUNTIFS('Reason_to_switch_&_keep_using'!$G:$G,$M32,'Reason_to_switch_&_keep_using'!$D:$D,Q$25) -> 1
M33: Explore | N33: =COUNTIFS('Reason_to_switch_&_keep_using'!$G:$G,$M33,'Reason_to_switch_&_keep_using'!$D:$D,N$25) -> 6 | O33: =COUNTIFS('Reason_to_switch_&_keep_using'!$G:$G,$M33,'Reason_to_switch_&_keep_using'!$D:$D,O$25) -> 7 | P33: =COUNTIFS('Reason_to_switch_&_keep_using'!$G:$G,$M33,'Reason_to_switch_&_keep_using'!$D:$D,P$25) -> 3 | Q33: =COUNTIFS('Reason_to_switch_&_keep_using'!$G:$G,$M33,'Reason_to_switch_&_keep_using'!$D:$D,Q$25) -> 3
M34: PUSH Factors
M35: Trust issues | N35: =COUNTIFS('Reason_to_switch_&_keep_using'!$G:$G,$M35,'Reason_to_switch_&_keep_using'!$D:$D,N$25) -> 1 | O35: =COUNTIFS('Reason_to_switch_&_keep_using'!$G:$G,$M35,'Reason_to_switch_&_keep_using'!$D:$D,O$25) -> 2 | P35: =COUNTIFS('Reason_to_switch_&_keep_using'!$G:$G,$M35,'Reason_to_switch_&_keep_using'!$D:$D,P$25) -> 1 | Q35: =COUNTIFS('Reason_to_switch_&_keep_using'!$G:$G,$M35,'Reason_to_switch_&_keep_using'!$D:$D,Q$25) -> 1
M36: Technical Failures | N36: =COUNTIFS('Reason_to_switch_&_keep_using'!$G:$G,$M36,'Reason_to_switch_&_keep_using'!$D:$D,N$25) -> 3 | O36: =COUNTIFS('Reason_to_switch_&_keep_using'!$G:$G,$M36,'Reason_to_switch_&_keep_using'!$D:$D,O$25) -> 0 | P36: =COUNTIFS('Reason_to_switch_&_keep_using'!$G:$G,$M36,'Reason_to_switch_&_keep_using'!$D:$D,P$25) -> 3 | Q36: =COUNTIFS('Reason_to_switch_&_keep_using'!$G:$G,$M36,'Reason_to_switch_&_keep_using'!$D:$D,Q$25) -> 2
M37: Account Access Issues | N37: =COUNTIFS('Reason_to_switch_&_keep_using'!$G:$G,$M37,'Reason_to_switch_&_keep_using'!$D:$D,N$25) -> 0 | O37: =COUNTIFS('Reason_to_switch_&_keep_using'!$G:$G,$M37,'Reason_to_switch_&_keep_using'!$D:$D,O$25) -> 2 | P37: =COUNTIFS('Reason_to_switch_&_keep_using'!$G:$G,$M37,'Reason_to_switch_&_keep_using'!$D:$D,P$25) -> 0 | Q37: =COUNTIFS('Reason_to_switch_&_keep_using'!$G:$G,$M37,'Reason_to_switch_&_keep_using'!$D:$D,Q$25) -> 0
M38: Bad UX | N38: =COUNTIFS('Reason_to_switch_&_keep_using'!$G:$G,$M38,'Reason_to_switch_&_keep_using'!$D:$D,N$25) -> 0 | O38: =COUNTIFS('Reason_to_switch_&_keep_using'!$G:$G,$M38,'Reason_to_switch_&_keep_using'!$D:$D,O$25) -> 2 | P38: =COUNTIFS('Reason_to_switch_&_keep_using'!$G:$G,$M38,'Reason_to_switch_&_keep_using'!$D:$D,P$25) -> 0 | Q38: =COUNTIFS('Reason_to_switch_&_keep_using'!$G:$G,$M38,'Reason_to_switch_&_keep_using'!$D:$D,Q$25) -> 0
M39: Poor Customer Service | N39: =COUNTIFS('Reason_to_switch_&_keep_using'!$G:$G,$M39,'Reason_to_switch_&_keep_using'!$D:$D,N$25) -> 0 | O39: =COUNTIFS('Reason_to_switch_&_keep_using'!$G:$G,$M39,'Reason_to_switch_&_keep_using'!$D:$D,O$25) -> 0 | P39: =COUNTIFS('Reason_to_switch_&_keep_using'!$G:$G,$M39,'Reason_to_switch_&_keep_using'!$D:$D,P$25) -> 0 | Q39: =COUNTIFS('Reason_to_switch_&_keep_using'!$G:$G,$M39,'Reason_to_switch_&_keep_using'!$D:$D,Q$25) -> 0
B41: Awareness
B42: App | C42: Count | D42: Percentage
B43: easypaisa | C43: =COUNTIF(Table10_1[Application(Awareness)],'Exploratory Data Analysis'!B43) -> 100 | D43: =C43/150 -> 0.66666667
B44: sadapay | C44: =COUNTIF(Table10_1[Application(Awareness)],'Exploratory Data Analysis'!B44) -> 61 | D44: =C44/150 -> 0.40666667
B45: jazzcash | C45: =COUNTIF(Table10_1[Application(Awareness)],'Exploratory Data Analysis'!B45) -> 114 | D45: =C45/150 -> 0.76 | M45: Reasons why people want to keep using their current app | N45: Favorite App
B46: nayapay | C46: =COUNTIF(Table10_1[Application(Awareness)],'Exploratory Data Analysis'!B46) -> 55 | D46: =C46/150 -> 0.36666667 | N46: easypaisa | O46: jazzcash | P46: sadapay | Q46: nayapay
M47: Better UX | N47: =COUNTIFS('Reason_to_switch_&_keep_using'!$K:$K,'Exploratory Data Analysis'!$M47,'Reason_to_switch_&_keep_using'!$D:$D,'Exploratory Data Analysis'!N$46) -> 15 | O47: =COUNTIFS('Reason_to_switch_&_keep_using'!$K:$K,'Exploratory Data Analysis'!$M47,'Reason_to_switch_&_keep_using'!$D:$D,'Exploratory Data Analysis'!O$46) -> 26 | P47: =COUNTIFS('Reason_to_switch_&_keep_using'!$K:$K,'Exploratory Data Analysis'!$M47,'Reason_to_switch_&_keep_using'!$D:$D,'Exploratory Data Analysis'!P$46) -> 8 | Q47: =COUNTIFS('Reason_to_switch_&_keep_using'!$K:$K,'Exploratory Data Analysis'!$M47,'Reason_to_switch_&_keep_using'!$D:$D,'Exploratory Data Analysis'!Q$46) -> 8
M48: Ecosystem Advantage | N48: =COUNTIFS('Reason_to_switch_&_keep_using'!$K:$K,'Exploratory Data Analysis'!$M48,'Reason_to_switch_&_keep_using'!$D:$D,'Exploratory Data Analysis'!N$46) -> 3 | O48: =COUNTIFS('Reason_to_switch_&_keep_using'!$K:$K,'Exploratory Data Analysis'!$M48,'Reason_to_switch_&_keep_using'!$D:$D,'Exploratory Data Analysis'!O$46) -> 7 | P48: =COUNTIFS('Reason_to_switch_&_keep_using'!$K:$K,'Exploratory Data Analysis'!$M48,'Reason_to_switch_&_keep_using'!$D:$D,'Exploratory Data Analysis'!P$46) -> 0 | Q48: =COUNTIFS('Reason_to_switch_&_keep_using'!$K:$K,'Exploratory Data Analysis'!$M48,'Reason_to_switch_&_keep_using'!$D:$D,'Exploratory Data Analysis'!Q$46) -> 0
M49: Performance | N49: =COUNTIFS('Reason_to_switch_&_keep_using'!$K:$K,'Exploratory Data Analysis'!$M49,'Reason_to_switch_&_keep_using'!$D:$D,'Exploratory Data Analysis'!N$46) -> 6 | O49: =COUNTIFS('Reason_to_switch_&_keep_using'!$K:$K,'Exploratory Data Analysis'!$M49,'Reason_to_switch_&_keep_using'!$D:$D,'Exploratory Data Analysis'!O$46) -> 9 | P49: =COUNTIFS('Reason_to_switch_&_keep_using'!$K:$K,'Exploratory Data Analysis'!$M49,'Reason_to_switch_&_keep_using'!$D:$D,'Exploratory Data Analysis'!P$46) -> 1 | Q49: =COUNTIFS('Reason_to_switch_&_keep_using'!$K:$K,'Exploratory Data Analysis'!$M49,'Reason_to_switch_&_keep_using'!$D:$D,'Exploratory Data Analysis'!Q$46) -> 2
M50: Better features | N50: =COUNTIFS('Reason_to_switch_&_keep_using'!$K:$K,'Exploratory Data Analysis'!$M50,'Reason_to_switch_&_keep_using'!$D:$D,'Exploratory Data Analysis'!N$46) -> 7 | O50: =COUNTIFS('Reason_to_switch_&_keep_using'!$K:$K,'Exploratory Data Analysis'!$M50,'Reason_to_switch_&_keep_using'!$D:$D,'Exploratory Data Analysis'!O$46) -> 8 | P50: =COUNTIFS('Reason_to_switch_&_keep_using'!$K:$K,'Exploratory Data Analysis'!$M50,'Reason_to_switch_&_keep_using'!$D:$D,'Exploratory Data Analysis'!P$46) -> 5 | Q50: =COUNTIFS('Reason_to_switch_&_keep_using'!$K:$K,'Exploratory Data Analysis'!$M50,'Reason_to_switch_&_keep_using'!$D:$D,'Exploratory Data Analysis'!Q$46) -> 7
M51: Other | N51: =COUNTIFS('Reason_to_switch_&_keep_using'!$K:$K,'Exploratory Data Analysis'!$M51,'Reason_to_switch_&_keep_using'!$D:$D,'Exploratory Data Analysis'!N$46) -> 2 | O51: =COUNTIFS('Reason_to_switch_&_keep_using'!$K:$K,'Exploratory Data Analysis'!$M51,'Reason_to_switch_&_keep_using'!$D:$D,'Exploratory Data Analysis'!O$46) -> 6 | P51: =COUNTIFS('Reason_to_switch_&_keep_using'!$K:$K,'Exploratory Data Analysis'!$M51,'Reason_to_switch_&_keep_using'!$D:$D,'Exploratory Data Analysis'!P$46) -> 0 | Q51: =COUNTIFS('Reason_to_switch_&_keep_using'!$K:$K,'Exploratory Data Analysis'!$M51,'Reason_to_switch_&_keep_using'!$D:$D,'Exploratory Data Analysis'!Q$46) -> 1
M52: Greater Trust | N52: =COUNTIFS('Reason_to_switch_&_keep_using'!$K:$K,'Exploratory Data Analysis'!$M52,'Reason_to_switch_&_keep_using'!$D:$D,'Exploratory Data Analysis'!N$46) -> 5 | O52: =COUNTIFS('Reason_to_switch_&_keep_using'!$K:$K,'Exploratory Data Analysis'!$M52,'Reason_to_switch_&_keep_using'!$D:$D,'Exploratory Data Analysis'!O$46) -> 1 | P52: =COUNTIFS('Reason_to_switch_&_keep_using'!$K:$K,'Exploratory Data Analysis'!$M52,'Reason_to_switch_&_keep_using'!$D:$D,'Exploratory Data Analysis'!P$46) -> 0 | Q52: =COUNTIFS('Reason_to_switch_&_keep_using'!$K:$K,'Exploratory Data Analysis'!$M52,'Reason_to_switch_&_keep_using'!$D:$D,'Exploratory Data Analysis'!Q$46) -> 2
M53: Good Customer Service | N53: =COUNTIFS('Reason_to_switch_&_keep_using'!$K:$K,'Exploratory Data Analysis'!$M53,'Reason_to_switch_&_keep_using'!$D:$D,'Exploratory Data Analysis'!N$46) -> 3 | O53: =COUNTIFS('Reason_to_switch_&_keep_using'!$K:$K,'Exploratory Data Analysis'!$M53,'Reason_to_switch_&_keep_using'!$D:$D,'Exploratory Data Analysis'!O$46) -> 6 | P53: =COUNTIFS('Reason_to_switch_&_keep_using'!$K:$K,'Exploratory Data Analysis'!$M53,'Reason_to_switch_&_keep_using'!$D:$D,'Exploratory Data Analysis'!P$46) -> 1 | Q53: =COUNTIFS('Reason_to_switch_&_keep_using'!$K:$K,'Exploratory Data Analysis'!$M53,'Reason_to_switch_&_keep_using'!$D:$D,'Exploratory Data Analysis'!Q$46) -> 1
M54: Financial benefits | N54: =COUNTIFS('Reason_to_switch_&_keep_using'!$K:$K,'Exploratory Data Analysis'!$M54,'Reason_to_switch_&_keep_using'!$D:$D,'Exploratory Data Analysis'!N$46) -> 0 | O54: =COUNTIFS('Reason_to_switch_&_keep_using'!$K:$K,'Exploratory Data Analysis'!$M54,'Reason_to_switch_&_keep_using'!$D:$D,'Exploratory Data Analysis'!O$46) -> 0 | P54: =COUNTIFS('Reason_to_switch_&_keep_using'!$K:$K,'Exploratory Data Analysis'!$M54,'Reason_to_switch_&_keep_using'!$D:$D,'Exploratory Data Analysis'!P$46) -> 0 | Q54: =COUNTIFS('Reason_to_switch_&_keep_using'!$K:$K,'Exploratory Data Analysis'!$M54,'Reason_to_switch_&_keep_using'!$D:$D,'Exploratory Data Analysis'!Q$46) -> 2
B56: Favorite App
B57: App | C57: Count | D57: Percentage
B58: {=_xlfn.UNIQUE(SINGLE_RESPONSES[FAVORITE])} -> easypaisa | C58: =COUNTIF(SINGLE_RESPONSES[FAVORITE],B58) -> 43 | D58: =C58/150 -> 0.28666667
B59: sadapay | C59: =COUNTIF(SINGLE_RESPONSES[FAVORITE],B59) -> 18 | D59: =C59/150 -> 0.12
B60: nayapay | C60: =COUNTIF(SINGLE_RESPONSES[FAVORITE],B60) -> 24 | D60: =C60/150 -> 0.16
B61: jazzcash | C61: =COUNTIF(SINGLE_RESPONSES[FAVORITE],B61) -> 65 | D61: =C61/150 -> 0.43333333
B71: Apps Usage
A73: 1 | B73: Less than 1 month | C73: =COUNTIFS($H$2:$H$151,$D73,$G$2:$G$151,C$227) -> 3 | D73: =COUNTIFS($H$2:$H$151,$D73,$G$2:$G$151,D$227) -> 3 | E73: =COUNTIFS($H$2:$H$151,$D73,$G$2:$G$151,E$227) -> 0 | F73: =COUNTIFS($H$2:$H$151,$D73,$G$2:$G$151,F$227) -> 4
A74: 2 | B74: 1-4 months | C74: =COUNTIFS($H$2:$H$151,$D74,$G$2:$G$151,C$227) -> 1 | D74: =COUNTIFS($H$2:$H$151,$D74,$G$2:$G$151,D$227) -> 0 | E74: =COUNTIFS($H$2:$H$151,$D74,$G$2:$G$151,E$227) -> 0 | F74: =COUNTIFS($H$2:$H$151,$D74,$G$2:$G$151,F$227) -> 7
A75: 3 | B75: 5-8 months | C75: =COUNTIFS($H$2:$H$151,$D75,$G$2:$G$151,C$227) -> 1 | D75: =COUNTIFS($H$2:$H$151,$D75,$G$2:$G$151,D$227) -> 2 | E75: =COUNTIFS($H$2:$H$151,$D75,$G$2:$G$151,E$227) -> 1 | F75: =COUNTIFS($H$2:$H$151,$D75,$G$2:$G$151,F$227) -> 2
A76: 4 | B76: 9-12 months | C76: =COUNTIFS($H$2:$H$151,$D76,$G$2:$G$151,C$227) -> 5 | D76: =COUNTIFS($H$2:$H$151,$D76,$G$2:$G$151,D$227) -> 1 | E76: =COUNTIFS($H$2:$H$151,$D76,$G$2:$G$151,E$227) -> 2 | F76: =COUNTIFS($H$2:$H$151,$D76,$G$2:$G$151,F$227) -> 9
A77: 5 | B77: 13-18 months | C77: =COUNTIFS($H$2:$H$151,$D77,$G$2:$G$151,C$227) -> 5 | D77: =COUNTIFS($H$2:$H$151,$D77,$G$2:$G$151,D$227) -> 3 | E77: =COUNTIFS($H$2:$H$151,$D77,$G$2:$G$151,E$227) -> 2 | F77: =COUNTIFS($H$2:$H$151,$D77,$G$2:$G$151,F$227) -> 5
A78: 6 | B78: 18-24 months | C78: =COUNTIFS($H$2:$H$151,$D78,$G$2:$G$151,C$227) -> 6 | D78: =COUNTIFS($H$2:$H$151,$D78,$G$2:$G$151,D$227) -> 2 | E78: =COUNTIFS($H$2:$H$151,$D78,$G$2:$G$151,E$227) -> 1 | F78: =COUNTIFS($H$2:$H$151,$D78,$G$2:$G$151,F$227) -> 7
A79: 7 | B79: More than 2 years | C79: =COUNTIFS($H$2:$H$151,$D79,$G$2:$G$151,C$227) -> 22 | D79: =COUNTIFS($H$2:$H$151,$D79,$G$2:$G$151,D$227) -> 7 | E79: =COUNTIFS($H$2:$H$151,$D79,$G$2:$G$151,E$227) -> 18 | F79: =COUNTIFS($H$2:$H$151,$D79,$G$2:$G$151,F$227) -> 31
B83: Where people moved from their Ex-App
B86: Current App | C86: Application | D86: Count | E86: Percentage
C87: easypaisa | D87: =COUNTIF(SINGLE_RESPONSES[Previous Brand],C87) -> 55 | E87: =D87/150 -> 0.36666667
C88: sadapay | D88: =COUNTIF(SINGLE_RESPONSES[Previous Brand],C88) -> 11 | E88: =D88/150 -> 0.073333333
C89: nayapay | D89: =COUNTIF(SINGLE_RESPONSES[Previous Brand],C89) -> 15 | E89: =D89/150 -> 0.1
C90: jazzcash | D90: =COUNTIF(SINGLE_RESPONSES[Previous Brand],C90) -> 69 | E90: =D90/150 -> 0.46

Sheet Top_of_Mind_Awareness
B1: =COUNTA(SINGLE_RESPONSES[TOM]) -> 150
B6: TOMA | C6: Count | D6: % | G6: TOTAL AWARENESS | H6: Count | I6: % | L6: CURRENT USAGE | M6: Count | N6: % | Q6: EVER USED | R6: Count | S6: % | V6: FAVORITE | W6: Count | X6: %
B7: {=_xlfn.UNIQUE(SINGLE_RESPONSES[TOM])} -> easypaisa | C7: =COUNTIF(SINGLE_RESPONSES[TOM],B7) -> 46 | D7: =C7/$B$1 -> 0.30666667 | G7: {=_xlfn.UNIQUE(SINGLE_RESPONSES[TOM])} -> easypaisa | H7: 100 | I7: =H7/$B$1 -> 0.66666667 | L7: {=_xlfn.UNIQUE(SINGLE_RESPONSES[TOM])} -> easypaisa | M7: =COUNTIF(CURRENT_USAGE[APP],L7) -> 77 | N7: =M7/$B$1 -> 0.51333333 | Q7: {=_xlfn.UNIQUE(SINGLE_RESPONSES[TOM])} -> easypaisa | R7: =COUNTIF(EVER_USED[APP],Q7) -> 89 | S7: =R7/$B$1 -> 0.59333333 | V7: {=_xlfn.UNIQUE(SINGLE_RESPONSES[TOM])} -> easypaisa | W7: =COUNTIF(SINGLE_RESPONSES[FAVORITE],V7) -> 43 | X7: =W7/$B$1 -> 0.28666667
B8: sadapay | C8: =COUNTIF(SINGLE_RESPONSES[TOM],B8) -> 8 | D8: =C8/$B$1 -> 0.053333333 | G8: sadapay | H8: 61 | I8: =H8/150 -> 0.40666667 | L8: sadapay | M8: =COUNTIF(CURRENT_USAGE[APP],L8) -> 41 | N8: =M8/$B$1 -> 0.27333333 | Q8: sadapay | R8: =COUNTIF(EVER_USED[APP],Q8) -> 57 | S8: =R8/$B$1 -> 0.38 | V8: sadapay | W8: =COUNTIF(SINGLE_RESPONSES[FAVORITE],V8) -> 18 | X8: =W8/$B$1 -> 0.12
B9: jazzcash | C9: =COUNTIF(SINGLE_RESPONSES[TOM],B9) -> 83 | D9: =C9/$B$1 -> 0.55333333 | G9: jazzcash | H9: 114 | I9: =Engineered_Awareness_data!G154 -> 0.76 | L9: jazzcash | M9: =COUNTIF(CURRENT_USAGE[APP],L9) -> 93 | N9: =M9/$B$1 -> 0.62 | Q9: jazzcash | R9: =COUNTIF(EVER_USED[APP],Q9) -> 99 | S9: =R9/$B$1 -> 0.66 | V9: jazzcash | W9: =COUNTIF(SINGLE_RESPONSES[FAVORITE],V9) -> 65 | X9: =W9/$B$1 -> 0.43333333
B10: nayapay | C10: =COUNTIF(SINGLE_RESPONSES[TOM],B10) -> 10 | D10: =C10/$B$1 -> 0.066666667 | G10: nayapay | H10: 55 | I10: =H10/$B$1 -> 0.36666667 | L10: nayapay | M10: =COUNTIF(CURRENT_USAGE[APP],L10) -> 43 | N10: =M10/$B$1 -> 0.28666667 | Q10: nayapay | R10: =COUNTIF(EVER_USED[APP],Q10) -> 53 | S10: =R10/$B$1 -> 0.35333333 | V10: nayapay | W10: =COUNTIF(SINGLE_RESPONSES[FAVORITE],V10) -> 24 | X10: =W10/$B$1 -> 0.16
B11: bankaccount | C11: =COUNTIF(SINGLE_RESPONSES[TOM],B11) -> 1 | D11: =C11/$B$1 -> 0.0066666667 | G11: bankaccount | H11: =COUNTIF(Engineered_Awareness_data!$B$2:$B$151,Top_of_Mind_Awareness!G11) -> 0 | I11: =H11/$B$1 -> 0 | L11: bankaccount | M11: =COUNTIF(CURRENT_USAGE[APP],L11) -> 0 | N11: =M11/$B$1 -> 0 | Q11: bankaccount | R11: =COUNTIF(EVER_USED[APP],Q11) -> 0 | S11: =R11/$B$1 -> 0 | V11: bankaccount | W11: =COUNTIF(SINGLE_RESPONSES[FAVORITE],V11) -> 0 | X11: =W11/$B$1 -> 0
B12: mashreq | C12: =COUNTIF(SINGLE_RESPONSES[TOM],B12) -> 1 | D12: =C12/$B$1 -> 0.0066666667 | G12: mashreq | H12: =COUNTIF(Engineered_Awareness_data!$B$2:$B$151,Top_of_Mind_Awareness!G12) -> 0 | I12: =H12/$B$1 -> 0 | L12: mashreq | M12: =COUNTIF(CURRENT_USAGE[APP],L12) -> 0 | N12: =M12/$B$1 -> 0 | Q12: mashreq | R12: =COUNTIF(EVER_USED[APP],Q12) -> 0 | S12: =R12/$B$1 -> 0 | V12: mashreq | W12: =COUNTIF(SINGLE_RESPONSES[FAVORITE],V12) -> 0 | X12: =W12/$B$1 -> 0
B13: hbl | C13: =COUNTIF(SINGLE_RESPONSES[TOM],B13) -> 1 | D13: =C13/$B$1 -> 0.0066666667 | G13: hbl | H13: =COUNTIF(Engineered_Awareness_data!$B$2:$B$151,Top_of_Mind_Awareness!G13) -> 0 | I13: =H13/$B$1 -> 0 | L13: hbl | M13: =COUNTIF(CURRENT_USAGE[APP],L13) -> 0 | N13: =M13/$B$1 -> 0 | Q13: hbl | R13: =COUNTIF(EVER_USED[APP],Q13) -> 0 | S13: =R13/$B$1 -> 0 | V13: hbl | W13: =COUNTIF(SINGLE_RESPONSES[FAVORITE],V13) -> 0 | X13: =W13/$B$1 -> 0
C14: =SUM(C7:C13) -> 150 | D14: =C14/$B$1 -> 1 | I14: =SUM(I7:I13) -> 2.2
C19: jazzcash | D19: easypaisa | E19: sadapay | F19: nayapay
B20: AWARENESS | C20: =Engineered_Awareness_data!G154 -> 0.76 | D20: =Engineered_Awareness_data!H154 -> 0.66666667 | E20: =Engineered_Awareness_data!I154 -> 0.40666667 | F20: =Engineered_Awareness_data!J154 -> 0.36666667
B21: EVER USED | C21: =S9 -> 0.66 | D21: =S7 -> 0.59333333 | E21: =S8 -> 0.38 | F21: =S10 -> 0.35333333
B22: CURRENT USAGE | C22: =N9 -> 0.62 | D22: =N7 -> 0.51333333 | E22: =N8 -> 0.27333333 | F22: =S10 -> 0.35333333
B23: FAVORITE | C23: =X9 -> 0.43333333 | D23: =X7 -> 0.28666667 | E23: =X8 -> 0.12 | F23: =X10 -> 0.16
C24: =C23/C20 -> 0.57017544 | D24: =D23/D20 -> 0.43 | E24: =E23/E20 -> 0.29508197 | F24: =F23/F20 -> 0.43636364

Sheet Imagery_Analysis
D6: IMAGERY | E6: {=TRANSPOSE(_xlfn.UNIQUE(IMAGERY[APP]))} -> sadapay | F6: easypaisa | G6: jazzcash | H6: nayapay
D7: {=_xlfn.UNIQUE(IMAGERY[IMAGERY])} -> Best app interface and user experience (UX) | E7: =COUNTIFS(IMAGERY_Data!$B$2:$B$1190,Imagery_Analysis!$D7,IMAGERY_Data!$C$2:$C$1190,Imagery_Analysis!E$6) -> 16 | F7: =COUNTIFS(IMAGERY_Data!$B$2:$B$1190,Imagery_Analysis!$D7,IMAGERY_Data!$C$2:$C$1190,Imagery_Analysis!F$6) -> 44 | G7: =COUNTIFS(IMAGERY_Data!$B$2:$B$1190,Imagery_Analysis!$D7,IMAGERY_Data!$C$2:$C$1190,Imagery_Analysis!G$6) -> 66 | H7: =COUNTIFS(IMAGERY_Data!$B$2:$B$1190,Imagery_Analysis!$D7,IMAGERY_Data!$C$2:$C$1190,Imagery_Analysis!H$6) -> 24
D8: Most reliable (least likely to have server/network down issues) | E8: =COUNTIFS(IMAGERY_Data!$B$2:$B$1190,Imagery_Analysis!$D8,IMAGERY_Data!$C$2:$C$1190,Imagery_Analysis!E$6) -> 20 | F8: =COUNTIFS(IMAGERY_Data!$B$2:$B$1190,Imagery_Analysis!$D8,IMAGERY_Data!$C$2:$C$1190,Imagery_Analysis!F$6) -> 48 | G8: =COUNTIFS(IMAGERY_Data!$B$2:$B$1190,Imagery_Analysis!$D8,IMAGERY_Data!$C$2:$C$1190,Imagery_Analysis!G$6) -> 62 | H8: =COUNTIFS(IMAGERY_Data!$B$2:$B$1190,Imagery_Analysis!$D8,IMAGERY_Data!$C$2:$C$1190,Imagery_Analysis!H$6) -> 19
D9: Offers the best discounts, deals, and cashbacks | E9: =COUNTIFS(IMAGERY_Data!$B$2:$B$1190,Imagery_Analysis!$D9,IMAGERY_Data!$C$2:$C$1190,Imagery_Analysis!E$6) -> 4 | F9: =COUNTIFS(IMAGERY_Data!$B$2:$B$1190,Imagery_Analysis!$D9,IMAGERY_Data!$C$2:$C$1190,Imagery_Analysis!F$6) -> 53 | G9: =COUNTIFS(IMAGERY_Data!$B$2:$B$1190,Imagery_Analysis!$D9,IMAGERY_Data!$C$2:$C$1190,Imagery_Analysis!G$6) -> 83 | H9: =COUNTIFS(IMAGERY_Data!$B$2:$B$1190,Imagery_Analysis!$D9,IMAGERY_Data!$C$2:$C$1190,Imagery_Analysis!H$6) -> 9
D10: Good customer service and quick issue resolution | E10: =COUNTIFS(IMAGERY_Data!$B$2:$B$1190,Imagery_Analysis!$D10,IMAGERY_Data!$C$2:$C$1190,Imagery_Analysis!E$6) -> 17 | F10: =COUNTIFS(IMAGERY_Data!$B$2:$B$1190,Imagery_Analysis!$D10,IMAGERY_Data!$C$2:$C$1190,Imagery_Analysis!F$6) -> 50 | G10: =COUNTIFS(IMAGERY_Data!$B$2:$B$1190,Imagery_Analysis!$D10,IMAGERY_Data!$C$2:$C$1190,Imagery_Analysis!G$6) -> 60 | H10: =COUNTIFS(IMAGERY_Data!$B$2:$B$1190,Imagery_Analysis!$D10,IMAGERY_Data!$C$2:$C$1190,Imagery_Analysis!H$6) -> 22
D11: Lowest transaction fees and free inter-bank fund transfers (IBFT) | E11: =COUNTIFS(IMAGERY_Data!$B$2:$B$1190,Imagery_Analysis!$D11,IMAGERY_Data!$C$2:$C$1190,Imagery_Analysis!E$6) -> 20 | F11: =COUNTIFS(IMAGERY_Data!$B$2:$B$1190,Imagery_Analysis!$D11,IMAGERY_Data!$C$2:$C$1190,Imagery_Analysis!F$6) -> 51 | G11: =COUNTIFS(IMAGERY_Data!$B$2:$B$1190,Imagery_Analysis!$D11,IMAGERY_Data!$C$2:$C$1190,Imagery_Analysis!G$6) -> 51 | H11: =COUNTIFS(IMAGERY_Data!$B$2:$B$1190,Imagery_Analysis!$D11,IMAGERY_Data!$C$2:$C$1190,Imagery_Analysis!H$6) -> 27
D12: Strongest security features | E12: =COUNTIFS(IMAGERY_Data!$B$2:$B$1190,Imagery_Analysis!$D12,IMAGERY_Data!$C$2:$C$1190,Imagery_Analysis!E$6) -> 14 | F12: =COUNTIFS(IMAGERY_Data!$B$2:$B$1190,Imagery_Analysis!$D12,IMAGERY_Data!$C$2:$C$1190,Imagery_Analysis!F$6) -> 44 | G12: =COUNTIFS(IMAGERY_Data!$B$2:$B$1190,Imagery_Analysis!$D12,IMAGERY_Data!$C$2:$C$1190,Imagery_Analysis!G$6) -> 69 | H12: =COUNTIFS(IMAGERY_Data!$B$2:$B$1190,Imagery_Analysis!$D12,IMAGERY_Data!$C$2:$C$1190,Imagery_Analysis!H$6) -> 22
D13: Easiest and fastest process for opening an account or ordering a physical debit card | E13: =COUNTIFS(IMAGERY_Data!$B$2:$B$1190,Imagery_Analysis!$D13,IMAGERY_Data!$C$2:$C$1190,Imagery_Analysis!E$6) -> 20 | F13: =COUNTIFS(IMAGERY_Data!$B$2:$B$1190,Imagery_Analysis!$D13,IMAGERY_Data!$C$2:$C$1190,Imagery_Analysis!F$6) -> 44 | G13: =COUNTIFS(IMAGERY_Data!$B$2:$B$1190,Imagery_Analysis!$D13,IMAGERY_Data!$C$2:$C$1190,Imagery_Analysis!G$6) -> 59 | H13: =COUNTIFS(IMAGERY_Data!$B$2:$B$1190,Imagery_Analysis!$D13,IMAGERY_Data!$C$2:$C$1190,Imagery_Analysis!H$6) -> 26
D14: Best app for international payments | E14: =COUNTIFS(IMAGERY_Data!$B$2:$B$1190,Imagery_Analysis!$D14,IMAGERY_Data!$C$2:$C$1190,Imagery_Analysis!E$6) -> 33 | F14: =COUNTIFS(IMAGERY_Data!$B$2:$B$1190,Imagery_Analysis!$D14,IMAGERY_Data!$C$2:$C$1190,Imagery_Analysis!F$6) -> 27 | G14: =COUNTIFS(IMAGERY_Data!$B$2:$B$1190,Imagery_Analysis!$D14,IMAGERY_Data!$C$2:$C$1190,Imagery_Analysis!G$6) -> 48 | H14: =COUNTIFS(IMAGERY_Data!$B$2:$B$1190,Imagery_Analysis!$D14,IMAGERY_Data!$C$2:$C$1190,Imagery_Analysis!H$6) -> 37
D18: IMAGERY | E18: {=TRANSPOSE(_xlfn.UNIQUE(IMAGERY[APP]))} -> sadapay | F18: easypaisa | G18: jazzcash | H18: nayapay
D19: {=_xlfn.UNIQUE(IMAGERY[IMAGERY])} -> Best app interface and user experience (UX) | E19: =E7/150 -> 0.10666667 | F19: =F7/150 -> 0.29333333 | G19: =G7/150 -> 0.44 | H19: =H7/150 -> 0.16
D20: Most reliable (least likely to have server/network down issues) | E20: =E8/150 -> 0.13333333 | F20: =F8/150 -> 0.32 | G20: =G8/150 -> 0.41333333 | H20: =H8/150 -> 0.12666667
D21: Offers the best discounts, deals, and cashbacks | E21: =E9/150 -> 0.026666667 | F21: =F9/150 -> 0.35333333 | G21: =G9/150 -> 0.55333333 | H21: =H9/150 -> 0.06
D22: Good customer service and quick issue resolution | E22: =E10/150 -> 0.11333333 | F22: =F10/150 -> 0.33333333 | G22: =G10/150 -> 0.4 | H22: =H10/150 -> 0.14666667
D23: Lowest transaction fees and free inter-bank fund transfers (IBFT) | E23: =E11/150 -> 0.13333333 | F23: =F11/150 -> 0.34 | G23: =G11/150 -> 0.34 | H23: =H11/150 -> 0.18
D24: Strongest security features | E24: =E12/150 -> 0.093333333 | F24: =F12/150 -> 0.29333333 | G24: =G12/150 -> 0.46 | H24: =H12/150 -> 0.14666667
D25: Easiest and fastest process for opening an account or ordering a physical debit card | E25: =E13/150 -> 0.13333333 | F25: =F13/150 -> 0.29333333 | G25: =G13/150 -> 0.39333333 | H25: =H13/150 -> 0.17333333
D26: Best app for international payments | E26: =E14/150 -> 0.22 | F26: =F14/150 -> 0.18 | G26: =G14/150 -> 0.32 | H26: =H14/150 -> 0.24666667

Sheet Sheet1
A1: previous app | C1: Favorite App
C3: easypaisa | D3: sadapay | E3: nayapay | F3: jazzcash
B4: easypaisa | D4: =COUNTIFS($I$2:$I$151,$F4,$G$2:$G$151,D$249) -> 7 | E4: =COUNTIFS($I$2:$I$151,$F4,$G$2:$G$151,E$249) -> 7 | F4: =COUNTIFS($I$2:$I$151,$F4,$G$2:$G$151,F$249) -> 26
B5: sadapay | C5: =COUNTIFS($I$2:$I$151,$F5,$G$2:$G$151,C$249) -> 4 | E5: =COUNTIFS($I$2:$I$151,$F5,$G$2:$G$151,E$249) -> 2 | F5: =COUNTIFS($I$2:$I$151,$F5,$G$2:$G$151,F$249) -> 3
B6: nayapay | C6: =COUNTIFS($I$2:$I$151,$F6,$G$2:$G$151,C$249) -> 4 | D6: =COUNTIFS($I$2:$I$151,$F6,$G$2:$G$151,D$249) -> 0 | F6: =COUNTIFS($I$2:$I$151,$F6,$G$2:$G$151,F$249) -> 5
B7: jazzcash | C7: =COUNTIFS($I$2:$I$151,$F7,$G$2:$G$151,C$249) -> 0 | D7: =COUNTIFS($I$2:$I$151,$F7,$G$2:$G$151,D$249) -> 0 | E7: =COUNTIFS($I$2:$I$151,$F7,$G$2:$G$151,E$249) -> 0

Sheet NPS
D6: NPS | E6: {=TRANSPOSE(_xlfn.UNIQUE(SINGLE_RESPONSES[FAVORITE]))} -> easypaisa | F6: sadapay | G6: nayapay | H6: jazzcash
D7: 0 | E7: =COUNTIFS(SINGLE_RESPONSES[FAVORITE],NPS!E$6,SINGLE_RESPONSES[NPS],NPS!$D7) -> 0 | F7: =COUNTIFS(SINGLE_RESPONSES[FAVORITE],NPS!F$6,SINGLE_RESPONSES[NPS],NPS!$D7) -> 0 | G7: =COUNTIFS(SINGLE_RESPONSES[FAVORITE],NPS!G$6,SINGLE_RESPONSES[NPS],NPS!$D7) -> 0 | H7: =COUNTIFS(SINGLE_RESPONSES[FAVORITE],NPS!H$6,SINGLE_RESPONSES[NPS],NPS!$D7) -> 0
D8: 1 | E8: =COUNTIFS(SINGLE_RESPONSES[FAVORITE],NPS!E$6,SINGLE_RESPONSES[NPS],NPS!$D8) -> 1 | F8: =COUNTIFS(SINGLE_RESPONSES[FAVORITE],NPS!F$6,SINGLE_RESPONSES[NPS],NPS!$D8) -> 1 | G8: =COUNTIFS(SINGLE_RESPONSES[FAVORITE],NPS!G$6,SINGLE_RESPONSES[NPS],NPS!$D8) -> 1 | H8: =COUNTIFS(SINGLE_RESPONSES[FAVORITE],NPS!H$6,SINGLE_RESPONSES[NPS],NPS!$D8) -> 5
D9: 2 | E9: =COUNTIFS(SINGLE_RESPONSES[FAVORITE],NPS!E$6,SINGLE_RESPONSES[NPS],NPS!$D9) -> 0 | F9: =COUNTIFS(SINGLE_RESPONSES[FAVORITE],NPS!F$6,SINGLE_RESPONSES[NPS],NPS!$D9) -> 1 | G9: =COUNTIFS(SINGLE_RESPONSES[FAVORITE],NPS!G$6,SINGLE_RESPONSES[NPS],NPS!$D9) -> 0 | H9: =COUNTIFS(SINGLE_RESPONSES[FAVORITE],NPS!H$6,SINGLE_RESPONSES[NPS],NPS!$D9) -> 1
D10: 3 | E10: =COUNTIFS(SINGLE_RESPONSES[FAVORITE],NPS!E$6,SINGLE_RESPONSES[NPS],NPS!$D10) -> 2 | F10: =COUNTIFS(SINGLE_RESPONSES[FAVORITE],NPS!F$6,SINGLE_RESPONSES[NPS],NPS!$D10) -> 1 | G10: =COUNTIFS(SINGLE_RESPONSES[FAVORITE],NPS!G$6,SINGLE_RESPONSES[NPS],NPS!$D10) -> 0 | H10: =COUNTIFS(SINGLE_RESPONSES[FAVORITE],NPS!H$6,SINGLE_RESPONSES[NPS],NPS!$D10) -> 2
D11: 4 | E11: =COUNTIFS(SINGLE_RESPONSES[FAVORITE],NPS!E$6,SINGLE_RESPONSES[NPS],NPS!$D11) -> 1 | F11: =COUNTIFS(SINGLE_RESPONSES[FAVORITE],NPS!F$6,SINGLE_RESPONSES[NPS],NPS!$D11) -> 0 | G11: =COUNTIFS(SINGLE_RESPONSES[FAVORITE],NPS!G$6,SINGLE_RESPONSES[NPS],NPS!$D11) -> 0 | H11: =COUNTIFS(SINGLE_RESPONSES[FAVORITE],NPS!H$6,SINGLE_RESPONSES[NPS],NPS!$D11) -> 3
D12: 5 | E12: =COUNTIFS(SINGLE_RESPONSES[FAVORITE],NPS!E$6,SINGLE_RESPONSES[NPS],NPS!$D12) -> 0 | F12: =COUNTIFS(SINGLE_RESPONSES[FAVORITE],NPS!F$6,SINGLE_RESPONSES[NPS],NPS!$D12) -> 1 | G12: =COUNTIFS(SINGLE_RESPONSES[FAVORITE],NPS!G$6,SINGLE_RESPONSES[NPS],NPS!$D12) -> 1 | H12: =COUNTIFS(SINGLE_RESPONSES[FAVORITE],NPS!H$6,SINGLE_RESPONSES[NPS],NPS!$D12) -> 5
D13: 6 | E13: =COUNTIFS(SINGLE_RESPONSES[FAVORITE],NPS!E$6,SINGLE_RESPONSES[NPS],NPS!$D13) -> 1 | F13: =COUNTIFS(SINGLE_RESPONSES[FAVORITE],NPS!F$6,SINGLE_RESPONSES[NPS],NPS!$D13) -> 2 | G13: =COUNTIFS(SINGLE_RESPONSES[FAVORITE],NPS!G$6,SINGLE_RESPONSES[NPS],NPS!$D13) -> 0 | H13: =COUNTIFS(SINGLE_RESPONSES[FAVORITE],NPS!H$6,SINGLE_RESPONSES[NPS],NPS!$D13) -> 3
D14: 7 | E14: =COUNTIFS(SINGLE_RESPONSES[FAVORITE],NPS!E$6,SINGLE_RESPONSES[NPS],NPS!$D14) -> 6 | F14: =COUNTIFS(SINGLE_RESPONSES[FAVORITE],NPS!F$6,SINGLE_RESPONSES[NPS],NPS!$D14) -> 1 | G14: =COUNTIFS(SINGLE_RESPONSES[FAVORITE],NPS!G$6,SINGLE_RESPONSES[NPS],NPS!$D14) -> 4 | H14: =COUNTIFS(SINGLE_RESPONSES[FAVORITE],NPS!H$6,SINGLE_RESPONSES[NPS],NPS!$D14) -> 7
D15: 8 | E15: =COUNTIFS(SINGLE_RESPONSES[FAVORITE],NPS!E$6,SINGLE_RESPONSES[NPS],NPS!$D15) -> 12 | F15: =COUNTIFS(SINGLE_RESPONSES[FAVORITE],NPS!F$6,SINGLE_RESPONSES[NPS],NPS!$D15) -> 4 | G15: =COUNTIFS(SINGLE_RESPONSES[FAVORITE],NPS!G$6,SINGLE_RESPONSES[NPS],NPS!$D15) -> 2 | H15: =COUNTIFS(SINGLE_RESPONSES[FAVORITE],NPS!H$6,SINGLE_RESPONSES[NPS],NPS!$D15) -> 14
D16: 9 | E16: =COUNTIFS(SINGLE_RESPONSES[FAVORITE],NPS!E$6,SINGLE_RESPONSES[NPS],NPS!$D16) -> 9 | F16: =COUNTIFS(SINGLE_RESPONSES[FAVORITE],NPS!F$6,SINGLE_RESPONSES[NPS],NPS!$D16) -> 3 | G16: =COUNTIFS(SINGLE_RESPONSES[FAVORITE],NPS!G$6,SINGLE_RESPONSES[NPS],NPS!$D16) -> 3 | H16: =COUNTIFS(SINGLE_RESPONSES[FAVORITE],NPS!H$6,SINGLE_RESPONSES[NPS],NPS!$D16) -> 6
D17: 10 | E17: =COUNTIFS(SINGLE_RESPONSES[FAVORITE],NPS!E$6,SINGLE_RESPONSES[NPS],NPS!$D17) -> 11 | F17: =COUNTIFS(SINGLE_RESPONSES[FAVORITE],NPS!F$6,SINGLE_RESPONSES[NPS],NPS!$D17) -> 4 | G17: =COUNTIFS(SINGLE_RESPONSES[FAVORITE],NPS!G$6,SINGLE_RESPONSES[NPS],NPS!$D17) -> 13 | H17: =COUNTIFS(SINGLE_RESPONSES[FAVORITE],NPS!H$6,SINGLE_RESPONSES[NPS],NPS!$D17) -> 19
E18: =SUM(E7:E17) -> 43 | F18: =SUM(F7:F17) -> 18 | G18: =SUM(G7:G17) -> 24 | H18: =SUM(H7:H17) -> 65
D21: Detractors | E21: =SUM(E7:E12) -> 4 | F21: =SUM(F7:F12) -> 4 | G21: =SUM(G7:G12) -> 2 | H21: =SUM(H7:H12) -> 16
D22: Neutral | E22: =E13+E14 -> 7 | F22: =F13+F14 -> 3 | G22: =G13+G14 -> 4 | H22: =H13+H14 -> 10
D23: Promoters | E23: =SUM(E15:E17) -> 32 | F23: =SUM(F15:F17) -> 11 | G23: =SUM(G15:G17) -> 18 | H23: =SUM(H15:H17) -> 39
D27: NPS | E27: =E23-E21 -> 28 | F27: =F23-F21 -> 7 | G27: =G23-G21 -> 16 | H27: =H23-H21 -> 23
E28: =E27/150 -> 0.18666667 | F28: =F27/150 -> 0.046666667 | G28: =G27/150 -> 0.10666667 | H28: =H27/150 -> 0.15333333

Sheet Analysis for alternate apps
A3: Count of Alternate App | B3: Column Labels
A4: Row Labels | B4: bank app | C4: easypaisa | D4: jazzcash | E4: nayapay | F4: none | G4: sadapay | H4: Grand Total
A5: easypaisa | B5: 4 | C5: 6 | D5: 15 | E5: 7 | G5: 11 | H5: 43
A6: jazzcash | B6: 11 | C6: 27 | D6: 8 | E6: 13 | F6: 1 | G6: 5 | H6: 65
A7: nayapay | B7: 6 | C7: 6 | D7: 7 | E7: 3 | G7: 2 | H7: 24
A8: sadapay | B8: 3 | C8: 4 | D8: 7 | E8: 3 | F8: 1 | H8: 18
A9: Grand Total | B9: 24 | C9: 43 | D9: 37 | E9: 26 | F9: 2 | G9: 18 | H9: 150
B10: Alternate App
A11: Favorite App | B11: bank app | C11: easypaisa | D11: jazzcash | E11: nayapay | F11: none | G11: sadapay
A12: easypaisa | B12: 4 | D12: 15 | E12: 7 | F12: 0 | G12: 11
A13: jazzcash | B13: 11 | C13: 27 | E13: 13 | F13: 1 | G13: 5
A14: nayapay | B14: 6 | C14: 6 | D14: 7 | G14: 2
A15: sadapay | B15: 3 | C15: 4 | D15: 7 | E15: 3 | F15: 1
A16: Grand total | B16: 24 | C16: 43 | D16: 30 | E16: 23 | F16: 2 | G16: 16

Sheet CURRENT USAGE_Data
A1: Index | B1: APP
A2: 1 | B2: easypaisa
A3: 2 | B3: easypaisa
A4: 3 | B4: sadapay
A5: 4 | B5: easypaisa
A6: 5 | B6: easypaisa
A7: 6 | B7: easypaisa
A8: 7 | B8: jazzcash
A9: 8 | B9: easypaisa
A10: 9 | B10: jazzcash
A11: 10 | B11: nayapay
A12: 11 | B12: jazzcash
A13: 12 | B13: jazzcash
... A255: 254 | B255: nayapay

Sheet Awareness_data
A1: Application(Awareness) | B1: Value
A2: jazzcash | B2: 1
A3: easypaisa | B3: 1
A4: sadapay | B4: 1
A5: easypaisa | B5: 1
A6: sadapay | B6: 1
A7: jazzcash | B7: 1
A8: easypaisa | B8: 1
A9: nayapay | B9: 1
A10: jazzcash | B10: 1
A11: easypaisa | B11: 1
A12: sadapay | B12: 1
A13: nayapay | B13: 1
... A331: nayapay | B331: 1

Sheet Engineered_Awareness_data
D1: TOM | E1: EVER USED | F1: CURRENT USAGE | G1: jazzcash | H1: easypaisa | I1: sadapay | J1: nayapay
D2: easypaisa | E2: jazzcash,easypaisa,sadapay | F2: easypaisa | G2: =IF(OR(ISNUMBER(SEARCH("jazzcash", D2)), ISNUMBER(SEARCH("jazzcash", E2)), ISNUMBER(SEARCH("jazzcash", F2))), 1, 0) -> 1 | H2: =IF(OR(ISNUMBER(SEARCH("easypaisa", D2)), ISNUMBER(SEARCH("easypaisa", E2)), ISNUMBER(SEARCH("easypaisa", F2))), 1, 0) -> 1 | I2: =IF(OR(ISNUMBER(SEARCH("sadapay", D2)), ISNUMBER(SEARCH("sadapay", E2)), ISNUMBER(SEARCH("sadapay", F2))), 1, 0) -> 1 | J2: =IF(OR(ISNUMBER(SEARCH("nayapay", D2)), ISNUMBER(SEARCH("nayapay", E2)), ISNUMBER(SEARCH("nayapay", F2))), 1, 0) -> 0
D3: easypaisa | E3: easypaisa | F3: easypaisa | G3: =IF(OR(ISNUMBER(SEARCH("jazzcash", D3)), ISNUMBER(SEARCH("jazzcash", E3)), ISNUMBER(SEARCH("jazzcash", F3))), 1, 0) -> 0 | H3: =IF(OR(ISNUMBER(SEARCH("easypaisa", D3)), ISNUMBER(SEARCH("easypaisa", E3)), ISNUMBER(SEARCH("easypaisa", F3))), 1, 0) -> 1 | I3: =IF(OR(ISNUMBER(SEARCH("sadapay", D3)), ISNUMBER(SEARCH("sadapay", E3)), ISNUMBER(SEARCH("sadapay", F3))), 1, 0) -> 0 | J3: =IF(OR(ISNUMBER(SEARCH("nayapay", D3)), ISNUMBER(SEARCH("nayapay", E3)), ISNUMBER(SEARCH("nayapay", F3))), 1, 0) -> 0
D4: sadapay | E4: sadapay | F4: sadapay | G4: =IF(OR(ISNUMBER(SEARCH("jazzcash", D4)), ISNUMBER(SEARCH("jazzcash", E4)), ISNUMBER(SEARCH("jazzcash", F4))), 1, 0) -> 0 | H4: =IF(OR(ISNUMBER(SEARCH("easypaisa", D4)), ISNUMBER(SEARCH("easypaisa", E4)), ISNUMBER(SEARCH("easypaisa", F4))), 1, 0) -> 0 | I4: =IF(OR(ISNUMBER(SEARCH("sadapay", D4)), ISNUMBER(SEARCH("sadapay", E4)), ISNUMBER(SEARCH("sadapay", F4))), 1, 0) -> 1 | J4: =IF(OR(ISNUMBER(SEARCH("nayapay", D4)), ISNUMBER(SEARCH("nayapay", E4)), ISNUMBER(SEARCH("nayapay", F4))), 1, 0) -> 0
D5: easypaisa | E5: jazzcash,easypaisa,nayapay | F5: easypaisa | G5: =IF(OR(ISNUMBER(SEARCH("jazzcash", D5)), ISNUMBER(SEARCH("jazzcash", E5)), ISNUMBER(SEARCH("jazzcash", F5))), 1, 0) -> 1 | H5: =IF(OR(ISNUMBER(SEARCH("easypaisa", D5)), ISNUMBER(SEARCH("easypaisa", E5)), ISNUMBER(SEARCH("easypaisa", F5))), 1, 0) -> 1 | I5: =IF(OR(ISNUMBER(SEARCH("sadapay", D5)), ISNUMBER(SEARCH("sadapay", E5)), ISNUMBER(SEARCH("sadapay", F5))), 1, 0) -> 0 | J5: =IF(OR(ISNUMBER(SEARCH("nayapay", D5)), ISNUMBER(SEARCH("nayapay", E5)), ISNUMBER(SEARCH("nayapay", F5))), 1, 0) -> 1
D6: easypaisa | E6: jazzcash,easypaisa,sadapay,nayapay | F6: easypaisa | G6: =IF(OR(ISNUMBER(SEARCH("jazzcash", D6)), ISNUMBER(SEARCH("jazzcash", E6)), ISNUMBER(SEARCH("jazzcash", F6))), 1, 0) -> 1 | H6: =IF(OR(ISNUMBER(SEARCH("easypaisa", D6)), ISNUMBER(SEARCH("easypaisa", E6)), ISNUMBER(SEARCH("easypaisa", F6))), 1, 0) -> 1 | I6: =IF(OR(ISNUMBER(SEARCH("sadapay", D6)), ISNUMBER(SEARCH("sadapay", E6)), ISNUMBER(SEARCH("sadapay", F6))), 1, 0) -> 1 | J6: =IF(OR(ISNUMBER(SEARCH("nayapay", D6)), ISNUMBER(SEARCH("nayapay", E6)), ISNUMBER(SEARCH("nayapay", F6))), 1, 0) -> 1
D7: jazzcash | E7: easypaisa | F7: easypaisa | G7: =IF(OR(ISNUMBER(SEARCH("jazzcash", D7)), ISNUMBER(SEARCH("jazzcash", E7)), ISNUMBER(SEARCH("jazzcash", F7))), 1, 0) -> 1 | H7: =IF(OR(ISNUMBER(SEARCH("easypaisa", D7)), ISNUMBER(SEARCH("easypaisa", E7)), ISNUMBER(SEARCH("easypaisa", F7))), 1, 0) -> 1 | I7: =IF(OR(ISNUMBER(SEARCH("sadapay", D7)), ISNUMBER(SEARCH("sadapay", E7)), ISNUMBER(SEARCH("sadapay", F7))), 1, 0) -> 0 | J7: =IF(OR(ISNUMBER(SEARCH("nayapay", D7)), ISNUMBER(SEARCH("nayapay", E7)), ISNUMBER(SEARCH("nayapay", F7))), 1, 0) -> 0
D8: easypaisa | E8: easypaisa | F8: jazzcash,easypaisa | G8: =IF(OR(ISNUMBER(SEARCH("jazzcash", D8)), ISNUMBER(SEARCH("jazzcash", E8)), ISNUMBER(SEARCH("jazzcash", F8))), 1, 0) -> 1 | H8: =IF(OR(ISNUMBER(SEARCH("easypaisa", D8)), ISNUMBER(SEARCH("easypaisa", E8)), ISNUMBER(SEARCH("easypaisa", F8))), 1, 0) -> 1 | I8: =IF(OR(ISNUMBER(SEARCH("sadapay", D8)), ISNUMBER(SEARCH("sadapay", E8)), ISNUMBER(SEARCH("sadapay", F8))), 1, 0) -> 0 | J8: =IF(OR(ISNUMBER(SEARCH("nayapay", D8)), ISNUMBER(SEARCH("nayapay", E8)), ISNUMBER(SEARCH("nayapay", F8))), 1, 0) -> 0
D9: nayapay | E9: jazzcash,sadapay,nayapay | F9: jazzcash,nayapay | G9: =IF(OR(ISNUMBER(SEARCH("jazzcash", D9)), ISNUMBER(SEARCH("jazzcash", E9)), ISNUMBER(SEARCH("jazzcash", F9))), 1, 0) -> 1 | H9: =IF(OR(ISNUMBER(SEARCH("easypaisa", D9)), ISNUMBER(SEARCH("easypaisa", E9)), ISNUMBER(SEARCH("easypaisa", F9))), 1, 0) -> 0 | I9: =IF(OR(ISNUMBER(SEARCH("sadapay", D9)), ISNUMBER(SEARCH("sadapay", E9)), ISNUMBER(SEARCH("sadapay", F9))), 1, 0) -> 1 | J9: =IF(OR(ISNUMBER(SEARCH("nayapay", D9)), ISNUMBER(SEARCH("nayapay", E9)), ISNUMBER(SEARCH("nayapay", F9))), 1, 0) -> 1
D10: jazzcash | E10: jazzcash,sadapay | F10: jazzcash | G10: =IF(OR(ISNUMBER(SEARCH("jazzcash", D10)), ISNUMBER(SEARCH("jazzcash", E10)), ISNUMBER(SEARCH("jazzcash", F10))), 1, 0) -> 1 | H10: =IF(OR(ISNUMBER(SEARCH("easypaisa", D10)), ISNUMBER(SEARCH("easypaisa", E10)), ISNUMBER(SEARCH("easypaisa", F10))), 1, 0) -> 0 | I10: =IF(OR(ISNUMBER(SEARCH("sadapay", D10)), ISNUMBER(SEARCH("sadapay", E10)), ISNUMBER(SEARCH("sadapay", F10))), 1, 0) -> 1 | J10: =IF(OR(ISNUMBER(SEARCH("nayapay", D10)), ISNUMBER(SEARCH("nayapay", E10)), ISNUMBER(SEARCH("nayapay", F10))), 1, 0) -> 0
D11: sadapay | E11: sadapay | F11: jazzcash,easypaisa,sadapay | G11: =IF(OR(ISNUMBER(SEARCH("jazzcash", D11)), ISNUMBER(SEARCH("jazzcash", E11)), ISNUMBER(SEARCH("jazzcash", F11))), 1, 0) -> 1 | H11: =IF(OR(ISNUMBER(SEARCH("easypaisa", D11)), ISNUMBER(SEARCH("easypaisa", E11)), ISNUMBER(SEARCH("easypaisa", F11))), 1, 0) -> 1 | I11: =IF(OR(ISNUMBER(SEARCH("sadapay", D11)), ISNUMBER(SEARCH("sadapay", E11)), ISNUMBER(SEARCH("sadapay", F11))), 1, 0) -> 1 | J11: =IF(OR(ISNUMBER(SEARCH("nayapay", D11)), ISNUMBER(SEARCH("nayapay", E11)), ISNUMBER(SEARCH("nayapay", F11))), 1, 0) -> 0
D12: jazzcash | E12: jazzcash,nayapay | F12: jazzcash,nayapay | G12: =IF(OR(ISNUMBER(SEARCH("jazzcash", D12)), ISNUMBER(SEARCH("jazzcash", E12)), ISNUMBER(SEARCH("jazzcash", F12))), 1, 0) -> 1 | H12: =IF(OR(ISNUMBER(SEARCH("easypaisa", D12)), ISNUMBER(SEARCH("easypaisa", E12)), ISNUMBER(SEARCH("easypaisa", F12))), 1, 0) -> 0 | I12: =IF(OR(ISNUMBER(SEARCH("sadapay", D12)), ISNUMBER(SEARCH("sadapay", E12)), ISNUMBER(SEARCH("sadapay", F12))), 1, 0) -> 0 | J12: =IF(OR(ISNUMBER(SEARCH("nayapay", D12)), ISNUMBER(SEARCH("nayapay", E12)), ISNUMBER(SEARCH("nayapay", F12))), 1, 0) -> 1
D13: jazzcash | E13: jazzcash,easypaisa,sadapay,nayapay | F13: easypaisa | G13: =IF(OR(ISNUMBER(SEARCH("jazzcash", D13)), ISNUMBER(SEARCH("jazzcash", E13)), ISNUMBER(SEARCH("jazzcash", F13))), 1, 0) -> 1 | H13: =IF(OR(ISNUMBER(SEARCH("easypaisa", D13)), ISNUMBER(SEARCH("easypaisa", E13)), ISNUMBER(SEARCH("easypaisa", F13))), 1, 0) -> 1 | I13: =IF(OR(ISNUMBER(SEARCH("sadapay", D13)), ISNUMBER(SEARCH("sadapay", E13)), ISNUMBER(SEARCH("sadapay", F13))), 1, 0) -> 1 | J13: =IF(OR(ISNUMBER(SEARCH("nayapay", D13)), ISNUMBER(SEARCH("nayapay", E13)), ISNUMBER(SEARCH("nayapay", F13))), 1, 0) -> 1
... D151: jazzcash | E151: jazzcash,easypaisa,sadapay,nayapay | F151: jazzcash,sadapay,nayapay | G151: =IF(OR(ISNUMBER(SEARCH("jazzcash", D151)), ISNUMBER(SEARCH("jazzcash", E151)), ISNUMBER(SEARCH("jazzcash", F151))), 1, 0) -> 1 | H151: =IF(OR(ISNUMBER(SEARCH("easypaisa", D151)), ISNUMBER(SEARCH("easypaisa", E151)), ISNUMBER(SEARCH("easypaisa", F151))), 1, 0) -> 1 | I151: =IF(OR(ISNUMBER(SEARCH("sadapay", D151)), ISNUMBER(SEARCH("sadapay", E151)), ISNUMBER(SEARCH("sadapay", F151))), 1, 0) -> 1 | J151: =IF(OR(ISNUMBER(SEARCH("nayapay", D151)), ISNUMBER(SEARCH("nayapay", E151)), ISNUMBER(SEARCH("nayapay", F151))), 1, 0) -> 1
G152: =SUM(G2:G151) -> 114 | H152: =SUM(H2:H151) -> 100 | I152: =SUM(I2:I151) -> 61 | J152: =SUM(J2:J151) -> 55
G154: =G152/150 -> 0.76 | H154: =H152/150 -> 0.66666667 | I154: =I152/150 -> 0.40666667 | J154: =J152/150 -> 0.36666667

Sheet EVER USED_Data
A1: Index | B1: APP
A2: 1 | B2: jazzcash
A3: 2 | B3: easypaisa
A4: 3 | B4: sadapay
A5: 4 | B5: easypaisa
A6: 5 | B6: sadapay
A7: 6 | B7: jazzcash
A8: 7 | B8: easypaisa
A9: 8 | B9: nayapay
A10: 9 | B10: jazzcash
A11: 10 | B11: easypaisa
A12: 11 | B12: sadapay
A13: 12 | B13: nayapay
... A299: 298 | B299: nayapay

Sheet IMAGERY_Data
A1: Index | B1: IMAGERY | C1: APP
A2: 1 | B2: Best app interface and user experience (UX) | C2: sadapay
A3: 1 | B3: Most reliable (least likely to have server/network down issues) | C3: easypaisa
A4: 1 | B4: Offers the best discounts, deals, and cashbacks | C4: jazzcash
A5: 1 | B5: Good customer service and quick issue resolution | C5: sadapay
A6: 1 | B6: Lowest transaction fees and free inter-bank fund transfers (IBFT) | C6: easypaisa
A7: 1 | B7: Strongest security features | C7: easypaisa
A8: 1 | B8: Easiest and fastest process for opening an account or ordering a physical debit card | C8: easypaisa
A9: 1 | B9: Best app for international payments | C9: easypaisa
A10: 2 | B10: Best app interface and user experience (UX) | C10: easypaisa
A11: 2 | B11: Most reliable (least likely to have server/network down issues) | C11: easypaisa
A12: 2 | B12: Offers the best discounts, deals, and cashbacks | C12: easypaisa
A13: 2 | B13: Good customer service and quick issue resolution | C13: easypaisa
... A1197: 150 | B1197: Best app for international payments | C1197: nayapay

Sheet SINGLE_RESPONSES
A1: Name | B1: Gender | C1: Age | D1: coding | E1: City | F1: TOM | G1: FAVORITE | H1: Using since | I1: Previous Brand | J1: Reasons for switching | K1: Future intent | L1: Reasons for keep using | M1: NPS | N1: Alternate App | O1: 5.1) Have you seen the advertisement above on TV recently or not? | P1: 5.2 ) What digital payment app was this ad for? | Q1: 5.3) In your own words, what was the main message of this ad? (Please be specific; avoid general answers like 'it is a good app.' | R1: 5.4) To what extent did you like this ad?
A2: Gulfam | B2: Male | C2: 30 - 41 | D2: {=_xlfn.IFS(SINGLE_RESPONSES[[#This Row],[Age]]="18 - 29",1, SINGLE_RESPONSES[[#This Row],[Age]]="30 - 41",2,SINGLE_RESPONSES[[#This Row],[Age]]="42 -53",3, SINGLE_RESPONSES[[#This Row],[Age]]="54 - 65",4, SINGLE_RESPONSES[[#This Row],[Age]]="66 and above",5)} -> 2 | E2: Lahore | F2: easypaisa | G2: easypaisa | H2: 6 | I2: sadapay | J2: account blockage and trust issues | K2: Yes | L2: easier to manage small transactions and payments like payment of bills etc | M2: 9 | N2: jazzcash | O2: No | P2: easypaisa | Q2: have not seen this ad | R2: 1
A3: waleed | B3: Male | C3: 18 - 29 | D3: {=_xlfn.IFS(SINGLE_RESPONSES[[#This Row],[Age]]="18 - 29",1, SINGLE_RESPONSES[[#This Row],[Age]]="30 - 41",2,SINGLE_RESPONSES[[#This Row],[Age]]="42 -53",3, SINGLE_RESPONSES[[#This Row],[Age]]="54 - 65",4, SINGLE_RESPONSES[[#This Row],[Age]]="66 and above",5)} -> 1 | E3: Lahore | F3: easypaisa | G3: easypaisa | H3: 4 | I3: easypaisa | J3: Not switched | K3: Yes | L3: Best user interface and user experience | M3: 9 | N3: bankingapp | O3: Yes | P3: easypaisa | Q3: You can transfer money from anywhere in your easy paisa account and it'll be transferred in your account immediately without any disruption | R3: 5
A4: Talha | B4: Male | C4: 18 - 29 | D4: {=_xlfn.IFS(SINGLE_RESPONSES[[#This Row],[Age]]="18 - 29",1, SINGLE_RESPONSES[[#This Row],[Age]]="30 - 41",2,SINGLE_RESPONSES[[#This Row],[Age]]="42 -53",3, SINGLE_RESPONSES[[#This Row],[Age]]="54 - 65",4, SINGLE_RESPONSES[[#This Row],[Age]]="66 and above",5)} -> 1 | E4: Lahore | F4: sadapay | G4: sadapay | H4: 4 | I4: easypaisa | J4: Easy to assess | K4: Yes | L4: Easy to assess | M4: 10 | N4: bankingapp | O4: Yes | P4: easypaisa | Q4: Easy to transfer | R4: 10
A5: Jawad Waseem | B5: Male | C5: 18 - 29 | D5: {=_xlfn.IFS(SINGLE_RESPONSES[[#This Row],[Age]]="18 - 29",1, SINGLE_RESPONSES[[#This Row],[Age]]="30 - 41",2,SINGLE_RESPONSES[[#This Row],[Age]]="42 -53",3, SINGLE_RESPONSES[[#This Row],[Age]]="54 - 65",4, SINGLE_RESPONSES[[#This Row],[Age]]="66 and above",5)} -> 1 | E5: Lahore | F5: easypaisa | G5: easypaisa | H5: 7 | I5: nayapay | J5: More options | K5: Yes | L5: Connectivity and | M5: 7 | N5: nayapay | O5: Yes | P5: easypaisa | Q5: Easy transfer | R5: 5
A6: Abdullah | B6: Male | C6: 18 - 29 | D6: {=_xlfn.IFS(SINGLE_RESPONSES[[#This Row],[Age]]="18 - 29",1, SINGLE_RESPONSES[[#This Row],[Age]]="30 - 41",2,SINGLE_RESPONSES[[#This Row],[Age]]="42 -53",3, SINGLE_RESPONSES[[#This Row],[Age]]="54 - 65",4, SINGLE_RESPONSES[[#This Row],[Age]]="66 and above",5)} -> 1 | E6: Lahore | F6: easypaisa | G6: easypaisa | H6: 6 | I6: jazzcash | J6: Bad service | K6: Yes | L6: Fast service | M6: 8 | N6: jazzcash | O6: Yes | P6: easypaisa | Q6: Make digital wallet for small transactions | R6: 7
A7: Muhammad saad ahmad | B7: Male | C7: 18 - 29 | D7: {=_xlfn.IFS(SINGLE_RESPONSES[[#This Row],[Age]]="18 - 29",1, SINGLE_RESPONSES[[#This Row],[Age]]="30 - 41",2,SINGLE_RESPONSES[[#This Row],[Age]]="42 -53",3, SINGLE_RESPONSES[[#This Row],[Age]]="54 - 65",4, SINGLE_RESPONSES[[#This Row],[Age]]="66 and above",5)} -> 1 | E7: Lahore | F7: jazzcash | G7: easypaisa | H7: 5 | I7: nayapay | J7: Wasn't reliable | K7: Yes | L7: Easy to use | M7: 9 | N7: nayapay | O7: No | P7: i have not seen this ad | Q7: That the transfer of money can be made remotely and easily | R7: 10
A8: Mubashir hassan | B8: Male | C8: 18 - 29 | D8: {=_xlfn.IFS(SINGLE_RESPONSES[[#This Row],[Age]]="18 - 29",1, SINGLE_RESPONSES[[#This Row],[Age]]="30 - 41",2,SINGLE_RESPONSES[[#This Row],[Age]]="42 -53",3, SINGLE_RESPONSES[[#This Row],[Age]]="54 - 65",4, SINGLE_RESPONSES[[#This Row],[Age]]="66 and above",5)} -> 1 | E8: Lahore | F8: easypaisa | G8: easypaisa | H8: 7 | I8: jazzcash | J8: User experience | K8: Yes | L8: User experience and user interface | M8: 7 | N8: bankingapp | O8: Yes | P8: jazzcash | Q8: They communicate. With customers... | R8: 7
A9: Ayesha | B9: Female | C9: 18 - 29 | D9: {=_xlfn.IFS(SINGLE_RESPONSES[[#This Row],[Age]]="18 - 29",1, SINGLE_RESPONSES[[#This Row],[Age]]="30 - 41",2,SINGLE_RESPONSES[[#This Row],[Age]]="42 -53",3, SINGLE_RESPONSES[[#This Row],[Age]]="54 - 65",4, SINGLE_RESPONSES[[#This Row],[Age]]="66 and above",5)} -> 1 | E9: Lahore | F9: nayapay | G9: nayapay | H9: 7 | I9: jazzcash | J9: It's secure and easy to use. | K9: Yes | L9: It's easy to use. | M9: 9 | N9: jazzcash | O9: Maybe | P9: easypaisa | Q9: Digital wallet apps awareness | R9: 10
A10: Kainat | B10: Female | C10: 18 - 29 | D10: {=_xlfn.IFS(SINGLE_RESPONSES[[#This Row],[Age]]="18 - 29",1, SINGLE_RESPONSES[[#This Row],[Age]]="30 - 41",2,SINGLE_RESPONSES[[#This Row],[Age]]="42 -53",3, SINGLE_RESPONSES[[#This Row],[Age]]="54 - 65",4, SINGLE_RESPONSES[[#This Row],[Age]]="66 and above",5)} -> 1 | E10: Lahore | F10: jazzcash | G10: jazzcash | H10: 4 | I10: jazzcash | J10: Not switched | K10: Yes | L10: Easily manageable and reliable | M10: 10 | N10: bankingapp | O10: Maybe | P10: i have not seen this ad | Q10: I haven't seen this ad | R10: 1
A11: Muhammad Danish Zafar | B11: Male | C11: 18 - 29 | D11: {=_xlfn.IFS(SINGLE_RESPONSES[[#This Row],[Age]]="18 - 29",1, SINGLE_RESPONSES[[#This Row],[Age]]="30 - 41",2,SINGLE_RESPONSES[[#This Row],[Age]]="42 -53",3, SINGLE_RESPONSES[[#This Row],[Age]]="54 - 65",4, SINGLE_RESPONSES[[#This Row],[Age]]="66 and above",5)} -> 1 | E11: Lahore | F11: sadapay | G11: sadapay | H11: 7 | I11: easypaisa | J11: Most of the time servers down | K11: Yes | L11: International transactions | M11: 8 | N11: jazzcash | O11: Maybe | P11: easypaisa | Q11: Payment transfer | R11: 5
A12: Hassan Jehangir | B12: Male | C12: 18 - 29 | D12: {=_xlfn.IFS(SINGLE_RESPONSES[[#This Row],[Age]]="18 - 29",1, SINGLE_RESPONSES[[#This Row],[Age]]="30 - 41",2,SINGLE_RESPONSES[[#This Row],[Age]]="42 -53",3, SINGLE_RESPONSES[[#This Row],[Age]]="54 - 65",4, SINGLE_RESPONSES[[#This Row],[Age]]="66 and above",5)} -> 1 | E12: Lahore | F12: jazzcash | G12: jazzcash | H12: 4 | I12: easypaisa | J12: Easy to transfer money instantly | K12: Yes | L12: Instant money transfer and good UI | M12: 10 | N12: nayapay | O12: No | P12: i have not seen this ad | Q12: No idea | R12: 1
A13: Rayyan Amin | B13: Female | C13: 18 - 29 | D13: {=_xlfn.IFS(SINGLE_RESPONSES[[#This Row],[Age]]="18 - 29",1, SINGLE_RESPONSES[[#This Row],[Age]]="30 - 41",2,SINGLE_RESPONSES[[#This Row],[Age]]="42 -53",3, SINGLE_RESPONSES[[#This Row],[Age]]="54 - 65",4, SINGLE_RESPONSES[[#This Row],[Age]]="66 and above",5)} -> 1 | E13: Lahore | F13: jazzcash | G13: easypaisa | H13: 5 | I13: jazzcash | J13: Better services | K13: Yes | L13: Easy transactions | M13: 8 | N13: sadapay | O13: No | P13: easypaisa | Q13: Cheap and easy | R13: 9
... A23: Shoaib Ahmad | B23: Male | C23: 18 - 29 | D23: {=_xlfn.IFS(SINGLE_RESPONSES[[#This Row],[Age]]="18 - 29",1, SINGLE_RESPONSES[[#This Row],[Age]]="30 - 41",2,SINGLE_RESPONSES[[#This Row],[Age]]="42 -53",3, SINGLE_RESPONSES[[#This Row],[Age]]="54 - 65",4, SINGLE_RESPONSES[[#This Row],[Age]]="66 and above",5)} -> 1 | E23: Okara | F23: easypaisa | G23: jazzcash | H23: 7 | I23: jazzcash | J23: Mostly use jazzcash | K23: Yes | L23: More preferable | M23: 10 | N23: jazzcash | O23: Maybe | P23: i have not seen this ad | Q23: Jazzcash | R23: 8
A24: DAC | B24: Male | C24: 18 - 29 | D24: {=_xlfn.IFS(SINGLE_RESPONSES[[#This Row],[Age]]="18 - 29",1, SINGLE_RESPONSES[[#This Row],[Age]]="30 - 41",2,SINGLE_RESPONSES[[#This Row],[Age]]="42 -53",3, SINGLE_RESPONSES[[#This Row],[Age]]="54 - 65",4, SINGLE_RESPONSES[[#This Row],[Age]]="66 and above",5)} -> 1 | E24: Lahore | F24: jazzcash | G24: jazzcash | H24: 7 | I24: nayapay | K24: Yes | L24: Bcz of its user friendly | M24: 10 | N24: nayapay | O24: Yes | P24: easypaisa | Q24: the convenience of online money transfer for festive gifts | R24: 7
A25: Momin Ali | B25: Male | C25: 18 - 29 | D25: {=_xlfn.IFS(SINGLE_RESPONSES[[#This Row],[Age]]="18 - 29",1, SINGLE_RESPONSES[[#This Row],[Age]]="30 - 41",2,SINGLE_RESPONSES[[#This Row],[Age]]="42 -53",3, SINGLE_RESPONSES[[#This Row],[Age]]="54 - 65",4, SINGLE_RESPONSES[[#This Row],[Age]]="66 and above",5)} -> 1 | E25: Gujrat | F25: easypaisa | G25: easypaisa | H25: 5 | I25: easypaisa | J25: Na | K25: Yes | L25: Availability | M25: 9 | N25: sadapay | P25: jazzcash | Q25: Dont remember much but i believe related to family n internet | R25: 9
A26: Iqra | B26: Female | C26: 18 - 29 | D26: {=_xlfn.IFS(SINGLE_RESPONSES[[#This Row],[Age]]="18 - 29",1, SINGLE_RESPONSES[[#This Row],[Age]]="30 - 41",2,SINGLE_RESPONSES[[#This Row],[Age]]="42 -53",3, SINGLE_RESPONSES[[#This Row],[Age]]="54 - 65",4, SINGLE_RESPONSES[[#This Row],[Age]]="66 and above",5)} -> 1 | E26: Lahore | F26: jazzcash | G26: jazzcash | H26: 7 | I26: jazzcash | J26: No change | K26: Yes | L26: It good | M26: 10 | N26: easypaisa | O26: No | P26: i have not seen this ad | Q26: No messs7 | R26: 1
A27: Amna | B27: Female | C27: 18 - 29 | D27: {=_xlfn.IFS(SINGLE_RESPONSES[[#This Row],[Age]]="18 - 29",1, SINGLE_RESPONSES[[#This Row],[Age]]="30 - 41",2,SINGLE_RESPONSES[[#This Row],[Age]]="42 -53",3, SINGLE_RESPONSES[[#This Row],[Age]]="54 - 65",4, SINGLE_RESPONSES[[#This Row],[Age]]="66 and above",5)} -> 1 | E27: Lahore | F27: jazzcash | G27: jazzcash | H27: 6 | I27: nayapay | J27: Using it for the first time. | K27: Yes | L27: Easy. | M27: 10 | N27: easypaisa | O27: Yes | P27: jazzcash | Q27: Faster money transfer | R27: 6
A28: Laiba | B28: Female | C28: 18 - 29 | D28: {=_xlfn.IFS(SINGLE_RESPONSES[[#This Row],[Age]]="18 - 29",1, SINGLE_RESPONSES[[#This Row],[Age]]="30 - 41",2,SINGLE_RESPONSES[[#This Row],[Age]]="42 -53",3, SINGLE_RESPONSES[[#This Row],[Age]]="54 - 65",4, SINGLE_RESPONSES[[#This Row],[Age]]="66 and above",5)} -> 1 | E28: Lahore | F28: jazzcash | G28: easypaisa | H28: 6 | I28: jazzcash | J28: Idk | K28: Yes | L28: Again idk, just using it. | M28: 9 | N28: jazzcash | O28: No | P28: i have not seen this ad | Q28: This should not be a required question. | R28: 1
A29: Haider shah | B29: Male | C29: 18 - 29 | D29: {=_xlfn.IFS(SINGLE_RESPONSES[[#This Row],[Age]]="18 - 29",1, SINGLE_RESPONSES[[#This Row],[Age]]="30 - 41",2,SINGLE_RESPONSES[[#This Row],[Age]]="42 -53",3, SINGLE_RESPONSES[[#This Row],[Age]]="54 - 65",4, SINGLE_RESPONSES[[#This Row],[Age]]="66 and above",5)} -> 1 | E29: Lahore | F29: easypaisa | G29: easypaisa | H29: 7 | I29: easypaisa | J29: Easypaisa is more essential | K29: Yes | L29: Its safe | M29: 4 | N29: nayapay | O29: No | P29: easypaisa | Q29: For forcing people to trust online platform | R29: 3
A30: Meerab Arshad | B30: Female | C30: 18 - 29 | D30: {=_xlfn.IFS(SINGLE_RESPONSES[[#This Row],[Age]]="18 - 29",1, SINGLE_RESPONSES[[#This Row],[Age]]="30 - 41",2,SINGLE_RESPONSES[[#This Row],[Age]]="42 -53",3, SINGLE_RESPONSES[[#This Row],[Age]]="54 - 65",4, SINGLE_RESPONSES[[#This Row],[Age]]="66 and above",5)} -> 1 | E30: Raiwind | F30: jazzcash | G30: jazzcash | H30: 2 | I30: jazzcash | J30: Jazz cash | K30: Yes | L30: Jazz cash | M30: 1 | N30: jazzcash | O30: Yes | P30: jazzcash | Q30: It's very helpful | R30: 1
A31: Muhammad Ziad Amir | B31: Male | C31: 18 - 29 | D31: {=_xlfn.IFS(SINGLE_RESPONSES[[#This Row],[Age]]="18 - 29",1, SINGLE_RESPONSES[[#This Row],[Age]]="30 - 41",2,SINGLE_RESPONSES[[#This Row],[Age]]="42 -53",3, SINGLE_RESPONSES[[#This Row],[Age]]="54 - 65",4, SINGLE_RESPONSES[[#This Row],[Age]]="66 and above",5)} -> 1 | E31: Lahore | F31: jazzcash | G31: sadapay | H31: 5 | I31: jazzcash | J31: App errors | K31: Yes | L31: Reliability | M31: 8 | N31: jazzcash | O31: Maybe | P31: easypaisa | Q31: Convinient for eidi transaction to your relatives | R31: 7
A32: Amina | B32: Female | C32: 30 - 41 | D32: {=_xlfn.IFS(SINGLE_RESPONSES[[#This Row],[Age]]="18 - 29",1, SINGLE_RESPONSES[[#This Row],[Age]]="30 - 41",2,SINGLE_RESPONSES[[#This Row],[Age]]="42 -53",3, SINGLE_RESPONSES[[#This Row],[Age]]="54 - 65",4, SINGLE_RESPONSES[[#This Row],[Age]]="66 and above",5)} -> 2 | E32: Lahore | F32: jazzcash | G32: jazzcash | H32: 7 | I32: jazzcash | J32: Today requirement in this digital world | K32: Yes | L32: One of the easy and fine way to send money around everywhere | M32: 9 | N32: none | O32: No | P32: i have not seen this ad | Q32: Not seen this ad | R32: 5
A33: Kanza | B33: Female | C33: 18 - 29 | D33: {=_xlfn.IFS(SINGLE_RESPONSES[[#This Row],[Age]]="18 - 29",1, SINGLE_RESPONSES[[#This Row],[Age]]="30 - 41",2,SINGLE_RESPONSES[[#This Row],[Age]]="42 -53",3, SINGLE_RESPONSES[[#This Row],[Age]]="54 - 65",4, SINGLE_RESPONSES[[#This Row],[Age]]="66 and above",5)} -> 1 | E33: Lahore | F33: sadapay | G33: sadapay | H33: 7 | I33: jazzcash | J33: I trust Sadapay better maybe cuz its not run locally | K33: Yes | L33: Convenience.. registering/ opening account in Sadapay was easy | M33: 8 | N33: none | O33: No | P33: i have not seen this ad | Q33: Accessibility, inclusivity | R33: 7
A34: Rana Ali Hassan | B34: Male | C34: 18 - 29 | D34: {=_xlfn.IFS(SINGLE_RESPONSES[[#This Row],[Age]]="18 - 29",1, SINGLE_RESPONSES[[#This Row],[Age]]="30 - 41",2,SINGLE_RESPONSES[[#This Row],[Age]]="42 -53",3, SINGLE_RESPONSES[[#This Row],[Age]]="54 - 65",4, SINGLE_RESPONSES[[#This Row],[Age]]="66 and above",5)} -> 1 | E34: Lahore | F34: easypaisa | G34: sadapay | H34: 3 | I34: sadapay | J34: Sometimes payment stuck and also some error are happened | K34: Yes | L34: It's used is simple, easy and safe | M34: 1 | N34: easypaisa | O34: No | P34: i have not seen this ad | Q34: To y Used digital app for payments | R34: 4
A35: amber | B35: Female | C35: 42 -53 | D35: {=_xlfn.IFS(SINGLE_RESPONSES[[#This Row],[Age]]="18 - 29",1, SINGLE_RESPONSES[[#This Row],[Age]]="30 - 41",2,SINGLE_RESPONSES[[#This Row],[Age]]="42 -53",3, SINGLE_RESPONSES[[#This Row],[Age]]="54 - 65",4, SINGLE_RESPONSES[[#This Row],[Age]]="66 and above",5)} -> 3 | E35: Lahore | F35: jazzcash | G35: jazzcash | H35: 2 | I35: easypaisa | J35: jazzcash is easy to use and am used to it now | K35: Yes | L35: for emergency if i need money to transfer anytime or anyone wants to return back my money | M35: 10 | N35: easypaisa | O35: Yes | P35: easypaisa | Q35: as everyone is using that app so transferred to their specific app through sadapay | R35: 10
A36: Naseer Ahmad | B36: Male | C36: 18 - 29 | D36: {=_xlfn.IFS(SINGLE_RESPONSES[[#This Row],[Age]]="18 - 29",1, SINGLE_RESPONSES[[#This Row],[Age]]="30 - 41",2,SINGLE_RESPONSES[[#This Row],[Age]]="42 -53",3, SINGLE_RESPONSES[[#This Row],[Age]]="54 - 65",4, SINGLE_RESPONSES[[#This Row],[Age]]="66 and above",5)} -> 1 | E36: Jhang | F36: easypaisa | G36: easypaisa | H36: 6 | I36: jazzcash | J36: For service issues | K36: Yes | L36: For good service | M36: 7 | N36: jazzcash | O36: Maybe | P36: easypaisa | Q36: It means this app is trustable and having fast service | R36: 7
A37: Mahnoor | B37: Female | C37: 18 - 29 | D37: {=_xlfn.IFS(SINGLE_RESPONSES[[#This Row],[Age]]="18 - 29",1, SINGLE_RESPONSES[[#This Row],[Age]]="30 - 41",2,SINGLE_RESPONSES[[#This Row],[Age]]="42 -53",3, SINGLE_RESPONSES[[#This Row],[Age]]="54 - 65",4, SINGLE_RESPONSES[[#This Row],[Age]]="66 and above",5)} -> 1 | E37: Lahore | F37: jazzcash | G37: jazzcash | H37: 4 | I37: jazzcash | J37: Is it good for myself and working fastly | K37: Yes | L37: Fast service | M37: 5 | N37: nayapay | O37: Maybe | P37: i have not seen this ad | Q37: To provide great service and advertising | R37: 3
... A151: Ghani Khan | B151: Male | C151: 18 - 29 | D151: {=_xlfn.IFS(SINGLE_RESPONSES[[#This Row],[Age]]="18 - 29",1, SINGLE_RESPONSES[[#This Row],[Age]]="30 - 41",2,SINGLE_RESPONSES[[#This Row],[Age]]="42 -53",3, SINGLE_RESPONSES[[#This Row],[Age]]="54 - 65",4, SINGLE_RESPONSES[[#This Row],[Age]]="66 and above",5)} -> 1 | E151: Faisalabad | F151: jazzcash | G151: jazzcash | H151: 7 | I151: jazzcash | J151: None | K151: Yes | L151: User friendly | M151: 7 | N151: easypaisa | O151: Maybe | P151: jazzcash | Q151: Easy access | R151: 5
B154: Gender analysis | G154: TOMA
C155: count | E155: Percentage | I155: count | J155: Percentage
B156: {=_xlfn.UNIQUE(SINGLE_RESPONSES[Gender])} -> Male | C156: =COUNTIF(SINGLE_RESPONSES[Gender],B156) -> 106 | E156: =C156/150 -> 0.70666667 | H156: easypaisa | I156: =COUNTIF(SINGLE_RESPONSES[TOM],H156) -> 46 | J156: =I156/150 -> 0.30666667
B157: Female | C157: =COUNTIF(SINGLE_RESPONSES[Gender],B157) -> 43 | E157: =C157/150 -> 0.28666667 | H157: sadapay | I157: =COUNTIF(SINGLE_RESPONSES[TOM],H157) -> 8 | J157: =I157/150 -> 0.053333333
B158: Prefer not to say | C158: =COUNTIF(SINGLE_RESPONSES[Gender],B158) -> 1 | E158: =C158/150 -> 0.0066666667 | H158: jazzcash | I158: =COUNTIF(SINGLE_RESPONSES[TOM],H158) -> 83 | J158: =I158/150 -> 0.55333333
H159: nayapay | I159: =COUNTIF(SINGLE_RESPONSES[TOM],H159) -> 10 | J159: =I159/150 -> 0.066666667
B176: Age group analysis
C177: count
A178: 18-29 | B178: {=_xlfn._xlws.SORT(_xlfn.UNIQUE(SINGLE_RESPONSES[coding]))} -> 1 | C178: =COUNTIF(SINGLE_RESPONSES[coding],B178) -> 127 | D178: =C178/150 -> 0.84666667
A179: 30-41 | B179: 2 | C179: =COUNTIF(SINGLE_RESPONSES[coding],B179) -> 15 | D179: =C179/150 -> 0.1
A180: 42-54 | B180: 3 | C180: =COUNTIF(SINGLE_RESPONSES[coding],B180) -> 5 | D180: =C180/150 -> 0.033333333
A181: 55-64 | B181: 4 | C181: =COUNTIF(SINGLE_RESPONSES[coding],B181) -> 2 | D181: =C181/150 -> 0.013333333
A182: 66 and above | B182: 5 | C182: =COUNTIF(SINGLE_RESPONSES[coding],B182) -> 1 | D182: =C182/150 -> 0.0066666667
G183: Awareness
H184: count | I184: percentage
G185: easypaisa | H185: =Engineered_Awareness_data!H152 -> 100 | I185: =H185/150 -> 0.66666667
G186: sadapay | H186: =Engineered_Awareness_data!I152 -> 61 | I186: =H186/150 -> 0.40666667
G187: jazzcash | H187: =Engineered_Awareness_data!G152 -> 114 | I187: =H187/150 -> 0.76
G188: nayapay | H188: =Engineered_Awareness_data!J152 -> 55 | I188: =H188/150 -> 0.36666667
G206: Favorite
H207: count | I207: %
G208: {=_xlfn.UNIQUE(SINGLE_RESPONSES[FAVORITE])} -> easypaisa | H208: =COUNTIF(SINGLE_RESPONSES[FAVORITE],G208) -> 43 | I208: =H208/150 -> 0.28666667
G209: sadapay | H209: =COUNTIF(SINGLE_RESPONSES[FAVORITE],G209) -> 18 | I209: =H209/150 -> 0.12
G210: nayapay | H210: =COUNTIF(SINGLE_RESPONSES[FAVORITE],G210) -> 24 | I210: =H210/150 -> 0.16
G211: jazzcash | H211: =COUNTIF(SINGLE_RESPONSES[FAVORITE],G211) -> 65 | I211: =H211/150 -> 0.43333333
G216: using since
F217: 1 | G217: Less than 1 month | H217: =COUNTIF(SINGLE_RESPONSES[Using since],F217) -> 10 | I217: =H217/150 -> 0.066666667
F218: 2 | G218: 1-4 months | H218: =COUNTIF(SINGLE_RESPONSES[Using since],F218) -> 8 | I218: =H218/150 -> 0.053333333
F219: 3 | G219: 5-8 months | H219: =COUNTIF(SINGLE_RESPONSES[Using since],F219) -> 6 | I219: =H219/150 -> 0.04
F220: 4 | G220: 9-12 months | H220: =COUNTIF(SINGLE_RESPONSES[Using since],F220) -> 17 | I220: =H220/150 -> 0.11333333
F221: 5 | G221: 13-18 months | H221: =COUNTIF(SINGLE_RESPONSES[Using since],F221) -> 15 | I221: =H221/150 -> 0.1
F222: 6 | G222: 18-24 months | H222: =COUNTIF(SINGLE_RESPONSES[Using since],F222) -> 16 | I222: =H222/150 -> 0.10666667
F223: 7 | G223: More than 2 years | H223: =COUNTIF(SINGLE_RESPONSES[Using since],F223) -> 78 | I223: =H223/150 -> 0.52
G226: Apps Usage
F227: {=TRANSPOSE(_xlfn.UNIQUE(SINGLE_RESPONSES[FAVORITE]))} -> easypaisa | G227: sadapay | H227: nayapay | I227: jazzcash
D228: 1 | E228: Less than 1 month | F228: =COUNTIFS($H$2:$H$151,$D228,$G$2:$G$151,F$227) -> 3 | G228: =COUNTIFS($H$2:$H$151,$D228,$G$2:$G$151,G$227) -> 3 | H228: =COUNTIFS($H$2:$H$151,$D228,$G$2:$G$151,H$227) -> 0 | I228: =COUNTIFS($H$2:$H$151,$D228,$G$2:$G$151,I$227) -> 4
D229: 2 | E229: 1-4 months | F229: =COUNTIFS($H$2:$H$151,$D229,$G$2:$G$151,F$227) -> 1 | G229: =COUNTIFS($H$2:$H$151,$D229,$G$2:$G$151,G$227) -> 0 | H229: =COUNTIFS($H$2:$H$151,$D229,$G$2:$G$151,H$227) -> 0 | I229: =COUNTIFS($H$2:$H$151,$D229,$G$2:$G$151,I$227) -> 7
D230: 3 | E230: 5-8 months | F230: =COUNTIFS($H$2:$H$151,$D230,$G$2:$G$151,F$227) -> 1 | G230: =COUNTIFS($H$2:$H$151,$D230,$G$2:$G$151,G$227) -> 2 | H230: =COUNTIFS($H$2:$H$151,$D230,$G$2:$G$151,H$227) -> 1 | I230: =COUNTIFS($H$2:$H$151,$D230,$G$2:$G$151,I$227) -> 2
D231: 4 | E231: 9-12 months | F231: =COUNTIFS($H$2:$H$151,$D231,$G$2:$G$151,F$227) -> 5 | G231: =COUNTIFS($H$2:$H$151,$D231,$G$2:$G$151,G$227) -> 1 | H231: =COUNTIFS($H$2:$H$151,$D231,$G$2:$G$151,H$227) -> 2 | I231: =COUNTIFS($H$2:$H$151,$D231,$G$2:$G$151,I$227) -> 9
D232: 5 | E232: 13-18 months | F232: =COUNTIFS($H$2:$H$151,$D232,$G$2:$G$151,F$227) -> 5 | G232: =COUNTIFS($H$2:$H$151,$D232,$G$2:$G$151,G$227) -> 3 | H232: =COUNTIFS($H$2:$H$151,$D232,$G$2:$G$151,H$227) -> 2 | I232: =COUNTIFS($H$2:$H$151,$D232,$G$2:$G$151,I$227) -> 5
D233: 6 | E233: 18-24 months | F233: =COUNTIFS($H$2:$H$151,$D233,$G$2:$G$151,F$227) -> 6 | G233: =COUNTIFS($H$2:$H$151,$D233,$G$2:$G$151,G$227) -> 2 | H233: =COUNTIFS($H$2:$H$151,$D233,$G$2:$G$151,H$227) -> 1 | I233: =COUNTIFS($H$2:$H$151,$D233,$G$2:$G$151,I$227) -> 7
D234: 7 | E234: More than 2 years | F234: =COUNTIFS($H$2:$H$151,$D234,$G$2:$G$151,F$227) -> 22 | G234: =COUNTIFS($H$2:$H$151,$D234,$G$2:$G$151,G$227) -> 7 | H234: =COUNTIFS($H$2:$H$151,$D234,$G$2:$G$151,H$227) -> 18 | I234: =COUNTIFS($H$2:$H$151,$D234,$G$2:$G$151,I$227) -> 31
G236: Where people moved from their Ex-App
F237: current app
H238: count
G239: easypaisa | H239: =COUNTIF(SINGLE_RESPONSES[Previous Brand],G239) -> 55 | I239: =H239/150 -> 0.36666667
G240: sadapay | H240: =COUNTIF(SINGLE_RESPONSES[Previous Brand],G240) -> 11 | I240: =H240/150 -> 0.073333333
G241: nayapay | H241: =COUNTIF(SINGLE_RESPONSES[Previous Brand],G241) -> 15 | I241: =H241/150 -> 0.1
G242: jazzcash | H242: =COUNTIF(SINGLE_RESPONSES[Previous Brand],G242) -> 69 | I242: =H242/150 -> 0.46
E247: previous app | G247: Favorite App
G249: easypaisa | H249: sadapay | I249: nayapay | J249: jazzcash
F250: easypaisa | H250: =COUNTIFS($I$2:$I$151,$F250,$G$2:$G$151,H$249) -> 7 | I250: =COUNTIFS($I$2:$I$151,$F250,$G$2:$G$151,I$249) -> 7 | J250: =COUNTIFS($I$2:$I$151,$F250,$G$2:$G$151,J$249) -> 26
F251: sadapay | G251: =COUNTIFS($I$2:$I$151,$F251,$G$2:$G$151,G$249) -> 4 | I251: =COUNTIFS($I$2:$I$151,$F251,$G$2:$G$151,I$249) -> 2 | J251: =COUNTIFS($I$2:$I$151,$F251,$G$2:$G$151,J$249) -> 3
F252: nayapay | G252: =COUNTIFS($I$2:$I$151,$F252,$G$2:$G$151,G$249) -> 4 | H252: =COUNTIFS($I$2:$I$151,$F252,$G$2:$G$151,H$249) -> 0 | J252: =COUNTIFS($I$2:$I$151,$F252,$G$2:$G$151,J$249) -> 5
F253: jazzcash | G253: =COUNTIFS($I$2:$I$151,$F253,$G$2:$G$151,G$249) -> 20 | H253: =COUNTIFS($I$2:$I$151,$F253,$G$2:$G$151,H$249) -> 9 | I253: =COUNTIFS($I$2:$I$151,$F253,$G$2:$G$151,I$249) -> 9
K258: Better UX
K259: 1 | L259: =COUNTIFS('[1]Reason_to_switch_&_keepusing'!$G$2:$G$149,$E$263,'[1]Reason_to_switch_&_keepusing'!$D$2:$D$149,F$261,'[1]Reason_to_switch_&_keepusing'!$H$2:$H$149,$K259) -> #VALUE!
E260: Reasons why people are moving to other apps | F260: Favorite App | K260: 2 | L260: =COUNTIFS('[1]Reason_to_switch_&_keepusing'!$G$2:$G$149,$E$263,'[1]Reason_to_switch_&_keepusing'!$D$2:$D$149,G$261,'[1]Reason_to_switch_&_keepusing'!$H$2:$H$149,$K260) -> #VALUE!
F261: easypaisa | G261: jazzcash | H261: sadapay | I261: nayapay | K261: 3 | L261: =COUNTIFS('[1]Reason_to_switch_&_keepusing'!$G$2:$G$149,$E$263,'[1]Reason_to_switch_&_keepusing'!$D$2:$D$149,G$261,'[1]Reason_to_switch_&_keepusing'!$H$2:$H$149,$K261) -> #VALUE!
E262: PULL factors | K262: 4 | L262: =COUNTIFS('[1]Reason_to_switch_&_keepusing'!$G$2:$G$149,$E$263,'[1]Reason_to_switch_&_keepusing'!$D$2:$D$149,G$261,'[1]Reason_to_switch_&_keepusing'!$H$2:$H$149,$K262) -> #VALUE!
E263: Better UX | F263: =COUNTIFS('Reason_to_switch_&_keep_using'!$G:$G,SINGLE_RESPONSES!$E263,'Reason_to_switch_&_keep_using'!$D:$D,SINGLE_RESPONSES!F$261) -> 4 | G263: =COUNTIFS('Reason_to_switch_&_keep_using'!$G:$G,SINGLE_RESPONSES!$E263,'Reason_to_switch_&_keep_using'!$D:$D,SINGLE_RESPONSES!G$261) -> 10 | H263: =COUNTIFS('Reason_to_switch_&_keep_using'!$G:$G,SINGLE_RESPONSES!$E263,'Reason_to_switch_&_keep_using'!$D:$D,SINGLE_RESPONSES!H$261) -> 4 | I263: =COUNTIFS('Reason_to_switch_&_keep_using'!$G:$G,SINGLE_RESPONSES!$E263,'Reason_to_switch_&_keep_using'!$D:$D,SINGLE_RESPONSES!I$261) -> 0 | K263: 5 | L263: =COUNTIFS('[1]Reason_to_switch_&_keepusing'!$G$2:$G$149,$E$263,'[1]Reason_to_switch_&_keepusing'!$D$2:$D$149,G$261,'[1]Reason_to_switch_&_keepusing'!$H$2:$H$149,$K263) -> #VALUE!
E264: Better Features | F264: =COUNTIFS('Reason_to_switch_&_keep_using'!$G:$G,SINGLE_RESPONSES!$E264,'Reason_to_switch_&_keep_using'!$D:$D,SINGLE_RESPONSES!F$261) -> 4 | G264: =COUNTIFS('Reason_to_switch_&_keep_using'!$G:$G,SINGLE_RESPONSES!$E264,'Reason_to_switch_&_keep_using'!$D:$D,SINGLE_RESPONSES!G$261) -> 3 | H264: =COUNTIFS('Reason_to_switch_&_keep_using'!$G:$G,SINGLE_RESPONSES!$E264,'Reason_to_switch_&_keep_using'!$D:$D,SINGLE_RESPONSES!H$261) -> 1 | I264: =COUNTIFS('Reason_to_switch_&_keep_using'!$G:$G,SINGLE_RESPONSES!$E264,'Reason_to_switch_&_keep_using'!$D:$D,SINGLE_RESPONSES!I$261) -> 2 | K264: 6 | L264: =COUNTIFS('[1]Reason_to_switch_&_keepusing'!$G$2:$G$149,$E$263,'[1]Reason_to_switch_&_keepusing'!$D$2:$D$149,G$261,'[1]Reason_to_switch_&_keepusing'!$H$2:$H$149,$K264) -> #VALUE!
E265: Performance | F265: =COUNTIFS('Reason_to_switch_&_keep_using'!$G:$G,SINGLE_RESPONSES!$E265,'Reason_to_switch_&_keep_using'!$D:$D,SINGLE_RESPONSES!F$261) -> 1 | G265: =COUNTIFS('Reason_to_switch_&_keep_using'!$G:$G,SINGLE_RESPONSES!$E265,'Reason_to_switch_&_keep_using'!$D:$D,SINGLE_RESPONSES!G$261) -> 4 | H265: =COUNTIFS('Reason_to_switch_&_keep_using'!$G:$G,SINGLE_RESPONSES!$E265,'Reason_to_switch_&_keep_using'!$D:$D,SINGLE_RESPONSES!H$261) -> 0 | I265: =COUNTIFS('Reason_to_switch_&_keep_using'!$G:$G,SINGLE_RESPONSES!$E265,'Reason_to_switch_&_keep_using'!$D:$D,SINGLE_RESPONSES!I$261) -> 0 | K265: 7 | N265: Hypothesis: those who say better UX are using it more than 2 years =TRUE
E266: Good Customer Services | F266: =COUNTIFS('Reason_to_switch_&_keep_using'!$G:$G,SINGLE_RESPONSES!$E266,'Reason_to_switch_&_keep_using'!$D:$D,SINGLE_RESPONSES!F$261) -> 1 | G266: =COUNTIFS('Reason_to_switch_&_keep_using'!$G:$G,SINGLE_RESPONSES!$E266,'Reason_to_switch_&_keep_using'!$D:$D,SINGLE_RESPONSES!G$261) -> 1 | H266: =COUNTIFS('Reason_to_switch_&_keep_using'!$G:$G,SINGLE_RESPONSES!$E266,'Reason_to_switch_&_keep_using'!$D:$D,SINGLE_RESPONSES!H$261) -> 1 | I266: =COUNTIFS('Reason_to_switch_&_keep_using'!$G:$G,SINGLE_RESPONSES!$E266,'Reason_to_switch_&_keep_using'!$D:$D,SINGLE_RESPONSES!I$261) -> 0
E267: Ecosystem Advantage | F267: =COUNTIFS('Reason_to_switch_&_keep_using'!$G:$G,SINGLE_RESPONSES!$E267,'Reason_to_switch_&_keep_using'!$D:$D,SINGLE_RESPONSES!F$261) -> 2 | G267: =COUNTIFS('Reason_to_switch_&_keep_using'!$G:$G,SINGLE_RESPONSES!$E267,'Reason_to_switch_&_keep_using'!$D:$D,SINGLE_RESPONSES!G$261) -> 3 | H267: =COUNTIFS('Reason_to_switch_&_keep_using'!$G:$G,SINGLE_RESPONSES!$E267,'Reason_to_switch_&_keep_using'!$D:$D,SINGLE_RESPONSES!H$261) -> 0 | I267: =COUNTIFS('Reason_to_switch_&_keep_using'!$G:$G,SINGLE_RESPONSES!$E267,'Reason_to_switch_&_keep_using'!$D:$D,SINGLE_RESPONSES!I$261) -> 0
E268: Greater Trust | F268: =COUNTIFS('Reason_to_switch_&_keep_using'!$G:$G,SINGLE_RESPONSES!$E268,'Reason_to_switch_&_keep_using'!$D:$D,SINGLE_RESPONSES!F$261) -> 0 | G268: =COUNTIFS('Reason_to_switch_&_keep_using'!$G:$G,SINGLE_RESPONSES!$E268,'Reason_to_switch_&_keep_using'!$D:$D,SINGLE_RESPONSES!G$261) -> 0 | H268: =COUNTIFS('Reason_to_switch_&_keep_using'!$G:$G,SINGLE_RESPONSES!$E268,'Reason_to_switch_&_keep_using'!$D:$D,SINGLE_RESPONSES!H$261) -> 0 | I268: =COUNTIFS('Reason_to_switch_&_keep_using'!$G:$G,SINGLE_RESPONSES!$E268,'Reason_to_switch_&_keep_using'!$D:$D,SINGLE_RESPONSES!I$261) -> 1
E269: Explore | F269: =COUNTIFS('Reason_to_switch_&_keep_using'!$G:$G,SINGLE_RESPONSES!$E269,'Reason_to_switch_&_keep_using'!$D:$D,SINGLE_RESPONSES!F$261) -> 6 | G269: =COUNTIFS('Reason_to_switch_&_keep_using'!$G:$G,SINGLE_RESPONSES!$E269,'Reason_to_switch_&_keep_using'!$D:$D,SINGLE_RESPONSES!G$261) -> 7 | H269: =COUNTIFS('Reason_to_switch_&_keep_using'!$G:$G,SINGLE_RESPONSES!$E269,'Reason_to_switch_&_keep_using'!$D:$D,SINGLE_RESPONSES!H$261) -> 3 | I269: =COUNTIFS('Reason_to_switch_&_keep_using'!$G:$G,SINGLE_RESPONSES!$E269,'Reason_to_switch_&_keep_using'!$D:$D,SINGLE_RESPONSES!I$261) -> 3 | J269: Explore: Everybody is talking about the easypaisa , jazzcash or everyother person has it so it might be | K269: Explore
E270: PUSH Factors | J270: possible they want to give it a try? | K270: 1 | L270: =COUNTIFS('[1]Reason_to_switch_&_keepusing'!$G$2:$G$149,$E$269,'[1]Reason_to_switch_&_keepusing'!$D$2:$D$149,G$261,'[1]Reason_to_switch_&_keepusing'!$H$2:$H$149,$K270) -> #VALUE!
E271: Trust issues | F271: =COUNTIFS('Reason_to_switch_&_keep_using'!$G:$G,SINGLE_RESPONSES!$E271,'Reason_to_switch_&_keep_using'!$D:$D,SINGLE_RESPONSES!F$261) -> 1 | G271: =COUNTIFS('Reason_to_switch_&_keep_using'!$G:$G,SINGLE_RESPONSES!$E271,'Reason_to_switch_&_keep_using'!$D:$D,SINGLE_RESPONSES!G$261) -> 2 | H271: =COUNTIFS('Reason_to_switch_&_keep_using'!$G:$G,SINGLE_RESPONSES!$E271,'Reason_to_switch_&_keep_using'!$D:$D,SINGLE_RESPONSES!H$261) -> 1 | I271: =COUNTIFS('Reason_to_switch_&_keep_using'!$G:$G,SINGLE_RESPONSES!$E271,'Reason_to_switch_&_keep_using'!$D:$D,SINGLE_RESPONSES!I$261) -> 1 | K271: 2 | L271: =COUNTIFS('[1]Reason_to_switch_&_keepusing'!$G$2:$G$149,$E$269,'[1]Reason_to_switch_&_keepusing'!$D$2:$D$149,G$261,'[1]Reason_to_switch_&_keepusing'!$H$2:$H$149,$K271) -> #VALUE!
E272: Technical Failures | F272: =COUNTIFS('Reason_to_switch_&_keep_using'!$G:$G,SINGLE_RESPONSES!$E272,'Reason_to_switch_&_keep_using'!$D:$D,SINGLE_RESPONSES!F$261) -> 3 | G272: =COUNTIFS('Reason_to_switch_&_keep_using'!$G:$G,SINGLE_RESPONSES!$E272,'Reason_to_switch_&_keep_using'!$D:$D,SINGLE_RESPONSES!G$261) -> 0 | H272: =COUNTIFS('Reason_to_switch_&_keep_using'!$G:$G,SINGLE_RESPONSES!$E272,'Reason_to_switch_&_keep_using'!$D:$D,SINGLE_RESPONSES!H$261) -> 3 | I272: =COUNTIFS('Reason_to_switch_&_keep_using'!$G:$G,SINGLE_RESPONSES!$E272,'Reason_to_switch_&_keep_using'!$D:$D,SINGLE_RESPONSES!I$261) -> 2 | K272: 3 | L272: =COUNTIFS('[1]Reason_to_switch_&_keepusing'!$G$2:$G$149,$E$269,'[1]Reason_to_switch_&_keepusing'!$D$2:$D$149,G$261,'[1]Reason_to_switch_&_keepusing'!$H$2:$H$149,$K272) -> #VALUE!
E273: Account Access Issues | F273: =COUNTIFS('Reason_to_switch_&_keep_using'!$G:$G,SINGLE_RESPONSES!$E273,'Reason_to_switch_&_keep_using'!$D:$D,SINGLE_RESPONSES!F$261) -> 0 | G273: =COUNTIFS('Reason_to_switch_&_keep_using'!$G:$G,SINGLE_RESPONSES!$E273,'Reason_to_switch_&_keep_using'!$D:$D,SINGLE_RESPONSES!G$261) -> 2 | H273: =COUNTIFS('Reason_to_switch_&_keep_using'!$G:$G,SINGLE_RESPONSES!$E273,'Reason_to_switch_&_keep_using'!$D:$D,SINGLE_RESPONSES!H$261) -> 0 | I273: =COUNTIFS('Reason_to_switch_&_keep_using'!$G:$G,SINGLE_RESPONSES!$E273,'Reason_to_switch_&_keep_using'!$D:$D,SINGLE_RESPONSES!I$261) -> 0 | K273: 4 | L273: =COUNTIFS('[1]Reason_to_switch_&_keepusing'!$G$2:$G$149,$E$269,'[1]Reason_to_switch_&_keepusing'!$D$2:$D$149,G$261,'[1]Reason_to_switch_&_keepusing'!$H$2:$H$149,$K273) -> #VALUE!
...

Sheet Main_Table
A1: Respondent Profile: Name | B1: Gender | C1: Age | D1: City | E1: TOM | F1: EVER USED | G1: CURRENT USAGE | H1: FAVORITE | I1: Using since | J1: Previous Brand | K1: Reasons for switching | L1: Future intent | M1: Reasons for keep using | N1: NPS | O1: Alternate App | P1: Best app interface and user experience (UX) | Q1: Most reliable (least likely to have server/network down issues) | R1: Offers the best discounts, deals, and cashbacks | S1: Good customer service and quick issue resolution | T1: Lowest transaction fees and free inter-bank fund transfers (IBFT) | U1: Strongest security features | V1: Easiest and fastest process for opening an account or ordering a physical debit card | W1: Best app for international payments | X1: 5.1) Have you seen the advertisement above on TV recently or not? | Y1: 5.2 ) What digital payment app was this ad for? | Z1: 5.3) In your own words, what was the main message of this ad? (Please be specific; avoid general answers like 'it is a good app.' | AA1: 5.4) To what extent did you like this ad?
A2: Gulfam | B2: Male | C2: 30 - 41 | D2: Lahore | E2: easypaisa | F2: jazzcash,easypaisa,sadapay | G2: easypaisa | H2: easypaisa | I2: 6 | J2: sadapay | K2: account blockage and trust issues | L2: Yes | M2: easier to manage small transactions and payments like payment of bills etc | N2: 9 | O2: jazzcash | P2: sadapay | Q2: easypaisa | R2: jazzcash | S2: sadapay | T2: easypaisa | U2: easypaisa | V2: easypaisa | W2: easypaisa | X2: No | Y2: easypaisa | Z2: have not seen this ad | AA2: 1
A3: waleed | B3: Male | C3: 18 - 29 | D3: Lahore | E3: easypaisa | F3: easypaisa | G3: easypaisa | H3: easypaisa | I3: 4 | J3: easypaisa | K3: Not switched | L3: Yes | M3: Best user interface and user experience | N3: 9 | O3: bankingapp | P3: easypaisa | Q3: easypaisa | R3: easypaisa | S3: easypaisa | T3: easypaisa | U3: easypaisa | V3: easypaisa | W3: easypaisa | X3: Yes | Y3: easypaisa | Z3: You can transfer money from anywhere in your easy paisa account and it'll be transferred in your account immediately without any disruption | AA3: 5
A4: Talha | B4: Male | C4: 18 - 29 | D4: Lahore | E4: sadapay | F4: sadapay | G4: sadapay | H4: sadapay | I4: 4 | J4: easypaisa | K4: Easy to assess | L4: Yes | M4: Easy to assess | N4: 10 | O4: bankingapp | P4: sadapay | Q4: nayapay | R4: easypaisa | S4: easypaisa | T4: sadapay | U4: easypaisa | V4: sadapay | W4: sadapay | X4: Yes | Y4: easypaisa | Z4: Easy to transfer | AA4: 10
A5: Jawad Waseem | B5: Male | C5: 18 - 29 | D5: Lahore | E5: easypaisa | F5: jazzcash,easypaisa,nayapay | G5: easypaisa | H5: easypaisa | I5: 7 | J5: nayapay | K5: More options | L5: Yes | M5: Connectivity and | N5: 7 | O5: nayapay | P5: easypaisa | Q5: easypaisa | R5: easypaisa | S5: easypaisa | T5: easypaisa | U5: easypaisa | V5: easypaisa | W5: easypaisa | X5: Yes | Y5: easypaisa | Z5: Easy transfer | AA5: 5
A6: Abdullah | B6: Male | C6: 18 - 29 | D6: Lahore | E6: easypaisa | F6: jazzcash,easypaisa,sadapay,nayapay | G6: easypaisa | H6: easypaisa | I6: 6 | J6: jazzcash | K6: Bad service | L6: Yes | M6: Fast service | N6: 8 | O6: jazzcash | P6: easypaisa | Q6: jazzcash | R6: jazzcash | S6: easypaisa | T6: easypaisa | U6: easypaisa | V6: easypaisa | W6: easypaisa | X6: Yes | Y6: easypaisa | Z6: Make digital wallet for small transactions | AA6: 7
A7: Muhammad saad ahmad | B7: Male | C7: 18 - 29 | D7: Lahore | E7: jazzcash | F7: easypaisa | G7: easypaisa | H7: easypaisa | I7: 5 | J7: nayapay | K7: Wasn't reliable | L7: Yes | M7: Easy to use | N7: 9 | O7: nayapay | P7: nayapay | Q7: jazzcash | R7: easypaisa | S7: easypaisa | T7: easypaisa | U7: jazzcash | V7: nayapay | W7: jazzcash | X7: No | Y7: i have not seen this ad | Z7: That the transfer of money can be made remotely and easily | AA7: 10
A8: Mubashir hassan | B8: Male | C8: 18 - 29 | D8: Lahore | E8: easypaisa | F8: easypaisa | G8: jazzcash,easypaisa | H8: easypaisa | I8: 7 | J8: jazzcash | K8: User experience | L8: Yes | M8: User experience and user interface | N8: 7 | O8: bankingapp | P8: jazzcash | Q8: jazzcash | R8: jazzcash | S8: jazzcash | T8: easypaisa | U8: jazzcash | V8: jazzcash | W8: jazzcash | X8: Yes | Y8: jazzcash | Z8: They communicate. With customers... | AA8: 7
A9: Ayesha | B9: Female | C9: 18 - 29 | D9: Lahore | E9: nayapay | F9: jazzcash,sadapay,nayapay | G9: jazzcash,nayapay | H9: nayapay | I9: 7 | J9: jazzcash | K9: It's secure and easy to use. | L9: Yes | M9: It's easy to use. | N9: 9 | O9: jazzcash | P9: nayapay | Q9: nayapay | R9: jazzcash | S9: nayapay | T9: nayapay | U9: nayapay | V9: nayapay | W9: sadapay | X9: Maybe | Y9: easypaisa | Z9: Digital wallet apps awareness | AA9: 10
A10: Kainat | B10: Female | C10: 18 - 29 | D10: Lahore | E10: jazzcash | F10: jazzcash,sadapay | G10: jazzcash | H10: jazzcash | I10: 4 | J10: jazzcash | K10: Not switched | L10: Yes | M10: Easily manageable and reliable | N10: 10 | O10: bankingapp | P10: jazzcash | Q10: jazzcash | R10: jazzcash | S10: jazzcash | T10: jazzcash | U10: jazzcash | V10: jazzcash | W10: jazzcash | X10: Maybe | Y10: i have not seen this ad | Z10: I haven't seen this ad | AA10: 1
A11: Muhammad Danish Zafar | B11: Male | C11: 18 - 29 | D11: Lahore | E11: sadapay | F11: sadapay | G11: jazzcash,easypaisa,sadapay | H11: sadapay | I11: 7 | J11: easypaisa | K11: Most of the time servers down | L11: Yes | M11: International transactions | N11: 8 | O11: jazzcash | P11: jazzcash | Q11: jazzcash | R11: jazzcash | S11: sadapay | T11: sadapay | U11: jazzcash | V11: jazzcash | W11: sadapay | X11: Maybe | Y11: easypaisa | Z11: Payment transfer | AA11: 5
A12: Hassan Jehangir | B12: Male | C12: 18 - 29 | D12: Lahore | E12: jazzcash | F12: jazzcash,nayapay | G12: jazzcash,nayapay | H12: jazzcash | I12: 4 | J12: easypaisa | K12: Easy to transfer money instantly | L12: Yes | M12: Instant money transfer and good UI | N12: 10 | O12: nayapay | P12: jazzcash | Q12: jazzcash | R12: jazzcash | S12: jazzcash | T12: jazzcash | U12: jazzcash | V12: jazzcash | W12: nayapay | X12: No | Y12: i have not seen this ad | Z12: No idea | AA12: 1
A13: Rayyan Amin | B13: Female | C13: 18 - 29 | D13: Lahore | E13: jazzcash | F13: jazzcash,easypaisa,sadapay,nayapay | G13: easypaisa | H13: easypaisa | I13: 5 | J13: jazzcash | K13: Better services | L13: Yes | M13: Easy transactions | N13: 8 | O13: sadapay | P13: jazzcash | Q13: easypaisa | R13: sadapay | S13: nayapay | T13: nayapay | U13: easypaisa | V13: nayapay | W13: jazzcash | X13: No | Y13: easypaisa | Z13: Cheap and easy | AA13: 9
... A23: Shoaib Ahmad | B23: Male | C23: 18 - 29 | D23: Okara | E23: easypaisa | F23: jazzcash | G23: jazzcash | H23: jazzcash | I23: 7 | J23: jazzcash | K23: Mostly use jazzcash | L23: Yes | M23: More preferable | N23: 10 | O23: jazzcash | P23: jazzcash | Q23: nayapay | R23: easypaisa | S23: jazzcash | T23: nayapay | U23: jazzcash | V23: jazzcash | W23: nayapay | X23: Maybe | Y23: i have not seen this ad | Z23: Jazzcash | AA23: 8
A24: DAC | B24: Male | C24: 18 - 29 | D24: Lahore | E24: jazzcash | F24: jazzcash,easypaisa,nayapay | G24: jazzcash,nayapay | H24: jazzcash | I24: 7 | J24: nayapay | L24: Yes | M24: Bcz of its user friendly | N24: 10 | O24: nayapay | P24: jazzcash | Q24: jazzcash | R24: jazzcash | S24: jazzcash | T24: nayapay | U24: nayapay | V24: jazzcash | W24: nayapay | X24: Yes | Y24: easypaisa | Z24: the convenience of online money transfer for festive gifts | AA24: 7
A25: Momin Ali | B25: Male | C25: 18 - 29 | D25: Gujrat | E25: easypaisa | F25: easypaisa | G25: easypaisa | H25: easypaisa | I25: 5 | J25: easypaisa | K25: Na | L25: Yes | M25: Availability | N25: 9 | O25: sadapay | P25: sadapay | Q25: sadapay | R25: jazzcash | S25: sadapay | T25: easypaisa | U25: easypaisa | V25: easypaisa | W25: jazzcash | Y25: jazzcash | Z25: Dont remember much but i believe related to family n internet | AA25: 9
A26: Iqra | B26: Female | C26: 18 - 29 | D26: Lahore | E26: jazzcash | F26: jazzcash | G26: jazzcash | H26: jazzcash | I26: 7 | J26: jazzcash | K26: No change | L26: Yes | M26: It good | N26: 10 | O26: easypaisa | P26: jazzcash | Q26: sadapay | R26: easypaisa | S26: easypaisa | T26: jazzcash | U26: jazzcash | V26: jazzcash | W26: jazzcash | X26: No | Y26: i have not seen this ad | Z26: No messs7 | AA26: 1
A27: Amna | B27: Female | C27: 18 - 29 | D27: Lahore | E27: jazzcash | F27: jazzcash | G27: jazzcash | H27: jazzcash | I27: 6 | J27: nayapay | K27: Using it for the first time. | L27: Yes | M27: Easy. | N27: 10 | O27: easypaisa | P27: jazzcash | Q27: jazzcash | R27: easypaisa | S27: jazzcash | T27: jazzcash | U27: nayapay | V27: easypaisa | W27: nayapay | X27: Yes | Y27: jazzcash | Z27: Faster money transfer | AA27: 6
A28: Laiba | B28: Female | C28: 18 - 29 | D28: Lahore | E28: jazzcash | F28: jazzcash,easypaisa,sadapay | G28: easypaisa | H28: easypaisa | I28: 6 | J28: jazzcash | K28: Idk | L28: Yes | M28: Again idk, just using it. | N28: 9 | O28: jazzcash | P28: easypaisa | Q28: easypaisa | R28: jazzcash | S28: jazzcash | T28: easypaisa | U28: easypaisa | V28: easypaisa | X28: No | Y28: i have not seen this ad | Z28: This should not be a required question. | AA28: 1
A29: Haider shah | B29: Male | C29: 18 - 29 | D29: Lahore | E29: easypaisa | F29: easypaisa,nayapay | G29: easypaisa | H29: easypaisa | I29: 7 | J29: easypaisa | K29: Easypaisa is more essential | L29: Yes | M29: Its safe | N29: 4 | O29: nayapay | P29: easypaisa | Q29: easypaisa | R29: easypaisa | S29: easypaisa | T29: easypaisa | U29: easypaisa | V29: easypaisa | W29: easypaisa | X29: No | Y29: easypaisa | Z29: For forcing people to trust online platform | AA29: 3
A30: Meerab Arshad | B30: Female | C30: 18 - 29 | D30: Raiwind | E30: jazzcash | F30: jazzcash | G30: jazzcash | H30: jazzcash | I30: 2 | J30: jazzcash | K30: Jazz cash | L30: Yes | M30: Jazz cash | N30: 1 | O30: jazzcash | P30: jazzcash | Q30: jazzcash | R30: easypaisa | S30: jazzcash | T30: jazzcash | U30: jazzcash | V30: jazzcash | W30: jazzcash | X30: Yes | Y30: jazzcash | Z30: It's very helpful | AA30: 1
A31: Muhammad Ziad Amir | B31: Male | C31: 18 - 29 | D31: Lahore | E31: jazzcash | F31: jazzcash,easypaisa,sadapay,nayapay | G31: sadapay | H31: sadapay | I31: 5 | J31: jazzcash | K31: App errors | L31: Yes | M31: Reliability | N31: 8 | O31: jazzcash | P31: sadapay | Q31: sadapay | R31: jazzcash | S31: jazzcash | T31: sadapay | U31: sadapay | V31: sadapay | W31: jazzcash | X31: Maybe | Y31: easypaisa | Z31: Convinient for eidi transaction to your relatives | AA31: 7
A32: Amina | B32: Female | C32: 30 - 41 | D32: Lahore | E32: jazzcash | F32: jazzcash | G32: jazzcash | H32: jazzcash | I32: 7 | J32: jazzcash | K32: Today requirement in this digital world | L32: Yes | M32: One of the easy and fine way to send money around everywhere | N32: 9 | O32: none | P32: jazzcash | Q32: jazzcash | R32: jazzcash | S32: jazzcash | T32: sadapay | U32: jazzcash | V32: jazzcash | W32: jazzcash | X32: No | Y32: i have not seen this ad | Z32: Not seen this ad | AA32: 5
A33: Kanza | B33: Female | C33: 18 - 29 | D33: Lahore | E33: sadapay | F33: sadapay | G33: sadapay | H33: sadapay | I33: 7 | J33: jazzcash | K33: I trust Sadapay better maybe cuz its not run locally | L33: Yes | M33: Convenience.. registering/ opening account in Sadapay was easy | N33: 8 | O33: none | P33: sadapay | Q33: sadapay | R33: jazzcash | S33: sadapay | T33: sadapay | U33: sadapay | V33: sadapay | W33: sadapay | X33: No | Y33: i have not seen this ad | Z33: Accessibility, inclusivity | AA33: 7
A34: Rana Ali Hassan | B34: Male | C34: 18 - 29 | D34: Lahore | E34: easypaisa | F34: easypaisa,sadapay | G34: sadapay | H34: sadapay | I34: 3 | J34: sadapay | K34: Sometimes payment stuck and also some error are happened | L34: Yes | M34: It's used is simple, easy and safe | N34: 1 | O34: easypaisa | P34: sadapay | Q34: easypaisa | R34: easypaisa | S34: sadapay | T34: sadapay | U34: jazzcash | V34: sadapay | W34: jazzcash | X34: No | Y34: i have not seen this ad | Z34: To y Used digital app for payments | AA34: 4
A35: amber | B35: Female | C35: 42 -53 | D35: Lahore | E35: jazzcash | F35: jazzcash | G35: jazzcash | H35: jazzcash | I35: 2 | J35: easypaisa | K35: jazzcash is easy to use and am used to it now | L35: Yes | M35: for emergency if i need money to transfer anytime or anyone wants to return back my money | N35: 10 | O35: easypaisa | P35: jazzcash | Q35: jazzcash | R35: jazzcash | S35: jazzcash | T35: jazzcash | U35: jazzcash | V35: jazzcash | W35: jazzcash | X35: Yes | Y35: easypaisa | Z35: as everyone is using that app so transferred to their specific app through sadapay | AA35: 10
A36: Naseer Ahmad | B36: Male | C36: 18 - 29 | D36: Jhang | E36: easypaisa | F36: jazzcash,easypaisa | G36: jazzcash,easypaisa | H36: easypaisa | I36: 6 | J36: jazzcash | K36: For service issues | L36: Yes | M36: For good service | N36: 7 | O36: jazzcash | P36: easypaisa | Q36: easypaisa | R36: easypaisa | S36: jazzcash | T36: easypaisa | U36: jazzcash | V36: jazzcash | W36: nayapay | X36: Maybe | Y36: easypaisa | Z36: It means this app is trustable and having fast service | AA36: 7
A37: Mahnoor | B37: Female | C37: 18 - 29 | D37: Lahore | E37: jazzcash | F37: jazzcash,nayapay | G37: jazzcash,nayapay | H37: jazzcash | I37: 4 | J37: jazzcash | K37: Is it good for myself and working fastly | L37: Yes | M37: Fast service | N37: 5 | O37: nayapay | P37: jazzcash | Q37: jazzcash | R37: jazzcash | S37: jazzcash | T37: jazzcash | U37: jazzcash | V37: jazzcash | W37: nayapay | X37: Maybe | Y37: i have not seen this ad | Z37: To provide great service and advertising | AA37: 3
A38: Abdul hafeez | B38: Male | C38: 18 - 29 | D38: Sadiqabad | E38: jazzcash | F38: jazzcash | G38: jazzcash | H38: jazzcash | I38: 7 | J38: jazzcash | K38: Its easy to me | L38: No | M38: Yes | N38: 1 | O38: jazzcash | P38: jazzcash | Q38: sadapay | R38: jazzcash | S38: jazzcash | T38: jazzcash | U38: jazzcash | V38: jazzcash | W38: jazzcash | X38: Yes | Y38: easypaisa | Z38: Not meaningful | AA38: 1
A39: Amna Zohaib | B39: Female | C39: 30 - 41 | D39: Lahore | E39: jazzcash | F39: jazzcash | G39: jazzcash,easypaisa | H39: jazzcash | I39: 6 | J39: easypaisa | K39: It's convenient for me | L39: Yes | M39: Not any big reason just easy to use this app | N39: 5 | O39: easypaisa | P39: jazzcash | Q39: sadapay | R39: jazzcash | S39: jazzcash | T39: jazzcash | U39: jazzcash | V39: jazzcash | W39: jazzcash | X39: No | Y39: i have not seen this ad | Z39: Yess | AA39: 1
A40: Sania | B40: Female | C40: 18 - 29 | D40: Lahore | E40: nayapay | F40: jazzcash,easypaisa,sadapay,nayapay | G40: jazzcash,nayapay | H40: nayapay | I40: 7 | J40: nayapay | K40: Didn’t switch | L40: Yes | M40: Easy to use | N40: 9 | O40: jazzcash | P40: nayapay | Q40: nayapay | R40: jazzcash | S40: nayapay | T40: nayapay | U40: jazzcash | V40: nayapay | W40: nayapay | X40: Maybe | Y40: jazzcash | Z40: Easy to use for everyone | AA40: 6
... A45: Zohaib javaid | B45: Male | C45: 30 - 41 | D45: Lahore | E45: jazzcash | F45: jazzcash | G45: jazzcash | H45: jazzcash | I45: 7 | J45: easypaisa | K45: No specific reason | L45: Yes | M45: Its more realibe | N45: 9 | O45: easypaisa | P45: jazzcash | Q45: easypaisa | R45: jazzcash | S45: jazzcash | T45: jazzcash | U45: easypaisa | V45: jazzcash | W45: easypaisa | X45: No | Y45: i have not seen this ad | Z45: I have no idea | AA45: 5
A46: Aroona | B46: Female | C46: 42 -53 | D46: Lahore | E46: easypaisa | F46: jazzcash,easypaisa | G46: jazzcash,easypaisa | H46: easypaisa | I46: 7 | J46: jazzcash | K46: Sometime app not responding | L46: Yes | M46: I m use to of this app too much | N46: 8 | O46: jazzcash | P46: easypaisa | Q46: easypaisa | R46: easypaisa | S46: easypaisa | T46: easypaisa | U46: easypaisa | V46: easypaisa | X46: Maybe | Y46: i have not seen this ad | Z46: I haven't seen bcz I didn't watch tv | AA46: 6
A47: Muhammad Tayyab | B47: Male | C47: 18 - 29 | D47: Lahore | E47: jazzcash | F47: jazzcash,easypaisa | G47: jazzcash,easypaisa | H47: jazzcash | I47: 7 | J47: easypaisa | K47: Quickest | L47: Yes | M47: Availability allover | N47: 10 | O47: bankingapp | P47: jazzcash | Q47: easypaisa | R47: easypaisa | S47: easypaisa | T47: easypaisa | U47: jazzcash | V47: easypaisa | W47: easypaisa | X47: Maybe | Y47: i have not seen this ad | Z47: Discussion about eidi | AA47: 1
A48: Dawood humayuon | B48: Male | C48: 18 - 29 | D48: Lahore | E48: easypaisa | F48: jazzcash,easypaisa | G48: jazzcash,easypaisa | H48: easypaisa | I48: 7 | J48: sadapay | K48: Easy payment method / transaction | L48: Yes | M48: Privacy policy | N48: 10 | O48: jazzcash | P48: easypaisa | Q48: easypaisa | R48: easypaisa | S48: easypaisa | T48: easypaisa | U48: easypaisa | V48: nayapay | W48: sadapay | X48: No | Y48: i have not seen this ad | Z48: Make it short video not long | AA48: 5
A49: Muhammad Afzal Faheem | B49: Male | C49: 30 - 41 | D49: Lahore | E49: easypaisa | F49: jazzcash,easypaisa | G49: jazzcash,easypaisa | H49: easypaisa | I49: 7 | J49: jazzcash | K49: The make the payment process more convenient | L49: Yes | M49: User-friendly, reliable, and time-saving | N49: 10 | O49: jazzcash | P49: easypaisa | Q49: easypaisa | R49: easypaisa | S49: easypaisa | T49: easypaisa | U49: easypaisa | V49: easypaisa | W49: easypaisa | X49: Yes | Y49: easypaisa | Z49: To switch to digital platform for transactions | AA49: 6
A50: Muhammad Mohsin Akram | B50: Male | C50: 18 - 29 | D50: Lahore | E50: easypaisa | F50: jazzcash,easypaisa | G50: jazzcash,easypaisa | H50: easypaisa | I50: 7 | J50: jazzcash | K50: No extra features in this app | L50: Yes | M50: Very good and attractive | N50: 8 | O50: bankingapp | P50: easypaisa | Q50: jazzcash | R50: easypaisa | S50: easypaisa | T50: easypaisa | U50: easypaisa | V50: easypaisa | W50: easypaisa | X50: Yes | Y50: jazzcash | Z50: Na | AA50: 3
A51: Aliza khan | B51: Female | C51: 18 - 29 | D51: Lahore | E51: easypaisa | F51: easypaisa | G51: easypaisa | H51: easypaisa | I51: 4 | J51: sadapay | K51: No specific reason | L51: Yes | M51: It’s easy to use | N51: 7 | O51: easypaisa | P51: jazzcash | Q51: easypaisa | R51: easypaisa | S51: easypaisa | T51: easypaisa | U51: jazzcash | V51: easypaisa | W51: easypaisa | X51: Yes | Y51: easypaisa | Z51: Don’t remember | AA51: 3
A52: Ikram mir | B52: Male | C52: 18 - 29 | D52: Lahore | E52: sadapay | F52: easypaisa,sadapay | G52: sadapay | H52: sadapay | I52: 5 | J52: easypaisa | K52: Extra use | L52: Yes | M52: Easy transfer | N52: 3 | O52: easypaisa | P52: easypaisa | Q52: sadapay | R52: easypaisa | S52: easypaisa | T52: sadapay | U52: sadapay | V52: sadapay | W52: nayapay | X52: No | Y52: i have not seen this ad | Z52: Money transfer | AA52: 1
A53: Talha | B53: Male | C53: 18 - 29 | D53: Lahore | E53: easypaisa | F53: sadapay | G53: sadapay | H53: sadapay | I53: 3 | J53: easypaisa | K53: Service | L53: Yes | M53: Easy to use | N53: 10 | O53: bank | P53: sadapay | Q53: sadapay | R53: easypaisa | S53: sadapay | T53: sadapay | U53: easypaisa | V53: sadapay | W53: sadapay | X53: Yes | Y53: easypaisa | Z53: Easy to transfer and it’s fast | AA53: 10
A54: jk | B54: Male | C54: 18 - 29 | D54: Lahore | E54: jazzcash | F54: jazzcash,easypaisa,sadapay | G54: jazzcash,sadapay | H54: jazzcash | I54: 6 | J54: easypaisa | K54: UI | L54: Yes | M54: use kerny me easy hai | N54: 9 | O54: nayapay | P54: nayapay | Q54: jazzcash | R54: jazzcash | S54: jazzcash | T54: nayapay | U54: jazzcash | V54: nayapay | W54: nayapay | X54: Yes | Y54: easypaisa | Z54: Promoting easypaisa app | AA54: 9
A55: Nasreen | B55: Female | C55: 42 -53 | D55: Lahore | E55: easypaisa | F55: easypaisa | G55: easypaisa,sadapay | H55: easypaisa | I55: 6 | J55: easypaisa | K55: Hight security | L55: Yes | M55: Service | N55: 10 | O55: sadapay | P55: easypaisa | Q55: easypaisa | R55: easypaisa | S55: easypaisa | T55: easypaisa | U55: easypaisa | V55: easypaisa | W55: easypaisa | X55: Yes | Y55: easypaisa | Z55: Easy to use and safe for all transfers | AA55: 10
A56: Ashraf Ali | B56: Male | C56: 66 and above | D56: Lahore | E56: jazzcash | F56: jazzcash | G56: jazzcash | H56: jazzcash | I56: 5 | J56: jazzcash | K56: N A | L56: Yes | M56: More common | N56: 5 | O56: easypaisa | P56: jazzcash | Q56: jazzcash | R56: jazzcash | S56: jazzcash | T56: easypaisa | U56: jazzcash | V56: easypaisa | W56: easypaisa | X56: Maybe | Y56: i have not seen this ad | Z56: N A | AA56: 5
A57: Ramsha Ashfaq | B57: Female | C57: 18 - 29 | D57: Lahore | E57: jazzcash | F57: sadapay | G57: sadapay | H57: sadapay | I57: 1 | J57: jazzcash | K57: None | L57: No | M57: None | N57: 2 | O57: bankingapp | P57: easypaisa | Q57: easypaisa | R57: jazzcash | S57: jazzcash | T57: jazzcash | U57: jazzcash | V57: jazzcash | W57: jazzcash | X57: No | Y57: easypaisa | Z57: That it’s easy to transfer money | AA57: 4
A58: Arfa | B58: Female | C58: 18 - 29 | D58: Lahore | E58: sadapay | F58: sadapay | G58: sadapay | H58: sadapay | I58: 1 | J58: easypaisa | K58: Better application and process | L58: Yes | M58: Its good to even pay internationally for like e.g netflix | N58: 6 | O58: nayapay | P58: sadapay | Q58: sadapay | R58: jazzcash | S58: sadapay | T58: sadapay | U58: sadapay | V58: jazzcash | W58: sadapay | X58: No | Y58: i have not seen this ad | Z58: I haven’t seen the ad | AA58: 3
... A84: Hassan | B84: Male | C84: 18 - 29 | D84: Faisalabad | E84: jazzcash | F84: jazzcash | G84: jazzcash | H84: jazzcash | I84: 5 | J84: easypaisa | K84: Convenience | L84: Yes | M84: Convenience | N84: 10 | O84: easypaisa | P84: jazzcash | Q84: jazzcash | R84: jazzcash | S84: jazzcash | T84: jazzcash | U84: jazzcash | V84: jazzcash | W84: sadapay | X84: No | Y84: i have not seen this ad | Z84: Don't know | AA84: 1
A85: Dr. Ata Ul Musawir | B85: Male | C85: 30 - 41 | D85: Lahore | E85: easypaisa | F85: jazzcash,easypaisa | G85: jazzcash,easypaisa | H85: jazzcash | I85: 2 | J85: easypaisa | K85: User-friendly UI, app speed | L85: Yes | M85: User-friendly UI, app speed & having a digital wallet payment option | N85: 8 | O85: easypaisa | P85: jazzcash | Q85: jazzcash | R85: jazzcash | S85: jazzcash | T85: jazzcash | U85: jazzcash | V85: jazzcash | X85: No | Y85: i have not seen this ad | Z85: Don't watch ads or TV | AA85: 5
A86: Zoha ashfaq | B86: Female | C86: 18 - 29 | D86: Lahore | E86: jazzcash | F86: sadapay,nayapay | G86: sadapay | H86: sadapay | I86: 7 | J86: jazzcash | K86: Wese hi | L86: Yes | M86: Idk | N86: 8 | O86: jazzcash | P86: jazzcash | Q86: jazzcash | R86: jazzcash | S86: jazzcash | T86: jazzcash | U86: jazzcash | V86: jazzcash | W86: jazzcash | X86: No | Y86: jazzcash | Z86: Lame | AA86: 1
A87: noor fatima | B87: Female | C87: 18 - 29 | D87: Lahore | E87: nayapay | F87: nayapay | G87: nayapay | H87: nayapay | I87: 7 | J87: nayapay | K87: I did not switch to another app because I am satisfied with my current primary app. It is easy to use, reliable, and meets all my needs. I feel comfortable using it, so I don’t see any strong reason to switch. | L87: Yes | M87: I am satisfied with my current primary app. It is easy to use, reliable, and meets all my needs. I feel comfortable using it, so I don’t see any strong reason to switch. | N87: 10 | O87: other | P87: nayapay | Q87: nayapay | R87: nayapay | S87: nayapay | T87: nayapay | U87: nayapay | V87: nayapay | W87: nayapay | X87: No | Y87: i have not seen this ad | Z87: its is easy , fast | AA87: 5
A88: Ahmer Amin | B88: Male | C88: 18 - 29 | D88: Lahore | E88: hbl | F88: jazzcash,easypaisa | G88: jazzcash | H88: jazzcash | I88: 5 | J88: easypaisa | K88: alternative app | L88: Yes | M88: need of the hour | N88: 8 | O88: nayapay | P88: easypaisa | Q88: jazzcash | R88: easypaisa | S88: easypaisa | T88: easypaisa | U88: easypaisa | V88: jazzcash | W88: easypaisa | X88: No | Y88: i have not seen this ad | Z88: not warched this ad | AA88: 4
A89: Minahil shahbaz | B89: Female | C89: 18 - 29 | D89: Lahore | E89: jazzcash | F89: jazzcash | G89: jazzcash | H89: jazzcash | I89: 1 | J89: jazzcash | K89: Reason for switching | L89: No | M89: I am nit using this app so don't asked to prefer | N89: 5 | O89: easypaisa | P89: easypaisa | Q89: jazzcash | R89: jazzcash | S89: easypaisa | T89: nayapay | U89: jazzcash | V89: easypaisa | W89: easypaisa | X89: Maybe | Y89: i have not seen this ad | Z89: Easypaisa transfer money very easily i think so | AA89: 1
A90: Ruttaba Ashraf | B90: Female | C90: 18 - 29 | D90: Lahore | E90: easypaisa | F90: easypaisa,sadapay,nayapay | G90: easypaisa,sadapay,nayapay | H90: nayapay | I90: 7 | J90: easypaisa | K90: Nayapay have more features than easypaisa | L90: Yes | M90: Nayapay Have Various Features and specifications | N90: 10 | O90: sadapay | P90: nayapay | Q90: sadapay | R90: easypaisa | S90: nayapay | T90: nayapay | U90: nayapay | V90: nayapay | W90: nayapay | X90: No | Y90: easypaisa | Z90: If anyone has not handed in cash, they can transfer it no worries at all. | AA90: 5
A91: Mian Asim | B91: Male | C91: 42 -53 | D91: Lahore | E91: jazzcash | F91: jazzcash,easypaisa | G91: jazzcash,easypaisa | H91: easypaisa | I91: 7 | J91: jazzcash | K91: Fraud detection | L91: No | M91: Secure | N91: 9 | O91: sadapay | P91: easypaisa | Q91: easypaisa | R91: easypaisa | S91: easypaisa | T91: easypaisa | U91: easypaisa | V91: easypaisa | W91: sadapay | X91: No | Y91: i have not seen this ad | Z91: not ever seen | AA91: 1
A92: Hafiz Irtaza Aslam | B92: Male | C92: 18 - 29 | D92: Lahore | E92: jazzcash | F92: jazzcash,easypaisa,sadapay,nayapay | G92: jazzcash,easypaisa,sadapay,nayapay | H92: jazzcash | I92: 7 | J92: jazzcash | K92: I haven’t switched to any single app. In fact, I use multiple apps because it allows me to handle payments from different wallets, making it easier and more convenient for my clients. This way, there’s no issue in receiving payments. | L92: Yes | M92: I prefer to keep using these apps because they provide flexibility for my clients. Each client might have a different preferred payment method or wallet, and by using multiple apps, I ensure smooth transactions, reduce friction, and make it as convenient as possible for them. | N92: 8 | O92: jazzcash | P92: jazzcash | Q92: jazzcash | R92: jazzcash | S92: jazzcash | T92: jazzcash | U92: jazzcash | V92: jazzcash | W92: jazzcash | X92: Yes | Y92: jazzcash | Z92: The main message of this ad is that even when traditional cash sources like ATMs aren’t working, you can still easily send or receive Eidi (gift money) through the Eidipaisa mobile wallet. It emphasizes convenience and ensures you never miss out on giving or receiving Eidi, even if physical cash is unavailable. | AA92: 5
A93: Raheeq Sharif | B93: Male | C93: 18 - 29 | D93: Lahore | E93: jazzcash | F93: jazzcash,easypaisa,sadapay,nayapay | G93: jazzcash,easypaisa,sadapay,nayapay | H93: nayapay | I93: 7 | J93: jazzcash | K93: Easy to use | L93: Yes | M93: No any charges | N93: 10 | O93: nayapay | P93: nayapay | Q93: nayapay | R93: nayapay | S93: nayapay | T93: nayapay | U93: nayapay | V93: nayapay | W93: nayapay | X93: Yes | Y93: nayapay | Z93: Online eidi | AA93: 10
A94: Hamza | B94: Male | C94: 18 - 29 | D94: Lahore | E94: jazzcash | F94: jazzcash,easypaisa | G94: jazzcash,easypaisa | H94: jazzcash | I94: 7 | J94: jazzcash | K94: No switch | L94: Yes | M94: Instand payment | N94: 10 | O94: easypaisa | P94: jazzcash | Q94: jazzcash | R94: jazzcash | S94: jazzcash | T94: jazzcash | U94: jazzcash | V94: jazzcash | W94: jazzcash | X94: No | Y94: i have not seen this ad | Z94: I don't no | AA94: 1
A95: esha | B95: Female | C95: 18 - 29 | D95: Lahore | E95: jazzcash | F95: jazzcash,easypaisa,sadapay | G95: jazzcash,sadapay | H95: jazzcash | I95: 6 | J95: jazzcash | K95: Never switched | L95: Yes | M95: Can send money to local stores, places easily | N95: 6 | O95: easypaisa | P95: easypaisa | Q95: easypaisa | R95: easypaisa | S95: sadapay | T95: easypaisa | U95: sadapay | V95: sadapay | W95: sadapay | X95: Maybe | Y95: easypaisa | Z95: Sending money to your loved ones to make them feel loved and special | AA95: 4
A96: Ali hussnain | B96: Male | C96: 18 - 29 | D96: Lahore | E96: jazzcash | F96: sadapay,nayapay | G96: sadapay,nayapay | H96: nayapay | I96: 7 | J96: jazzcash | K96: Easy transfer and no chances of scam | L96: Yes | M96: I can use it globally and have a safe payment method | N96: 10 | O96: easypaisa | P96: nayapay | Q96: nayapay | R96: easypaisa | S96: nayapay | T96: sadapay | U96: nayapay | V96: nayapay | W96: sadapay | X96: Yes | Y96: easypaisa | Z96: To support digital wallets | AA96: 7
A97: Muhammad Saqib Shoaib | B97: Male | C97: 18 - 29 | D97: Lahore | E97: jazzcash | F97: jazzcash | G97: jazzcash,easypaisa | H97: jazzcash | I97: 7 | J97: jazzcash | K97: Jazz cash | L97: Yes | M97: Best Services | N97: 2 | O97: easypaisa | P97: jazzcash | Q97: jazzcash | R97: easypaisa | S97: jazzcash | T97: easypaisa | U97: easypaisa | V97: jazzcash | W97: jazzcash | X97: Yes | Y97: jazzcash | Z97: Yes | AA97: 1
... A131: Haider Zulfiqar | B131: Male | C131: 18 - 29 | D131: Lahore | E131: easypaisa | F131: jazzcash,easypaisa,nayapay | G131: jazzcash,easypaisa | H131: easypaisa | I131: 7 | J131: easypaisa | K131: More options available specifically like Mtag payments | L131: Yes | M131: Easy to use and even now scan and pay is getting normal at local stores so no need to carry cash | N131: 8 | O131: jazzcash | P131: easypaisa | Q131: easypaisa | R131: easypaisa | S131: easypaisa | T131: easypaisa | U131: easypaisa | V131: easypaisa | W131: nayapay | X131: Yes | Y131: easypaisa | Z131: Main message was to use Easypaisa to easily send eidi to love ones | AA131: 9
A132: Khalid Niazi | B132: Male | C132: 54 - 65 | D132: London | E132: jazzcash | F132: jazzcash | G132: jazzcash | H132: jazzcash | I132: 4 | J132: easypaisa | K132: easy to use | L132: Yes | M132: easy to use | N132: 8 | O132: easypaisa | P132: jazzcash | Q132: jazzcash | R132: jazzcash | S132: jazzcash | T132: easypaisa | U132: jazzcash | V132: jazzcash | X132: No | Y132: easypaisa | Z132: conviniance | AA132: 6
A133: Muhammad Anas | B133: Male | C133: 18 - 29 | D133: Lahore | E133: jazzcash | F133: jazzcash,easypaisa,sadapay | G133: jazzcash,easypaisa,sadapay | H133: sadapay | I133: 1 | J133: jazzcash | K133: For better service | L133: Yes | M133: Sadapay has fastest payment transfer method. | N133: 9 | O133: easypaisa | P133: sadapay | Q133: sadapay | R133: jazzcash | S133: sadapay | T133: sadapay | U133: sadapay | V133: sadapay | W133: sadapay | X133: No | Y133: jazzcash | Z133: This is the public awareness ad to use the app that is more secure and reliable for you internet banking | AA133: 5
A134: Anny | B134: Female | C134: 18 - 29 | D134: Islamabad | E134: easypaisa | F134: easypaisa | G134: easypaisa | H134: easypaisa | I134: 4 | J134: easypaisa | K134: It is the first app I used | L134: Yes | M134: Payment | N134: 3 | O134: easypaisa | P134: easypaisa | Q134: easypaisa | R134: easypaisa | S134: easypaisa | T134: easypaisa | U134: easypaisa | V134: easypaisa | W134: sadapay | X134: No | Y134: easypaisa | Z134: You can give online Eidi now without excuses | AA134: 1
A135: Hussian | B135: Male | C135: 18 - 29 | D135: Lahore | E135: jazzcash | F135: nayapay | G135: nayapay | H135: nayapay | I135: 7 | J135: nayapay | K135: N/A | L135: Yes | M135: Easy | N135: 9 | O135: jazzcash | P135: nayapay | Q135: nayapay | R135: jazzcash | S135: nayapay | T135: nayapay | U135: nayapay | V135: nayapay | W135: nayapay | X135: Yes | Y135: easypaisa | Z135: Promotion | AA135: 5
A136: Taah Mahmood | B136: Male | C136: 18 - 29 | D136: Lahore | E136: jazzcash | F136: jazzcash,nayapay | G136: jazzcash,nayapay | H136: nayapay | I136: 3 | J136: jazzcash | K136: I got a physical card free of cost from nayapay so i switched my services from jazz cash to nayapay as it was more convenient for me. | L136: Yes | M136: It is convenient for me to use as i have physical card. And this app has built my trust overtime. Once i got double charged for the same thing i raised the concern with their customer service and they refunded the amount within 2 or 3 hours | N136: 7 | O136: bankingapp | P136: nayapay | Q136: nayapay | R136: jazzcash | S136: nayapay | T136: nayapay | U136: jazzcash | V136: nayapay | W136: nayapay | X136: Maybe | Y136: jazzcash | Z136: The main message in this add was ro potray how easy it is to transfer the funds using digital wallet. | AA136: 6
A137: Sameer | B137: Male | C137: 18 - 29 | D137: Lahore | E137: sadapay | F137: sadapay | G137: sadapay | H137: sadapay | I137: 6 | J137: easypaisa | K137: Better app quality and easy money transfer | L137: Yes | M137: Easy transfers | N137: 5 | O137: nayapay | P137: sadapay | Q137: sadapay | R137: easypaisa | S137: easypaisa | T137: sadapay | U137: sadapay | V137: sadapay | W137: sadapay | X137: No | Y137: i have not seen this ad | Z137: None | AA137: 5
A138: Maarib Naqvi | B138: Male | C138: 18 - 29 | D138: Lahore | E138: jazzcash | F138: jazzcash,sadapay | G138: jazzcash | H138: jazzcash | I138: 7 | J138: sadapay | K138: Its shit | L138: Yes | M138: Shit but better than shit | N138: 5 | O138: easypaisa | P138: jazzcash | Q138: easypaisa | R138: jazzcash | S138: easypaisa | T138: jazzcash | U138: easypaisa | V138: jazzcash | W138: jazzcash | X138: Yes | Y138: easypaisa | Z138: Convenience of their app | AA138: 7
A139: Fahad | B139: Male | C139: 18 - 29 | D139: Lahore | E139: easypaisa | F139: jazzcash,easypaisa,sadapay,nayapay | G139: easypaisa,nayapay | H139: easypaisa | I139: 7 | J139: jazzcash | K139: Because JazzCash automatically subscribe services through my account and payment deducts automatically | L139: Yes | M139: Because easypaisa is mostly available everywhere and that don't deduct amount without our permission like JazzCash do. | N139: 9 | O139: nayapay | P139: easypaisa | Q139: nayapay | R139: jazzcash | S139: easypaisa | T139: easypaisa | U139: easypaisa | V139: easypaisa | W139: nayapay | X139: Maybe | Y139: easypaisa | Z139: Advertising the app's feature | AA139: 7
A140: Hanzala Ahmad | B140: Male | C140: 18 - 29 | D140: Lahore | E140: easypaisa | F140: easypaisa | G140: easypaisa | H140: easypaisa | I140: 7 | J140: jazzcash | K140: Very good and reliable. | L140: Yes | M140: main easypaisa app ko refer nahin karta jab payment karenge Apne payment katati hai Maine charges Rakh liye hain isliye bus main ek majburi ki tahat isko use karta hun jashcash Mera Nahin hai | N140: 1 | O140: sadapay | P140: easypaisa | Q140: jazzcash | R140: jazzcash | S140: easypaisa | T140: jazzcash | U140: easypaisa | V140: easypaisa | W140: sadapay | X140: No | Y140: easypaisa | Z140: You were trying to find out which app people use the most. | AA140: 10
A141: Momina | B141: Female | C141: 18 - 29 | D141: Lahore | E141: jazzcash | F141: jazzcash,easypaisa | G141: jazzcash | H141: jazzcash | I141: 3 | J141: easypaisa | K141: Wanted to try a new one | L141: Yes | M141: Easy to use | N141: 6 | O141: easypaisa | P141: jazzcash | Q141: easypaisa | R141: jazzcash | S141: jazzcash | T141: jazzcash | U141: jazzcash | V141: jazzcash | W141: jazzcash | X141: No | Y141: i have not seen this ad | Z141: I haven’t watched the add yet | AA141: 5
A142: 5G services Jazz and warid? | B142: Male | C142: 54 - 65 | D142: Lahore | E142: jazzcash | F142: jazzcash,easypaisa | G142: jazzcash | H142: jazzcash | I142: 7 | J142: easypaisa | K142: Better services | L142: Yes | M142: Good response | N142: 1 | O142: sadapay | P142: jazzcash | Q142: jazzcash | R142: nayapay | S142: jazzcash | T142: jazzcash | U142: jazzcash | V142: jazzcash | W142: jazzcash | X142: No | Y142: i have not seen this ad | Z142: Good work | AA142: 10
A143: Mujtaba Javed | B143: Male | C143: 18 - 29 | D143: Lahore | E143: sadapay | F143: jazzcash,easypaisa,sadapay,nayapay | G143: jazzcash,easypaisa,sadapay,nayapay | H143: nayapay | I143: 7 | J143: jazzcash | K143: A virtual card | L143: Yes | M143: Friendly interface + no IBFT charges | N143: 8 | O143: easypaisa | P143: sadapay | Q143: jazzcash | R143: jazzcash | S143: nayapay | T143: nayapay | U143: jazzcash | V143: nayapay | W143: nayapay | X143: Yes | Y143: easypaisa | Z143: To communicate that it is far more easy to send money instead of hassling for cash through atms via easypaisa | AA143: 8
A144: Aurangzeb | B144: Male | C144: 18 - 29 | D144: Lahore | E144: jazzcash | F144: jazzcash | G144: jazzcash | H144: jazzcash | I144: 2 | J144: easypaisa | K144: Wanted to | L144: Yes | M144: Efficient | N144: 6 | O144: bankingapp | P144: jazzcash | Q144: jazzcash | R144: jazzcash | S144: jazzcash | T144: nayapay | U144: jazzcash | V144: jazzcash | W144: nayapay | X144: No | Y144: i have not seen this ad | Z144: Haven’t seen the ad | AA144: 5
... A151: Ghani Khan | B151: Male | C151: 18 - 29 | D151: Faisalabad | E151: jazzcash | F151: jazzcash,easypaisa,sadapay,nayapay | G151: jazzcash,sadapay,nayapay | H151: jazzcash | I151: 7 | J151: jazzcash | K151: None | L151: Yes | M151: User friendly | N151: 7 | O151: easypaisa | P151: jazzcash | Q151: easypaisa | R151: easypaisa | S151: easypaisa | T151: easypaisa | U151: jazzcash | V151: jazzcash | W151: nayapay | X151: Maybe | Y151: jazzcash | Z151: Easy access | AA151: 5

Sheet Form Responses 1
A1: Timestamp | B1: Respondent Profile: Name | C1: Gender | D1: What is your age group? | E1: What is your current city of residence? | F1: When thinking about mobile wallets and digital payment apps in Pakistan, what is the first name that comes into your mind? (JazzCash, Easypaisa, etc.) | G1: 2.1) Which of these digital payment apps have you ever used personally? | H1: 2.2) Which of these apps are you currently using? | I1: 2.3) Of all the apps you use, which one do you consider as your PRIMARY (most used) digital payment app? | J1: 2.4) For how long have you been using your PRIMARY digital payment app? | K1: 2.5) What was the app name (most used before switching to the current PRIMARY app)? Please select an app DIFFERENT from your current primary app. | L1: 2.6) What were the reasons for you to switch to your current primary app | M1: 2.7) Do you plan to keep using this app in future as well? | N1: 2.8) For what reasons do you prefer to keep using this app? | O1: 2.9) Based on your PRIMARY digital payment app, how likely is it for you to recommend the brand to your family, friends, and relatives? | P1: 3.1) Suppose the apps you are currently using were not available; which other app, if any, would you consider? | Q1: Best app interface and user experience (UX) | R1: Most reliable (least likely to have server/network down issues) | S1: Offers the best discounts, deals, and cashbacks | T1: Good customer service and quick issue resolution | U1: Lowest transaction fees and free inter-bank fund transfers (IBFT) | V1: Strongest security features | W1: Easiest and fastest process for opening an account or ordering a physical debit card | X1: Best app for international payments | Y1: 5.1) Have you seen the advertisement above on TV recently or not? | Z1: 5.2 ) What digital payment app was this ad for? | AA1: 5.3) In your own words, what was the main message of this ad? (Please be specific; avoid general answers like 'it is a good app.' | AB1: 5.4) To what extent did you like this ad?
A2: 46099.533 | B2: Gulfam | C2: Male | D2: 36-45 | E2: Lahore | F2: easypaisa | G2: JazzCash, Easypaisa, Sadapay | H2: Easypaisa | I2: Easypais | J2: 18-24 months | K2: Sadapay | L2: account blockage and trust issues | M2: Yes | N2: easier to manage small transactions and payments like payment of bills etc | O2: 9 | P2: Jazz cash | Q2: Sadapay | R2: Easypaisa | S2: Jazz Cash | T2: Sadapay | U2: Easypaisa | V2: Easypaisa | W2: Easypaisa | X2: Easypaisa | Y2: No | Z2: Easypaisa | AA2: have not seen this ad | AB2: 1
A3: 46109.93 | B3: waleed | C3: Male | D3: 18 - 29 | E3: Lahore | F3: Easypaisa | G3: Easypaisa | H3: Easypaisa | I3: Easypais | J3: 9-12 months | K3: Easypaisa | L3: All government platforms related payments can be initiate under one platform with best user experience | M3: Yes | N3: Best user interface and user experience | O3: 9 | P3: Zindagi | Q3: Easypaisa | R3: Easypaisa | S3: Easypaisa | T3: Easypaisa | U3: Easypaisa | V3: Easypaisa | W3: Easypaisa | X3: Easypaisa | Y3: Yes | Z3: Easypaisa | AA3: You can transfer money from anywhere in your easy paisa account and it'll be transferred in your account immediately without any disruption | AB3: 5
A4: 46109.933 | B4: Talha | C4: Male | D4: 18 - 29 | E4: Lahore | F4: Sadapay | G4: Sadapay | H4: Sadapay | I4: Sadapay | J4: 9-12 months | K4: Easypaisa | L4: Easy to assess | M4: Yes | N4: Easy to assess | O4: 10 | P4: Meezan | Q4: Sadapay | R4: Nayapay | S4: Easypaisa | T4: Easypaisa | U4: Sadapay | V4: Easypaisa | W4: Sadapay | X4: Sadapay | Y4: Yes | Z4: Easypaisa | AA4: Easy to transfer | AB4: 10
A5: 46109.938 | B5: Jawad Waseem | C5: Male | D5: 18 - 29 | E5: Lahore | F5: Easypaisa | G5: Jazzcash, Easypaisa, Nayapay | H5: Easypaisa | I5: Easypais | J5: More than 2 years | K5: NAYAPAY | L5: More options | M5: Yes | N5: Connectivity and | O5: 7 | P5: Nayapay | Q5: Easypaisa | R5: Easypaisa | S5: Easypaisa | T5: Easypaisa | U5: Easypaisa | V5: Easypaisa | W5: Easypaisa | X5: Easypaisa | Y5: Yes | Z5: Easypaisa | AA5: Easy transfer | AB5: 5
A6: 46109.942 | B6: Abdullah | C6: Male | D6: 18 - 29 | E6: Lahore | F6: Easypaisa | G6: Jazzcash, Easypaisa, Sadapay, Nayapay | H6: Easypaisa | I6: Easypais | J6: 18-24 months | K6: Jazz cash | L6: Bad service | M6: Yes | N6: Fast service | O6: 8 | P6: Jazz cash | Q6: Easypaisa | R6: Jazz Cash | S6: Jazz Cash | T6: Easypaisa | U6: Easypaisa | V6: Easypaisa | W6: Easypaisa | X6: Easypaisa | Y6: Yes | Z6: Easypaisa | AA6: Make digital wallet for small transactions | AB6: 7
A7: 46109.943 | B7: Muhammad saad ahmad | C7: Male | D7: 18 - 29 | E7: Lahore | F7: Jazzcash | G7: Easypaisa | H7: Easypaisa | I7: Easypais | J7: 13-18 months | K7: NAYAPAY | L7: Wasn't reliable | M7: Yes | N7: Easy to use | O7: 9 | P7: Nayapay | Q7: Nayapay | R7: Jazz Cash | S7: Easypaisa | T7: Easypaisa | U7: Easypaisa | V7: Jazz Cash | W7: Nayapay | X7: Jazz Cash | Y7: No | Z7: I have not seen this ad | AA7: That the transfer of money can be made remotely and easily | AB7: 10
A8: 46109.944 | B8: Mubashir hassan | C8: Male | D8: 18 - 29 | E8: Lahore | F8: Easypaisa | G8: Easypaisa | H8: Jazz cash, Easypaisa | I8: Easypais | J8: More than 2 years | K8: Jazz cash | L8: User experience | M8: Yes | N8: User experience and user interface | O8: 7 | P8: Banking app like UBL cuz sadapay and nayapay are third party apps | Q8: Jazz Cash | R8: Jazz Cash | S8: Jazz Cash | T8: Jazz Cash | U8: Easypaisa | V8: Jazz Cash | W8: Jazz Cash | X8: Jazz Cash | Y8: Yes | Z8: Jazzcash | AA8: They communicate. With customers... | AB8: 7
A9: 46109.944 | B9: Ayesha | C9: Female | D9: 18 - 29 | E9: Lahore | F9: Nayapay | G9: Jazzcash, Sadapay, Nayapay | H9: Jazz cash, Nayapay | I9: Nayapay | J9: More than 2 years | K9: Jazz cash | L9: It's secure and easy to use. | M9: Yes | N9: It's easy to use. | O9: 9 | P9: Jazz cash | Q9: Nayapay | R9: Nayapay | S9: Jazz Cash | T9: Nayapay | U9: Nayapay | V9: Nayapay | W9: Nayapay | X9: Sadapay | Y9: Maybe | Z9: Easypaisa | AA9: Digital wallet apps awareness | AB9: 10
A10: 46109.945 | B10: Kainat | C10: Female | D10: 18 - 29 | E10: Lahore | F10: JazzCash | G10: Jazzcash, Sadapay | H10: Jazz cash | I10: Jazzcash | J10: 9-12 months | K10: Jazz cash | L10: I didn't switch | M10: Yes | N10: Easily manageable and reliable | O10: 10 | P10: Bank Account App | Q10: Jazz Cash | R10: Jazz Cash | S10: Jazz Cash | T10: Jazz Cash | U10: Jazz Cash | V10: Jazz Cash | W10: Jazz Cash | X10: Jazz Cash | Y10: Maybe | Z10: I have not seen this ad | AA10: I haven't seen this ad | AB10: 1
A11: 46109.953 | B11: Muhammad Danish Zafar | C11: Male | D11: 18 - 29 | E11: Lahore | F11: Sada pay | G11: Sadapay | H11: Jazz cash, Easypaisa, Sadapay | I11: Sadapay | J11: More than 2 years | K11: Easypaisa | L11: Most of the time servers down | M11: Yes | N11: International transactions | O11: 8 | P11: Jazz cash | Q11: Jazz Cash | R11: Jazz Cash | S11: Jazz Cash | T11: Sadapay | U11: Sadapay | V11: Jazz Cash | W11: Jazz Cash | X11: Sadapay | Y11: Maybe | Z11: Easypaisa | AA11: Payment transfer | AB11: 5
A12: 46109.956 | B12: Hassan Jehangir | C12: Male | D12: 18 - 29 | E12: Lahore | F12: JazzCash | G12: Jazzcash, Nayapay | H12: Jazz cash, Nayapay | I12: Jazzcash | J12: 9-12 months | K12: Easypaisa | L12: Easy to transfer money instantly | M12: Yes | N12: Instant money transfer and good UI | O12: 10 | P12: Nayapay | Q12: Jazz Cash | R12: Jazz Cash | S12: Jazz Cash | T12: Jazz Cash | U12: Jazz Cash | V12: Jazz Cash | W12: Jazz Cash | X12: Nayapay | Y12: No | Z12: I have not seen this ad | AA12: No idea | AB12: 1
A13: 46109.956 | B13: Rayyan Amin | C13: Female | D13: 18 - 29 | E13: Lahore | F13: Jazzcash | G13: Jazzcash, Easypaisa, Sadapay, Nayapay | H13: Easypaisa | I13: Easypaisa | J13: 13-18 months | K13: Jazz cash | L13: Better services | M13: Yes | N13: Easy transactions | O13: 8 | P13: Sadapay | Q13: Jazz Cash | R13: Easypaisa | S13: Sadapay | T13: Nayapay | U13: Nayapay | V13: Easypaisa | W13: Nayapay | X13: Jazz Cash | Y13: No | Z13: Easypaisa | AA13: Cheap and easy | AB13: 9
... A23: 46109.994 | B23: Shoaib Ahmad | C23: Male | D23: 18 - 29 | E23: Okara | F23: Easypaisa | G23: Jazzcash | H23: Jazz cash | I23: Jazzcash | J23: More than 2 years | K23: Jazz cash | L23: Mostly use jazzcash | M23: Yes | N23: More preferable | O23: 10 | P23: Jazz cash | Q23: Jazz Cash | R23: Nayapay | S23: Easypaisa | T23: Jazz Cash | U23: Nayapay | V23: Jazz Cash | W23: Jazz Cash | X23: Nayapay | Y23: Maybe | Z23: I have not seen this ad | AA23: Jazzcash | AB23: 8
A24: 46109.997 | B24: DAC | C24: Male | D24: 18 - 29 | E24: Lahore | F24: Jazz cash | G24: Jazzcash, Easypaisa, Nayapay | H24: Jazz cash, Nayapay | I24: Jazzcash | J24: More than 2 years | K24: NAYAPAY | M24: Yes | N24: Bcz of its user friendly | O24: 10 | P24: Nayapay | Q24: Jazz Cash | R24: Jazz Cash | S24: Jazz Cash | T24: Jazz Cash | U24: Nayapay | V24: Nayapay | W24: Jazz Cash | X24: Nayapay | Y24: Yes | Z24: Easypaisa | AA24: the convenience of online money transfer for festive gifts | AB24: 7
A25: 46110.011 | B25: Momin Ali | C25: Male | D25: 18 - 29 | E25: Gujrat | F25: Easypaisa | G25: Easypaisa | H25: Easypaisa | I25: Easypaisa | J25: 13-18 months | K25: Easypaisa | L25: Na | M25: Yes | N25: Availability | O25: 9 | P25: Sadapay | Q25: Sadapay | R25: Sadapay | S25: Jazz Cash | T25: Sadapay | U25: Easypaisa | V25: Easypaisa | W25: Easypaisa | X25: Jazz Cash | Z25: Jazzcash | AA25: Dont remember much but i believe related to family n internet | AB25: 9
A26: 46110.014 | B26: Iqra | C26: Female | D26: 18 - 29 | E26: Lahore | F26: Jazz cash | G26: Jazzcash | H26: Jazz cash | I26: Jazzcash | J26: More than 2 years | K26: Jazz cash | L26: No change | M26: Yes | N26: It good | O26: 10 | P26: Easypaisa | Q26: Jazz Cash | R26: Sadapay | S26: Easypaisa | T26: Easypaisa | U26: Jazz Cash | V26: Jazz Cash | W26: Jazz Cash | X26: Jazz Cash | Y26: No | Z26: I have not seen this ad | AA26: No messs7 | AB26: 1
A27: 46110.034 | B27: Amna | C27: Female | D27: 18 - 29 | E27: Lahore | F27: Jazzcash. | G27: Jazzcash | H27: Jazz cash | I27: Jazzcash | J27: 18-24 months | K27: NAYAPAY | L27: Using it for the first time. | M27: Yes | N27: Easy. | O27: 10 | P27: Easypaisa | Q27: Jazz Cash | R27: Jazz Cash | S27: Easypaisa | T27: Jazz Cash | U27: Jazz Cash | V27: Nayapay | W27: Easypaisa | X27: Nayapay | Y27: Yes | Z27: Jazzcash | AA27: Faster money transfer | AB27: 6
A28: 46110.038 | B28: Laiba | C28: Female | D28: 18 - 29 | E28: Lahore | F28: Jazzcash | G28: Jazzcash, Easypaisa, Sadapay | H28: Easypaisa | I28: Easypaisa | J28: 18-24 months | K28: Jazz cash | L28: Idk | M28: Yes | N28: Again idk, just using it. | O28: 9 | P28: Jazz cash | Q28: Easypaisa | R28: Easypaisa | S28: Jazz Cash | T28: Jazz Cash | U28: Easypaisa | V28: Easypaisa | W28: Easypaisa | Y28: No | Z28: I have not seen this ad | AA28: This should not be a required question. | AB28: 1
A29: 46110.042 | B29: Haider shah | C29: Male | D29: 18 - 29 | E29: Lahore | F29: Easy paisa | G29: Easypaisa, Nayapay | H29: Easypaisa | I29: Easypaisa | J29: More than 2 years | K29: Easypaisa | L29: Easypaisa is more essential | M29: Yes | N29: Its safe | O29: 4 | P29: Nayapay | Q29: Easypaisa | R29: Easypaisa | S29: Easypaisa | T29: Easypaisa | U29: Easypaisa | V29: Easypaisa | W29: Easypaisa | X29: Easypaisa | Y29: No | Z29: Easypaisa | AA29: For forcing people to trust online platform | AB29: 3
A30: 46110.125 | B30: Meerab Arshad | C30: Female | D30: 18 - 29 | E30: Raiwind | F30: Jazz cash | G30: Jazzcash | H30: Jazz cash | I30: Jazzcash | J30: 1-4 months | K30: Jazz cash | L30: Jazz cash | M30: Yes | N30: Jazz cash | O30: 1 | P30: Jazz cash | Q30: Jazz Cash | R30: Jazz Cash | S30: Easypaisa | T30: Jazz Cash | U30: Jazz Cash | V30: Jazz Cash | W30: Jazz Cash | X30: Jazz Cash | Y30: Yes | Z30: Jazzcash | AA30: It's very helpful | AB30: 1
A31: 46110.155 | B31: Muhammad Ziad Amir | C31: Male | D31: 18 - 29 | E31: Lahore | F31: Jazzcash | G31: Jazzcash, Easypaisa, Sadapay, Nayapay | H31: Sadapay | I31: Sadapay | J31: 13-18 months | K31: Jazz cash | L31: App errors | M31: Yes | N31: Reliability | O31: 8 | P31: Jazz cash | Q31: Sadapay | R31: Sadapay | S31: Jazz Cash | T31: Jazz Cash | U31: Sadapay | V31: Sadapay | W31: Sadapay | X31: Jazz Cash | Y31: Maybe | Z31: Easypaisa | AA31: Convinient for eidi transaction to your relatives | AB31: 7
A32: 46110.275 | B32: Amina | C32: Female | D32: 30 - 41 | E32: Lahore | F32: Jazzcash | G32: Jazzcash | H32: Jazz cash | I32: Jazzcash | J32: More than 2 years | K32: Jazz cash | L32: Today requirement in this digital world | M32: Yes | N32: One of the easy and fine way to send money around everywhere | O32: 9 | P32: My own wallet | Q32: Jazz Cash | R32: Jazz Cash | S32: Jazz Cash | T32: Jazz Cash | U32: Sadapay | V32: Jazz Cash | W32: Jazz Cash | X32: Jazz Cash | Y32: No | Z32: I have not seen this ad | AA32: Not seen this ad | AB32: 5
A33: 46110.284 | B33: Kanza | C33: Female | D33: 18 - 29 | E33: Lahore | F33: Sadapay | G33: Sadapay | H33: Sadapay | I33: Sadapay | J33: More than 2 years | K33: Jazz cash | L33: I trust Sadapay better maybe cuz its not run locally | M33: Yes | N33: Convenience.. registering/ opening account in Sadapay was easy | O33: 8 | P33: None | Q33: Sadapay | R33: Sadapay | S33: Jazz Cash | T33: Sadapay | U33: Sadapay | V33: Sadapay | W33: Sadapay | X33: Sadapay | Y33: No | Z33: I have not seen this ad | AA33: Accessibility, inclusivity | AB33: 7
A34: 46110.315 | B34: Rana Ali Hassan | C34: Male | D34: 18 - 29 | E34: Lahore | F34: Easypaisa | G34: Easypaisa, Sadapay | H34: Sadapay | I34: Sadapay | J34: 5-8 months | K34: Sadapay | L34: Sometimes payment stuck and also some error are happened | M34: Yes | N34: It's used is simple, easy and safe | O34: 1 | P34: Easypaisa | Q34: Sadapay | R34: Easypaisa | S34: Easypaisa | T34: Sadapay | U34: Sadapay | V34: Jazz Cash | W34: Sadapay | X34: Jazz Cash | Y34: No | Z34: I have not seen this ad | AA34: To y Used digital app for payments | AB34: 4
A35: 46110.429 | B35: amber | C35: Female | D35: 42 -53 | E35: Lahore | F35: JazzCash | G35: Jazzcash | H35: Jazz cash | I35: Jazzcash | J35: 1-4 months | K35: Easypaisa | L35: jazzcash is easy to use and am used to it now | M35: Yes | N35: for emergency if i need money to transfer anytime or anyone wants to return back my money | O35: 10 | P35: Easypaisa | Q35: Jazz Cash | R35: Jazz Cash | S35: Jazz Cash | T35: Jazz Cash | U35: Jazz Cash | V35: Jazz Cash | W35: Jazz Cash | X35: Jazz Cash | Y35: Yes | Z35: Easypaisa | AA35: as everyone is using that app so transferred to their specific app through sadapay | AB35: 10
A36: 46110.447 | B36: Naseer Ahmad | C36: Male | D36: 18 - 29 | E36: Jhang | F36: Easypaisa | G36: Jazzcash, Easypaisa | H36: Jazz cash, Easypaisa | I36: Easypaisa | J36: 18-24 months | K36: Jazz cash | L36: For service issues | M36: Yes | N36: For good service | O36: 7 | P36: Jazz cash | Q36: Easypaisa | R36: Easypaisa | S36: Easypaisa | T36: Jazz Cash | U36: Easypaisa | V36: Jazz Cash | W36: Jazz Cash | X36: Nayapay | Y36: Maybe | Z36: Easypaisa | AA36: It means this app is trustable and having fast service | AB36: 7
A37: 46110.475 | B37: Mahnoor | C37: Female | D37: 18 - 29 | E37: Lahore | F37: Jazzcash | G37: Jazzcash, Nayapay | H37: Jazz cash, Nayapay | I37: Jazzcash | J37: 9-12 months | K37: Jazz cash | L37: Is it good for myself and working fastly | M37: Yes | N37: Fast service | O37: 5 | P37: Nayapay | Q37: Jazz Cash | R37: Jazz Cash | S37: Jazz Cash | T37: Jazz Cash | U37: Jazz Cash | V37: Jazz Cash | W37: Jazz Cash | X37: Nayapay | Y37: Maybe | Z37: I have not seen this ad | AA37: To provide great service and advertising | AB37: 3
A38: 46110.484 | B38: Abdul hafeez | C38: Male | D38: 18 - 29 | E38: Sadiqabad | F38: Jazz cash | G38: Jazzcash | H38: Jazz cash | I38: Jazzcash | J38: More than 2 years | K38: Jazz cash | L38: Its easy to me | M38: No | N38: Yes | O38: 1 | P38: Jazz cash | Q38: Jazz Cash | R38: Sadapay | S38: Jazz Cash | T38: Jazz Cash | U38: Jazz Cash | V38: Jazz Cash | W38: Jazz Cash | X38: Jazz Cash | Y38: Yes | Z38: Easypaisa | AA38: Not meaningful | AB38: 1
A39: 46110.535 | B39: Amna Zohaib | C39: Female | D39: 30 - 41 | E39: Lahore | F39: Jazz cash | G39: Jazzcash | H39: Jazz cash, Easypaisa | I39: Jazzcash | J39: 18-24 months | K39: Easypaisa | L39: It's convenient for me | M39: Yes | N39: Not any big reason just easy to use this app | O39: 5 | P39: Easypaisa | Q39: Jazz Cash | R39: Sadapay | S39: Jazz Cash | T39: Jazz Cash | U39: Jazz Cash | V39: Jazz Cash | W39: Jazz Cash | X39: Jazz Cash | Y39: No | Z39: I have not seen this ad | AA39: Yess | AB39: 1
A40: 46110.606 | B40: Sania | C40: Female | D40: 18 - 29 | E40: Lahore | F40: Nayapay | G40: Jazzcash, Easypaisa, Sadapay, Nayapay | H40: Jazz cash, Nayapay | I40: Nayapay | J40: More than 2 years | K40: NAYAPAY | L40: Didn’t switch | M40: Yes | N40: Easy to use | O40: 9 | P40: Jazz cash | Q40: Nayapay | R40: Nayapay | S40: Jazz Cash | T40: Nayapay | U40: Nayapay | V40: Jazz Cash | W40: Nayapay | X40: Nayapay | Y40: Maybe | Z40: Jazzcash | AA40: Easy to use for everyone | AB40: 6
... A45: 46111.223 | B45: Zohaib javaid | C45: Male | D45: 30 - 41 | E45: Lahore | F45: Jazz cash | G45: Jazzcash | H45: Jazz cash | I45: Jazzcash | J45: More than 2 years | K45: Easypaisa | L45: No specific reason | M45: Yes | N45: Its more realibe | O45: 9 | P45: Easypaisa | Q45: Jazz Cash | R45: Easypaisa | S45: Jazz Cash | T45: Jazz Cash | U45: Jazz Cash | V45: Easypaisa | W45: Jazz Cash | X45: Easypaisa | Y45: No | Z45: I have not seen this ad | AA45: I have no idea | AB45: 5
A46: 46114.946 | B46: Aroona | C46: Female | D46: 42 -53 | E46: Lahore | F46: Easy paisa | G46: Jazzcash, Easypaisa | H46: Jazz cash, Easypaisa | I46: Easypaisa | J46: More than 2 years | K46: Jazz cash | L46: Sometime app not responding | M46: Yes | N46: I m use to of this app too much | O46: 8 | P46: Jazz cash | Q46: Easypaisa | R46: Easypaisa | S46: Easypaisa | T46: Easypaisa | U46: Easypaisa | V46: Easypaisa | W46: Easypaisa | Y46: Maybe | Z46: I have not seen this ad | AA46: I haven't seen bcz I didn't watch tv | AB46: 6
A47: 46115.893 | B47: Muhammad Tayyab | C47: Male | D47: 18 - 29 | E47: Lahore | F47: Jazzcash | G47: Jazzcash, Easypaisa | H47: Jazz cash, Easypaisa | I47: Jazzcash | J47: More than 2 years | K47: Easypaisa | L47: Quickest | M47: Yes | N47: Availability allover | O47: 10 | P47: MCB LIVE | Q47: Jazz Cash | R47: Easypaisa | S47: Easypaisa | T47: Easypaisa | U47: Easypaisa | V47: Jazz Cash | W47: Easypaisa | X47: Easypaisa | Y47: Maybe | Z47: I have not seen this ad | AA47: Discussion about eidi | AB47: 1
A48: 46119.974 | B48: Dawood humayuon | C48: Male | D48: 18 - 29 | E48: Lahore | F48: Easypaisa | G48: Jazzcash, Easypaisa | H48: Jazz cash, Easypaisa | I48: Easypaisa | J48: More than 2 years | K48: Sadapay | L48: Easy payment method / transaction | M48: Yes | N48: Privacy policy | O48: 10 | P48: Jazz cash | Q48: Easypaisa | R48: Easypaisa | S48: Easypaisa | T48: Easypaisa | U48: Easypaisa | V48: Easypaisa | W48: Nayapay | X48: Sadapay | Y48: No | Z48: I have not seen this ad | AA48: Make it short video not long | AB48: 5
A49: 46120.81 | B49: Muhammad Afzal Faheem | C49: Male | D49: 30 - 41 | E49: Lahore | F49: Eaisypaisa | G49: Jazzcash, Easypaisa | H49: Jazz cash, Easypaisa | I49: Easypaisa | J49: More than 2 years | K49: Jazz cash | L49: The make the payment process more convenient | M49: Yes | N49: User-friendly, reliable, and time-saving | O49: 10 | P49: Jazz cash | Q49: Easypaisa | R49: Easypaisa | S49: Easypaisa | T49: Easypaisa | U49: Easypaisa | V49: Easypaisa | W49: Easypaisa | X49: Easypaisa | Y49: Yes | Z49: Easypaisa | AA49: To switch to digital platform for transactions | AB49: 6
A50: 46131.574 | B50: Muhammad Mohsin Akram | C50: Male | D50: 18 - 29 | E50: Lahore | F50: Easypaisa | G50: Jazzcash, Easypaisa | H50: Jazz cash, Easypaisa | I50: Easypaisa | J50: More than 2 years | K50: Jazz cash | L50: No extra features in this app | M50: Yes | N50: Very good and attractive | O50: 8 | P50: Zindagi | Q50: Easypaisa | R50: Jazz Cash | S50: Easypaisa | T50: Easypaisa | U50: Easypaisa | V50: Easypaisa | W50: Easypaisa | X50: Easypaisa | Y50: Yes | Z50: Jazzcash | AA50: Na | AB50: 3
A51: 46131.576 | B51: Aliza khan | C51: Female | D51: 18 - 29 | E51: Lahore | F51: Easy paisa | G51: Easypaisa | H51: Easypaisa | I51: Easypaisa | J51: 9-12 months | K51: Sadapay | L51: No specific reason | M51: Yes | N51: It’s easy to use | O51: 7 | P51: Easypaisa | Q51: Jazz Cash | R51: Easypaisa | S51: Easypaisa | T51: Easypaisa | U51: Easypaisa | V51: Jazz Cash | W51: Easypaisa | X51: Easypaisa | Y51: Yes | Z51: Easypaisa | AA51: Don’t remember | AB51: 3
A52: 46131.588 | B52: Ikram mir | C52: Male | D52: 18 - 29 | E52: Lahore | F52: Sadapay | G52: Easypaisa, Sadapay | H52: Sadapay | I52: Sadapay | J52: 13-18 months | K52: Easypaisa | L52: Extra use | M52: Yes | N52: Easy transfer | O52: 3 | P52: Easypaisa | Q52: Easypaisa | R52: Sadapay | S52: Easypaisa | T52: Easypaisa | U52: Sadapay | V52: Sadapay | W52: Sadapay | X52: Nayapay | Y52: No | Z52: I have not seen this ad | AA52: Money transfer | AB52: 1
A53: 46131.615 | B53: Talha | C53: Male | D53: 18 - 29 | E53: Lahore | F53: Easypaisa | G53: Sadapay | H53: Sadapay | I53: Sadapay | J53: 5-8 months | K53: Easypaisa | L53: Service | M53: Yes | N53: Easy to use | O53: 10 | P53: Bank | Q53: Sadapay | R53: Sadapay | S53: Easypaisa | T53: Sadapay | U53: Sadapay | V53: Easypaisa | W53: Sadapay | X53: Sadapay | Y53: Yes | Z53: Easypaisa | AA53: Easy to transfer and it’s fast | AB53: 10
A54: 46131.617 | B54: jk | C54: Male | D54: 18 - 29 | E54: Lahore | F54: jazzcash, zindigi, easypaisa,sadapay | G54: Jazzcash, Easypaisa, Sadapay | H54: Jazz cash, Sadapay | I54: Jazzcash | J54: 18-24 months | K54: Easypaisa | L54: UI | M54: Yes | N54: use kerny me easy hai | O54: 9 | P54: Nayapay | Q54: Nayapay | R54: Jazz Cash | S54: Jazz Cash | T54: Jazz Cash | U54: Nayapay | V54: Jazz Cash | W54: Nayapay | X54: Nayapay | Y54: Yes | Z54: Easypaisa | AA54: Promoting easypaisa app | AB54: 9
A55: 46131.617 | B55: Nasreen | C55: Female | D55: 42 -53 | E55: Lahore | F55: Easypaissa | G55: Easypaisa | H55: Easypaisa, Sadapay | I55: Easypaisa | J55: 18-24 months | K55: Easypaisa | L55: Hight security | M55: Yes | N55: Service | O55: 10 | P55: Sadapay | Q55: Easypaisa | R55: Easypaisa | S55: Easypaisa | T55: Easypaisa | U55: Easypaisa | V55: Easypaisa | W55: Easypaisa | X55: Easypaisa | Y55: Yes | Z55: Easypaisa | AA55: Easy to use and safe for all transfers | AB55: 10
A56: 46131.618 | B56: Ashraf Ali | C56: Male | D56: 66 and above | E56: Lahore | F56: Jazz cash | G56: Jazzcash | H56: Jazz cash | I56: Jazzcash | J56: 13-18 months | K56: Jazz cash | L56: N A | M56: Yes | N56: More common | O56: 5 | P56: Easypaisa | Q56: Jazz Cash | R56: Jazz Cash | S56: Jazz Cash | T56: Jazz Cash | U56: Easypaisa | V56: Jazz Cash | W56: Easypaisa | X56: Easypaisa | Y56: Maybe | Z56: I have not seen this ad | AA56: N A | AB56: 5
A57: 46131.622 | B57: Ramsha Ashfaq | C57: Female | D57: 18 - 29 | E57: Lahore | F57: Jazzcash | G57: Sadapay | H57: Sadapay | I57: Sadapay | J57: Less than 1 month | K57: Jazz cash | L57: None | M57: No | N57: None | O57: 2 | P57: Meezan bank | Q57: Easypaisa | R57: Easypaisa | S57: Jazz Cash | T57: Jazz Cash | U57: Jazz Cash | V57: Jazz Cash | W57: Jazz Cash | X57: Jazz Cash | Y57: No | Z57: Easypaisa | AA57: That it’s easy to transfer money | AB57: 4
A58: 46131.622 | B58: Arfa | C58: Female | D58: 18 - 29 | E58: Lahore | F58: Sadapay | G58: Sadapay | H58: Sadapay | I58: Sadapay | J58: Less than 1 month | K58: Easypaisa | L58: Better application and process | M58: Yes | N58: Its good to even pay internationally for like e.g netflix | O58: 6 | P58: Nayapay | Q58: Sadapay | R58: Sadapay | S58: Jazz Cash | T58: Sadapay | U58: Sadapay | V58: Sadapay | W58: Jazz Cash | X58: Sadapay | Y58: No | Z58: I have not seen this ad | AA58: I haven’t seen the ad | AB58: 3
... A84: 46131.668 | B84: Hassan | C84: Male | D84: 18 - 29 | E84: Faisalabad | F84: Jazzcash | G84: Jazzcash | H84: Jazz cash | I84: Jazzcash | J84: 13-18 months | K84: Easypaisa | L84: Convenience | M84: Yes | N84: Convenience | O84: 10 | P84: Easypaisa | Q84: Jazz Cash | R84: Jazz Cash | S84: Jazz Cash | T84: Jazz Cash | U84: Jazz Cash | V84: Jazz Cash | W84: Jazz Cash | X84: Sadapay | Y84: No | Z84: I have not seen this ad | AA84: Don't know | AB84: 1
A85: 46131.672 | B85: Dr. Ata Ul Musawir | C85: Male | D85: 30 - 41 | E85: Lahore | F85: Easypaisa | G85: Jazzcash, Easypaisa | H85: Jazz cash, Easypaisa | I85: Jazzcash | J85: 1-4 months | K85: Easypaisa | L85: User-friendly UI, app speed | M85: Yes | N85: User-friendly UI, app speed & having a digital wallet payment option | O85: 8 | P85: Easypaisa | Q85: Jazz Cash | R85: Jazz Cash | S85: Jazz Cash | T85: Jazz Cash | U85: Jazz Cash | V85: Jazz Cash | W85: Jazz Cash | Y85: No | Z85: I have not seen this ad | AA85: Don't watch ads or TV | AB85: 5
A86: 46131.674 | B86: Zoha ashfaq | C86: Female | D86: 18 - 29 | E86: Lahore | F86: Jazzcash | G86: Sadapay, Nayapay | H86: Sadapay | I86: Sadapay | J86: More than 2 years | K86: Jazz cash | L86: Wese hi | M86: Yes | N86: Idk | O86: 8 | P86: Jazz cash | Q86: Jazz Cash | R86: Jazz Cash | S86: Jazz Cash | T86: Jazz Cash | U86: Jazz Cash | V86: Jazz Cash | W86: Jazz Cash | X86: Jazz Cash | Y86: No | Z86: Jazzcash | AA86: Lame | AB86: 1
A87: 46131.674 | B87: noor fatima | C87: Female | D87: 18 - 29 | E87: Lahore | F87: nayapay | G87: Nayapay | H87: Nayapay | I87: Nayapay | J87: More than 2 years | K87: NAYAPAY | L87: I did not switch to another app because I am satisfied with my current primary app. It is easy to use, reliable, and meets all my needs. I feel comfortable using it, so I don’t see any strong reason to switch. | M87: Yes | N87: I am satisfied with my current primary app. It is easy to use, reliable, and meets all my needs. I feel comfortable using it, so I don’t see any strong reason to switch. | O87: 10 | P87: other | Q87: Nayapay | R87: Nayapay | S87: Nayapay | T87: Nayapay | U87: Nayapay | V87: Nayapay | W87: Nayapay | X87: Nayapay | Y87: No | Z87: I have not seen this ad | AA87: its is easy , fast | AB87: 5
A88: 46131.675 | B88: Ahmer Amin | C88: Male | D88: 18 - 29 | E88: Lahore | F88: HBL, Jazzcash, easypaisa | G88: Jazzcash, Easypaisa | H88: Jazz cash | I88: Jazzcash | J88: 13-18 months | K88: Easypaisa | L88: alternative app | M88: Yes | N88: need of the hour | O88: 8 | P88: Nayapay | Q88: Easypaisa | R88: Jazz Cash | S88: Easypaisa | T88: Easypaisa | U88: Easypaisa | V88: Easypaisa | W88: Jazz Cash | X88: Easypaisa | Y88: No | Z88: I have not seen this ad | AA88: not warched this ad | AB88: 4
A89: 46131.678 | B89: Minahil shahbaz | C89: Female | D89: 18 - 29 | E89: Lahore | F89: I am not currently using any but I am aware of JazzCash and Easypaisa.” | G89: Jazzcash | H89: Jazz cash | I89: Jazzcash | J89: Less than 1 month | K89: Jazz cash | L89: Reason for switching | M89: No | N89: I am nit using this app so don't asked to prefer | O89: 5 | P89: Easypaisa | Q89: Easypaisa | R89: Jazz Cash | S89: Jazz Cash | T89: Easypaisa | U89: Nayapay | V89: Jazz Cash | W89: Easypaisa | X89: Easypaisa | Y89: Maybe | Z89: I have not seen this ad | AA89: Easypaisa transfer money very easily i think so | AB89: 1
A90: 46131.679 | B90: Ruttaba Ashraf | C90: Female | D90: 18 - 29 | E90: Lahore | F90: Easypaisa | G90: Easypaisa, Sadapay, Nayapay | H90: Easypaisa, Sadapay, Nayapay | I90: Nayapay | J90: More than 2 years | K90: Easypaisa | L90: Nayapay have more features than easypaisa | M90: Yes | N90: Nayapay Have Various Features and specifications | O90: 10 | P90: Sadapay | Q90: Nayapay | R90: Sadapay | S90: Easypaisa | T90: Nayapay | U90: Nayapay | V90: Nayapay | W90: Nayapay | X90: Nayapay | Y90: No | Z90: Easypaisa | AA90: If anyone has not handed in cash, they can transfer it no worries at all. | AB90: 5
A91: 46131.681 | B91: Mian Asim | C91: Male | D91: 42 -53 | E91: Lahore | F91: JazzCash | G91: Jazzcash, Easypaisa | H91: Jazz cash, Easypaisa | I91: Easypaisa | J91: More than 2 years | K91: Jazz cash | L91: Fraud detection | M91: No | N91: Secure | O91: 9 | P91: Sadapay | Q91: Easypaisa | R91: Easypaisa | S91: Easypaisa | T91: Easypaisa | U91: Easypaisa | V91: Easypaisa | W91: Easypaisa | X91: Sadapay | Y91: No | Z91: I have not seen this ad | AA91: not ever seen | AB91: 1
A92: 46131.684 | B92: Hafiz Irtaza Aslam | C92: Male | D92: 18 - 29 | E92: Lahore | F92: JazzCash | G92: Jazzcash, Easypaisa, Sadapay, Nayapay | H92: Jazz cash, Easypaisa, Sadapay, Nayapay | I92: Jazzcash | J92: More than 2 years | K92: Jazz cash | L92: I haven’t switched to any single app. In fact, I use multiple apps because it allows me to handle payments from different wallets, making it easier and more convenient for my clients. This way, there’s no issue in receiving payments. | M92: Yes | N92: I prefer to keep using these apps because they provide flexibility for my clients. Each client might have a different preferred payment method or wallet, and by using multiple apps, I ensure smooth transactions, reduce friction, and make it as convenient as possible for them. | O92: 8 | P92: Jazz cash | Q92: Jazz Cash | R92: Jazz Cash | S92: Jazz Cash | T92: Jazz Cash | U92: Jazz Cash | V92: Jazz Cash | W92: Jazz Cash | X92: Jazz Cash | Y92: Yes | Z92: Jazzcash | AA92: The main message of this ad is that even when traditional cash sources like ATMs aren’t working, you can still easily send or receive Eidi (gift money) through the Eidipaisa mobile wallet. It emphasizes convenience and ensures you never miss out on giving or receiving Eidi, even if physical cash is unavailable. | AB92: 5
A93: 46131.689 | B93: Raheeq Sharif | C93: Male | D93: 18 - 29 | E93: Lahore | F93: Jazzcash | G93: Jazzcash, Easypaisa, Sadapay, Nayapay | H93: Jazz cash, Easypaisa, Sadapay, Nayapay | I93: Nayapay | J93: More than 2 years | K93: Jazz cash | L93: Easy to use | M93: Yes | N93: No any charges | O93: 10 | P93: Nayapay | Q93: Nayapay | R93: Nayapay | S93: Nayapay | T93: Nayapay | U93: Nayapay | V93: Nayapay | W93: Nayapay | X93: Nayapay | Y93: Yes | Z93: Nayapay | AA93: Online eidi | AB93: 10
A94: 46131.69 | B94: Hamza | C94: Male | D94: 18 - 29 | E94: Lahore | F94: Jazz cash | G94: Jazzcash, Easypaisa | H94: Jazz cash, Easypaisa | I94: Jazzcash | J94: More than 2 years | K94: Jazz cash | L94: No switch | M94: Yes | N94: Instand payment | O94: 10 | P94: Easypaisa | Q94: Jazz Cash | R94: Jazz Cash | S94: Jazz Cash | T94: Jazz Cash | U94: Jazz Cash | V94: Jazz Cash | W94: Jazz Cash | X94: Jazz Cash | Y94: No | Z94: I have not seen this ad | AA94: I don't no | AB94: 1
A95: 46131.693 | B95: esha | C95: Female | D95: 18 - 29 | E95: Lahore | F95: Jazzcash | G95: Jazzcash, Easypaisa, Sadapay | H95: Jazz cash, Sadapay | I95: Jazzcash | J95: 18-24 months | K95: Jazz cash | L95: Never switched | M95: Yes | N95: Can send money to local stores, places easily | O95: 6 | P95: Easypaisa | Q95: Easypaisa | R95: Easypaisa | S95: Easypaisa | T95: Sadapay | U95: Easypaisa | V95: Sadapay | W95: Sadapay | X95: Sadapay | Y95: Maybe | Z95: Easypaisa | AA95: Sending money to your loved ones to make them feel loved and special | AB95: 4
A96: 46131.698 | B96: Ali hussnain | C96: Male | D96: 18 - 29 | E96: Lahore | F96: Jazzcash | G96: Sadapay, Nayapay | H96: Sadapay, Nayapay | I96: Nayapay | J96: More than 2 years | K96: Jazz cash | L96: Easy transfer and no chances of scam | M96: Yes | N96: I can use it globally and have a safe payment method | O96: 10 | P96: Easypaisa | Q96: Nayapay | R96: Nayapay | S96: Easypaisa | T96: Nayapay | U96: Sadapay | V96: Nayapay | W96: Nayapay | X96: Sadapay | Y96: Yes | Z96: Easypaisa | AA96: To support digital wallets | AB96: 7
A97: 46131.698 | B97: Muhammad Saqib Shoaib | C97: Male | D97: 18 - 29 | E97: Lahore | F97: Jaaz cash | G97: Jazzcash | H97: Jazz cash, Easypaisa | I97: Jazzcash | J97: More than 2 years | K97: Jazz cash | L97: Jazz cash | M97: Yes | N97: Best Services | O97: 2 | P97: Easypaisa | Q97: Jazz Cash | R97: Jazz Cash | S97: Easypaisa | T97: Jazz Cash | U97: Easypaisa | V97: Easypaisa | W97: Jazz Cash | X97: Jazz Cash | Y97: Yes | Z97: Jazzcash | AA97: Yes | AB97: 1
... A131: 46131.845 | B131: Haider Zulfiqar | C131: Male | D131: 18 - 29 | E131: Lahore | F131: Easypaisa | G131: Jazzcash, Easypaisa, Nayapay | H131: Jazz cash, Easypaisa | I131: Easypaisa | J131: More than 2 years | K131: Easypaisa | L131: More options available specifically like Mtag payments | M131: Yes | N131: Easy to use and even now scan and pay is getting normal at local stores so no need to carry cash | O131: 8 | P131: Jazz cash | Q131: Easypaisa | R131: Easypaisa | S131: Easypaisa | T131: Easypaisa | U131: Easypaisa | V131: Easypaisa | W131: Easypaisa | X131: Nayapay | Y131: Yes | Z131: Easypaisa | AA131: Main message was to use Easypaisa to easily send eidi to love ones | AB131: 9
A132: 46131.867 | B132: Khalid Niazi | C132: Male | D132: 54 - 65 | E132: London | F132: JAZZ Cash | G132: Jazzcash | H132: Jazz cash | I132: Jazzcash | J132: 9-12 months | K132: Easypaisa | L132: easy to use | M132: Yes | N132: easy to use | O132: 8 | P132: Easypaisa | Q132: Jazz Cash | R132: Jazz Cash | S132: Jazz Cash | T132: Jazz Cash | U132: Easypaisa | V132: Jazz Cash | W132: Jazz Cash | Y132: No | Z132: Easypaisa | AA132: conviniance | AB132: 6
A133: 46131.882 | B133: Muhammad Anas | C133: Male | D133: 18 - 29 | E133: Lahore | F133: Jazz cash | G133: Jazzcash, Easypaisa, Sadapay | H133: Jazz cash, Easypaisa, Sadapay | I133: Sadapay | J133: Less than 1 month | K133: Jazz cash | L133: For better service | M133: Yes | N133: Sadapay has fastest payment transfer method. | O133: 9 | P133: Easypaisa | Q133: Sadapay | R133: Sadapay | S133: Jazz Cash | T133: Sadapay | U133: Sadapay | V133: Sadapay | W133: Sadapay | X133: Sadapay | Y133: No | Z133: Jazzcash | AA133: This is the public awareness ad to use the app that is more secure and reliable for you internet banking | AB133: 5
A134: 46131.902 | B134: Anny | C134: Female | D134: 18 - 29 | E134: Islamabad | F134: Easypaisa | G134: Easypaisa | H134: Easypaisa | I134: Easypaisa | J134: 9-12 months | K134: Easypaisa | L134: It is the first app I used | M134: Yes | N134: Payment | O134: 3 | P134: Easypaisa | Q134: Easypaisa | R134: Easypaisa | S134: Easypaisa | T134: Easypaisa | U134: Easypaisa | V134: Easypaisa | W134: Easypaisa | X134: Sadapay | Y134: No | Z134: Easypaisa | AA134: You can give online Eidi now without excuses | AB134: 1
A135: 46131.908 | B135: Hussian | C135: Male | D135: 18 - 29 | E135: Lahore | F135: JazzCash | G135: Nayapay | H135: Nayapay | I135: Nayapay | J135: More than 2 years | K135: NAYAPAY | L135: N/A | M135: Yes | N135: Easy | O135: 9 | P135: Jazz cash | Q135: Nayapay | R135: Nayapay | S135: Jazz Cash | T135: Nayapay | U135: Nayapay | V135: Nayapay | W135: Nayapay | X135: Nayapay | Y135: Yes | Z135: Easypaisa | AA135: Promotion | AB135: 5
A136: 46131.932 | B136: Taah Mahmood | C136: Male | D136: 18 - 29 | E136: Lahore | F136: The first name that comes to my mind is jazz cash as it is the most common digital wallet | G136: Jazzcash, Nayapay | H136: Jazz cash, Nayapay | I136: Nayapay | J136: 5-8 months | K136: Jazz cash | L136: I got a physical card free of cost from nayapay so i switched my services from jazz cash to nayapay as it was more convenient for me. | M136: Yes | N136: It is convenient for me to use as i have physical card. And this app has built my trust overtime. Once i got double charged for the same thing i raised the concern with their customer service and they refunded the amount within 2 or 3 hours | O136: 7 | P136: I would recomend using an official bank application like meezan bank or mcb. | Q136: Nayapay | R136: Nayapay | S136: Jazz Cash | T136: Nayapay | U136: Nayapay | V136: Jazz Cash | W136: Nayapay | X136: Nayapay | Y136: Maybe | Z136: Jazzcash | AA136: The main message in this add was ro potray how easy it is to transfer the funds using digital wallet. | AB136: 6
A137: 46131.943 | B137: Sameer | C137: Male | D137: 18 - 29 | E137: Lahore | F137: Sadapay | G137: Sadapay | H137: Sadapay | I137: Sadapay | J137: 18-24 months | K137: Easypaisa | L137: Better app quality and easy money transfer | M137: Yes | N137: Easy transfers | O137: 5 | P137: Nayapay | Q137: Sadapay | R137: Sadapay | S137: Easypaisa | T137: Easypaisa | U137: Sadapay | V137: Sadapay | W137: Sadapay | X137: Sadapay | Y137: No | Z137: I have not seen this ad | AA137: None | AB137: 5
A138: 46131.96 | B138: Maarib Naqvi | C138: Male | D138: 18 - 29 | E138: Lahore | F138: Jazzcash | G138: Jazzcash, Sadapay | H138: Jazz cash | I138: Jazzcash | J138: More than 2 years | K138: Sadapay | L138: Its shit | M138: Yes | N138: Shit but better than shit | O138: 5 | P138: Easypaisa | Q138: Jazz Cash | R138: Easypaisa | S138: Jazz Cash | T138: Easypaisa | U138: Jazz Cash | V138: Easypaisa | W138: Jazz Cash | X138: Jazz Cash | Y138: Yes | Z138: Easypaisa | AA138: Convenience of their app | AB138: 7
A139: 46131.965 | B139: Fahad | C139: Male | D139: 18 - 29 | E139: Lahore | F139: Easypaisa | G139: Jazzcash, Easypaisa, Sadapay, Nayapay | H139: Easypaisa, Nayapay | I139: Easypaisa | J139: More than 2 years | K139: Jazz cash | L139: Because JazzCash automatically subscribe services through my account and payment deducts automatically | M139: Yes | N139: Because easypaisa is mostly available everywhere and that don't deduct amount without our permission like JazzCash do. | O139: 9 | P139: Nayapay | Q139: Easypaisa | R139: Nayapay | S139: Jazz Cash | T139: Easypaisa | U139: Easypaisa | V139: Easypaisa | W139: Easypaisa | X139: Nayapay | Y139: Maybe | Z139: Easypaisa | AA139: Advertising the app's feature | AB139: 7
A140: 46131.966 | B140: Hanzala Ahmad | C140: Male | D140: 18 - 29 | E140: Lahore | F140: Easypaisa | G140: Easypaisa | H140: Easypaisa | I140: Easypaisa | J140: More than 2 years | K140: Jazz cash | L140: Very good and reliable. | M140: Yes | N140: main easypaisa app ko refer nahin karta jab payment karenge Apne payment katati hai Maine charges Rakh liye hain isliye bus main ek majburi ki tahat isko use karta hun jashcash Mera Nahin hai | O140: 1 | P140: Sadapay | Q140: Easypaisa | R140: Jazz Cash | S140: Jazz Cash | T140: Easypaisa | U140: Jazz Cash | V140: Easypaisa | W140: Easypaisa | X140: Sadapay | Y140: No | Z140: Easypaisa | AA140: You were trying to find out which app people use the most. | AB140: 10
A141: 46132.069 | B141: Momina | C141: Female | D141: 18 - 29 | E141: Lahore | F141: Jazzcash | G141: Jazzcash, Easypaisa | H141: Jazz cash | I141: Jazzcash | J141: 5-8 months | K141: Easypaisa | L141: Wanted to try a new one | M141: Yes | N141: Easy to use | O141: 6 | P141: Easypaisa | Q141: Jazz Cash | R141: Easypaisa | S141: Jazz Cash | T141: Jazz Cash | U141: Jazz Cash | V141: Jazz Cash | W141: Jazz Cash | X141: Jazz Cash | Y141: No | Z141: I have not seen this ad | AA141: I haven’t watched the add yet | AB141: 5
A142: 46132.319 | B142: 5G services Jazz and warid? | C142: Male | D142: 54 - 65 | E142: Lahore | F142: Jazz Cash | G142: Jazzcash, easypaisa | H142: Jazz cash | I142: Jazzcash | J142: More than 2 years | K142: Easypaisa | L142: Better services | M142: Yes | N142: Good response | O142: 1 | P142: Sadapay | Q142: Jazz Cash | R142: Jazz Cash | S142: Nayapay | T142: Jazz Cash | U142: Jazz Cash | V142: Jazz Cash | W142: Jazz Cash | X142: Jazz Cash | Y142: No | Z142: I have not seen this ad | AA142: Good work | AB142: 10
A143: 46132.567 | B143: Mujtaba Javed | C143: Male | D143: 18 - 29 | E143: Lahore | F143: Sadapay | G143: Jazzcash, Easypaisa, Sadapay, Nayapay | H143: Jazz cash, Easypaisa, Sadapay, Nayapay | I143: Nayapay | J143: More than 2 years | K143: Jazz cash | L143: A virtual card | M143: Yes | N143: Friendly interface + no IBFT charges | O143: 8 | P143: Easypaisa | Q143: Sadapay | R143: Jazz Cash | S143: Jazz Cash | T143: Nayapay | U143: Nayapay | V143: Jazz Cash | W143: Nayapay | X143: Nayapay | Y143: Yes | Z143: Easypaisa | AA143: To communicate that it is far more easy to send money instead of hassling for cash through atms via easypaisa | AB143: 8
A144: 46132.569 | B144: Aurangzeb | C144: Male | D144: 18 - 29 | E144: Lahore | F144: Jazzcash, easypaisa, credit cards | G144: Jazzcash | H144: Jazz cash | I144: Jazzcash | J144: 1-4 months | K144: Easypaisa | L144: Wanted to | M144: Yes | N144: Efficient | O144: 6 | P144: Banking apps | Q144: Jazz Cash | R144: Jazz Cash | S144: Jazz Cash | T144: Jazz Cash | U144: Nayapay | V144: Jazz Cash | W144: Jazz Cash | X144: Nayapay | Y144: No | Z144: I have not seen this ad | AA144: Haven’t seen the ad | AB144: 5
... A151: 46134.406 | B151: Ghani Khan | C151: Male | D151: 18 - 29 | E151: Faisalabad | F151: Jazzcash | G151: Jazzcash, Easypaisa, Sadapay, Nayapay | H151: Jazz cash, Sadapay, Nayapay | I151: Jazzcash | J151: More than 2 years | K151: Jazz cash | L151: None | M151: Yes | N151: User friendly | O151: 7 | P151: Easypaisa | Q151: Jazz Cash | R151: Easypaisa | S151: Easypaisa | T151: Easypaisa | U151: Easypaisa | V151: Jazz Cash | W151: Jazz Cash | X151: Nayapay | Y151: Maybe | Z151: Jazzcash | AA151: Easy access | AB151: 5

Sheet Reason_to_switch_&_keep_using
A1: Name | B1: CURRENT USAGE | C1: Previous Brand | D1: Favorite | E1: Reasons for switching | F1: Switch_Status | G1: Switch_basket | H1: using | I1: Switch | J1: Push/Pull Factors | K1: Reasons for keep using
A2: Gulfam | B2: easypaisa | C2: sadapay | D2: easypaisa | E2: account blockage and trust issues | F2: account blockage and trust issues | G2: Trust issues | H2: =VLOOKUP(Reason_to_switch[[#This Row],[Name]],SINGLE_RESPONSES[],8,FALSE) -> 6 | I2: =IF(Reason_to_switch[[#This Row],[Switch_Status]]="Not Switched",Reason_to_switch[[#This Row],[Switch_Status]],"TRUE") -> TRUE | J2: Push | K2: Better UX
A3: waleed | B3: easypaisa | C3: easypaisa | D3: easypaisa | E3: Not switched | F3: Not Switched | G3: =IF(Reason_to_switch[[#This Row],[Switch_Status]]="Not Switched",Reason_to_switch[[#This Row],[Switch_Status]]) -> Not Switched | H3: =VLOOKUP(Reason_to_switch[[#This Row],[Name]],SINGLE_RESPONSES[],8,FALSE) -> 4 | I3: =IF(Reason_to_switch[[#This Row],[Switch_Status]]="Not Switched",Reason_to_switch[[#This Row],[Switch_Status]],"TRUE") -> Not Switched | J3: Neutral | K3: Better UX
A4: Talha | B4: sadapay | C4: easypaisa | D4: sadapay | E4: Easy to assess | F4: Easy to assess | G4: Better UX | H4: =VLOOKUP(Reason_to_switch[[#This Row],[Name]],SINGLE_RESPONSES[],8,FALSE) -> 4 | I4: =IF(Reason_to_switch[[#This Row],[Switch_Status]]="Not Switched",Reason_to_switch[[#This Row],[Switch_Status]],"TRUE") -> TRUE | J4: Pull | K4: Better UX
A5: Jawad Waseem | B5: easypaisa | C5: nayapay | D5: easypaisa | E5: More options | F5: More options | G5: Better Features | H5: =VLOOKUP(Reason_to_switch[[#This Row],[Name]],SINGLE_RESPONSES[],8,FALSE) -> 7 | I5: =IF(Reason_to_switch[[#This Row],[Switch_Status]]="Not Switched",Reason_to_switch[[#This Row],[Switch_Status]],"TRUE") -> TRUE | J5: Pull | K5: Ecosystem Advantage
A6: Abdullah | B6: easypaisa | C6: jazzcash | D6: easypaisa | E6: Bad service | F6: Bad service | G6: Poor Customer Services | H6: =VLOOKUP(Reason_to_switch[[#This Row],[Name]],SINGLE_RESPONSES[],8,FALSE) -> 6 | I6: =IF(Reason_to_switch[[#This Row],[Switch_Status]]="Not Switched",Reason_to_switch[[#This Row],[Switch_Status]],"TRUE") -> TRUE | J6: Push | K6: Performance
A7: Muhammad saad ahmad | B7: easypaisa | C7: nayapay | D7: easypaisa | E7: Wasn't reliable | F7: Wasn't reliable | G7: Technical Failures | H7: =VLOOKUP(Reason_to_switch[[#This Row],[Name]],SINGLE_RESPONSES[],8,FALSE) -> 5 | I7: =IF(Reason_to_switch[[#This Row],[Switch_Status]]="Not Switched",Reason_to_switch[[#This Row],[Switch_Status]],"TRUE") -> TRUE | J7: Push | K7: Better UX
A8: Mubashir hassan | B8: jazzcash | C8: jazzcash | D8: easypaisa | E8: User experience | F8: Not Switched | G8: =IF(Reason_to_switch[[#This Row],[Switch_Status]]="Not Switched",Reason_to_switch[[#This Row],[Switch_Status]]) -> Not Switched | H8: =VLOOKUP(Reason_to_switch[[#This Row],[Name]],SINGLE_RESPONSES[],8,FALSE) -> 7 | I8: =IF(Reason_to_switch[[#This Row],[Switch_Status]]="Not Switched",Reason_to_switch[[#This Row],[Switch_Status]],"TRUE") -> Not Switched | J8: Neutral | K8: Better UX
A9: Ayesha | B9: jazzcash | C9: jazzcash | D9: nayapay | E9: It's secure and easy to use. | F9: Not Switched | G9: =IF(Reason_to_switch[[#This Row],[Switch_Status]]="Not Switched",Reason_to_switch[[#This Row],[Switch_Status]]) -> Not Switched | H9: =VLOOKUP(Reason_to_switch[[#This Row],[Name]],SINGLE_RESPONSES[],8,FALSE) -> 7 | I9: =IF(Reason_to_switch[[#This Row],[Switch_Status]]="Not Switched",Reason_to_switch[[#This Row],[Switch_Status]],"TRUE") -> Not Switched | J9: Neutral | K9: Better UX
A10: Kainat | B10: jazzcash | C10: jazzcash | D10: jazzcash | E10: Not switched | F10: Not Switched | G10: =IF(Reason_to_switch[[#This Row],[Switch_Status]]="Not Switched",Reason_to_switch[[#This Row],[Switch_Status]]) -> Not Switched | H10: =VLOOKUP(Reason_to_switch[[#This Row],[Name]],SINGLE_RESPONSES[],8,FALSE) -> 4 | I10: =IF(Reason_to_switch[[#This Row],[Switch_Status]]="Not Switched",Reason_to_switch[[#This Row],[Switch_Status]],"TRUE") -> Not Switched | J10: Neutral | K10: Better UX
A11: Muhammad Danish Zafar | B11: jazzcash | C11: easypaisa | D11: sadapay | E11: Most of the time servers down | F11: Most of the time servers down | G11: Technical Failures | H11: =VLOOKUP(Reason_to_switch[[#This Row],[Name]],SINGLE_RESPONSES[],8,FALSE) -> 7 | I11: =IF(Reason_to_switch[[#This Row],[Switch_Status]]="Not Switched",Reason_to_switch[[#This Row],[Switch_Status]],"TRUE") -> TRUE | J11: Push | K11: Better features
A12: Hassan Jehangir | B12: jazzcash | C12: easypaisa | D12: jazzcash | E12: Easy to transfer money instantly | F12: Easy to transfer money instantly | G12: Performance | H12: =VLOOKUP(Reason_to_switch[[#This Row],[Name]],SINGLE_RESPONSES[],8,FALSE) -> 4 | I12: =IF(Reason_to_switch[[#This Row],[Switch_Status]]="Not Switched",Reason_to_switch[[#This Row],[Switch_Status]],"TRUE") -> TRUE | J12: Pull | K12: Better UX
A13: Rayyan Amin | B13: easypaisa | C13: jazzcash | D13: easypaisa | E13: Better services | F13: Better services | G13: Good Customer Services | H13: =VLOOKUP(Reason_to_switch[[#This Row],[Name]],SINGLE_RESPONSES[],8,FALSE) -> 5 | I13: =IF(Reason_to_switch[[#This Row],[Switch_Status]]="Not Switched",Reason_to_switch[[#This Row],[Switch_Status]],"TRUE") -> TRUE | J13: Pull | K13: Better UX
A14: Arslan Nawaz | B14: easypaisa | C14: easypaisa | D14: nayapay | E14: Due to More Features and International transactions features | F14: Not Switched | G14: =IF(Reason_to_switch[[#This Row],[Switch_Status]]="Not Switched",Reason_to_switch[[#This Row],[Switch_Status]]) -> Not Switched | H14: =VLOOKUP(Reason_to_switch[[#This Row],[Name]],SINGLE_RESPONSES[],8,FALSE) -> 7 | I14: =IF(Reason_to_switch[[#This Row],[Switch_Status]]="Not Switched",Reason_to_switch[[#This Row],[Switch_Status]],"TRUE") -> Not Switched | J14: Neutral | K14: Better Features
A15: Hamza | B15: easypaisa | C15: jazzcash | D15: jazzcash | E15: Sada pay account ban | F15: Sada pay account ban | G15: Account Access Issues | H15: =VLOOKUP(Reason_to_switch[[#This Row],[Name]],SINGLE_RESPONSES[],8,FALSE) -> 7 | I15: =IF(Reason_to_switch[[#This Row],[Switch_Status]]="Not Switched",Reason_to_switch[[#This Row],[Switch_Status]],"TRUE") -> TRUE | J15: Push | K15: Other
A16: Mona Amir | B16: jazzcash | C16: jazzcash | D16: jazzcash | E16: Easy to use and login | F16: Not Switched | G16: =IF(Reason_to_switch[[#This Row],[Switch_Status]]="Not Switched",Reason_to_switch[[#This Row],[Switch_Status]]) -> Not Switched | H16: =VLOOKUP(Reason_to_switch[[#This Row],[Name]],SINGLE_RESPONSES[],8,FALSE) -> 7 | I16: =IF(Reason_to_switch[[#This Row],[Switch_Status]]="Not Switched",Reason_to_switch[[#This Row],[Switch_Status]],"TRUE") -> Not Switched | J16: Neutral | K16: Better UX
A17: Ab | B17: jazzcash | C17: easypaisa | D17: sadapay | E17: Easy to use | F17: Easy to use | G17: Better UX | H17: =VLOOKUP(Reason_to_switch[[#This Row],[Name]],SINGLE_RESPONSES[],8,FALSE) -> 7 | I17: =IF(Reason_to_switch[[#This Row],[Switch_Status]]="Not Switched",Reason_to_switch[[#This Row],[Switch_Status]],"TRUE") -> TRUE | J17: Pull | K17: Better UX
A18: Hafiz Jawad | B18: jazzcash | C18: easypaisa | D18: jazzcash | E18: EasyPaisa PIN was compromised | F18: EasyPaisa PIN was compromised | G18: Trust issues | H18: =VLOOKUP(Reason_to_switch[[#This Row],[Name]],SINGLE_RESPONSES[],8,FALSE) -> 4 | I18: =IF(Reason_to_switch[[#This Row],[Switch_Status]]="Not Switched",Reason_to_switch[[#This Row],[Switch_Status]],"TRUE") -> TRUE | J18: Push | K18: Ecosystem Advantage
A19: Adan Ahmad | B19: easypaisa | C19: jazzcash | D19: easypaisa | E19: No particular reason | F19: Explore | G19: Explore | H19: =VLOOKUP(Reason_to_switch[[#This Row],[Name]],SINGLE_RESPONSES[],8,FALSE) -> 7 | I19: =IF(Reason_to_switch[[#This Row],[Switch_Status]]="Not Switched",Reason_to_switch[[#This Row],[Switch_Status]],"TRUE") -> TRUE | J19: Pull | K19: Better UX
A20: .. | B20: jazzcash | C20: jazzcash | D20: jazzcash | E20: 😬 | F20: Not Switched | G20: =IF(Reason_to_switch[[#This Row],[Switch_Status]]="Not Switched",Reason_to_switch[[#This Row],[Switch_Status]]) -> Not Switched | H20: =VLOOKUP(Reason_to_switch[[#This Row],[Name]],SINGLE_RESPONSES[],8,FALSE) -> 7 | I20: =IF(Reason_to_switch[[#This Row],[Switch_Status]]="Not Switched",Reason_to_switch[[#This Row],[Switch_Status]],"TRUE") -> Not Switched | J20: Neutral | K20: Better Features
A21: Imtisaal | B21: jazzcash | C21: jazzcash | D21: jazzcash | E21: Can do it with ubl digital account | F21: Not Switched | G21: =IF(Reason_to_switch[[#This Row],[Switch_Status]]="Not Switched",Reason_to_switch[[#This Row],[Switch_Status]]) -> Not Switched | H21: =VLOOKUP(Reason_to_switch[[#This Row],[Name]],SINGLE_RESPONSES[],8,FALSE) -> 5 | I21: =IF(Reason_to_switch[[#This Row],[Switch_Status]]="Not Switched",Reason_to_switch[[#This Row],[Switch_Status]],"TRUE") -> Not Switched | J21: Neutral | K21: Better UX
A22: Rana Hassaan | B22: jazzcash | C22: jazzcash | D22: jazzcash | E22: To manage international payments I prefer sada pay | F22: Not Switched | G22: =IF(Reason_to_switch[[#This Row],[Switch_Status]]="Not Switched",Reason_to_switch[[#This Row],[Switch_Status]]) -> Not Switched | H22: =VLOOKUP(Reason_to_switch[[#This Row],[Name]],SINGLE_RESPONSES[],8,FALSE) -> 6 | I22: =IF(Reason_to_switch[[#This Row],[Switch_Status]]="Not Switched",Reason_to_switch[[#This Row],[Switch_Status]],"TRUE") -> Not Switched | J22: Neutral | K22: Better UX
A23: Shoaib Ahmad | B23: jazzcash | C23: jazzcash | D23: jazzcash | E23: Mostly use jazzcash | F23: Not Switched | G23: =IF(Reason_to_switch[[#This Row],[Switch_Status]]="Not Switched",Reason_to_switch[[#This Row],[Switch_Status]]) -> Not Switched | H23: =VLOOKUP(Reason_to_switch[[#This Row],[Name]],SINGLE_RESPONSES[],8,FALSE) -> 7 | I23: =IF(Reason_to_switch[[#This Row],[Switch_Status]]="Not Switched",Reason_to_switch[[#This Row],[Switch_Status]],"TRUE") -> Not Switched | J23: Neutral | K23: Ecosystem Advantage
A24: DAC | B24: jazzcash | C24: nayapay | D24: jazzcash | G24: Better UX | H24: =VLOOKUP(Reason_to_switch[[#This Row],[Name]],SINGLE_RESPONSES[],8,FALSE) -> 7 | I24: =IF(Reason_to_switch[[#This Row],[Switch_Status]]="Not Switched",Reason_to_switch[[#This Row],[Switch_Status]],"TRUE") -> TRUE | J24: Pull | K24: Better UX
A25: Momin Ali | B25: easypaisa | C25: easypaisa | D25: easypaisa | E25: Na | F25: Not Switched | G25: =IF(Reason_to_switch[[#This Row],[Switch_Status]]="Not Switched",Reason_to_switch[[#This Row],[Switch_Status]]) -> Not Switched | H25: =VLOOKUP(Reason_to_switch[[#This Row],[Name]],SINGLE_RESPONSES[],8,FALSE) -> 5 | I25: =IF(Reason_to_switch[[#This Row],[Switch_Status]]="Not Switched",Reason_to_switch[[#This Row],[Switch_Status]],"TRUE") -> Not Switched | J25: Neutral | K25: Better Features
A26: Iqra | B26: jazzcash | C26: jazzcash | D26: jazzcash | E26: No change | F26: Not Switched | G26: =IF(Reason_to_switch[[#This Row],[Switch_Status]]="Not Switched",Reason_to_switch[[#This Row],[Switch_Status]]) -> Not Switched | H26: =VLOOKUP(Reason_to_switch[[#This Row],[Name]],SINGLE_RESPONSES[],8,FALSE) -> 7 | I26: =IF(Reason_to_switch[[#This Row],[Switch_Status]]="Not Switched",Reason_to_switch[[#This Row],[Switch_Status]],"TRUE") -> Not Switched | J26: Neutral | K26: Better UX
A27: Amna | B27: jazzcash | C27: nayapay | D27: jazzcash | E27: Using it for the first time. | F27: Using it for the first time. | G27: Explore | H27: =VLOOKUP(Reason_to_switch[[#This Row],[Name]],SINGLE_RESPONSES[],8,FALSE) -> 6 | I27: =IF(Reason_to_switch[[#This Row],[Switch_Status]]="Not Switched",Reason_to_switch[[#This Row],[Switch_Status]],"TRUE") -> TRUE | J27: Pull | K27: Better UX
A28: Laiba | B28: easypaisa | C28: jazzcash | D28: easypaisa | E28: Idk | F28: Idk | G28: Explore | H28: =VLOOKUP(Reason_to_switch[[#This Row],[Name]],SINGLE_RESPONSES[],8,FALSE) -> 6 | I28: =IF(Reason_to_switch[[#This Row],[Switch_Status]]="Not Switched",Reason_to_switch[[#This Row],[Switch_Status]],"TRUE") -> TRUE | J28: Pull | K28: Explore
A29: Haider shah | B29: easypaisa | C29: easypaisa | D29: easypaisa | E29: Easypaisa is more essential | F29: Not Switched | G29: =IF(Reason_to_switch[[#This Row],[Switch_Status]]="Not Switched",Reason_to_switch[[#This Row],[Switch_Status]]) -> Not Switched | H29: =VLOOKUP(Reason_to_switch[[#This Row],[Name]],SINGLE_RESPONSES[],8,FALSE) -> 7 | I29: =IF(Reason_to_switch[[#This Row],[Switch_Status]]="Not Switched",Reason_to_switch[[#This Row],[Switch_Status]],"TRUE") -> Not Switched | J29: Neutral | K29: Greater Trust
A30: Meerab Arshad | B30: jazzcash | C30: jazzcash | D30: jazzcash | E30: Jazz cash | F30: Not Switched | G30: =IF(Reason_to_switch[[#This Row],[Switch_Status]]="Not Switched",Reason_to_switch[[#This Row],[Switch_Status]]) -> Not Switched | H30: =VLOOKUP(Reason_to_switch[[#This Row],[Name]],SINGLE_RESPONSES[],8,FALSE) -> 2 | I30: =IF(Reason_to_switch[[#This Row],[Switch_Status]]="Not Switched",Reason_to_switch[[#This Row],[Switch_Status]],"TRUE") -> Not Switched | J30: Neutral | K30: Other
A31: Muhammad Ziad Amir | B31: sadapay | C31: jazzcash | D31: sadapay | E31: App errors | F31: App errors | G31: Technical Failures | H31: =VLOOKUP(Reason_to_switch[[#This Row],[Name]],SINGLE_RESPONSES[],8,FALSE) -> 5 | I31: =IF(Reason_to_switch[[#This Row],[Switch_Status]]="Not Switched",Reason_to_switch[[#This Row],[Switch_Status]],"TRUE") -> TRUE | J31: Push | K31: Better Features
A32: Amina | B32: jazzcash | C32: jazzcash | D32: jazzcash | E32: Today requirement in this digital world | F32: Not Switched | G32: =IF(Reason_to_switch[[#This Row],[Switch_Status]]="Not Switched",Reason_to_switch[[#This Row],[Switch_Status]]) -> Not Switched | H32: =VLOOKUP(Reason_to_switch[[#This Row],[Name]],SINGLE_RESPONSES[],8,FALSE) -> 7 | I32: =IF(Reason_to_switch[[#This Row],[Switch_Status]]="Not Switched",Reason_to_switch[[#This Row],[Switch_Status]],"TRUE") -> Not Switched | J32: Neutral | K32: Better UX
A33: Kanza | B33: sadapay | C33: jazzcash | D33: sadapay | E33: I trust Sadapay better maybe cuz its not run locally | F33: I trust Sadapay better maybe cuz its not run locally | G33: Trust issues | H33: =VLOOKUP(Reason_to_switch[[#This Row],[Name]],SINGLE_RESPONSES[],8,FALSE) -> 7 | I33: =IF(Reason_to_switch[[#This Row],[Switch_Status]]="Not Switched",Reason_to_switch[[#This Row],[Switch_Status]],"TRUE") -> TRUE | J33: Push | K33: Better UX
A34: Rana Ali Hassan | B34: sadapay | C34: sadapay | D34: sadapay | E34: Sometimes payment stuck and also some error are happened | F34: Not Switched | G34: =IF(Reason_to_switch[[#This Row],[Switch_Status]]="Not Switched",Reason_to_switch[[#This Row],[Switch_Status]]) -> Not Switched | H34: =VLOOKUP(Reason_to_switch[[#This Row],[Name]],SINGLE_RESPONSES[],8,FALSE) -> 3 | I34: =IF(Reason_to_switch[[#This Row],[Switch_Status]]="Not Switched",Reason_to_switch[[#This Row],[Switch_Status]],"TRUE") -> Not Switched | J34: Neutral | K34: Better UX
A35: amber | B35: jazzcash | C35: easypaisa | D35: jazzcash | E35: jazzcash is easy to use and am used to it now | F35: jazzcash is easy to use and am used to it now | G35: Better UX | H35: =VLOOKUP(Reason_to_switch[[#This Row],[Name]],SINGLE_RESPONSES[],8,FALSE) -> 2 | I35: =IF(Reason_to_switch[[#This Row],[Switch_Status]]="Not Switched",Reason_to_switch[[#This Row],[Switch_Status]],"TRUE") -> TRUE | J35: Pull | K35: Ecosystem Advantage
A36: Naseer Ahmad | B36: jazzcash | C36: jazzcash | D36: easypaisa | E36: For service issues | F36: Not Switched | G36: =IF(Reason_to_switch[[#This Row],[Switch_Status]]="Not Switched",Reason_to_switch[[#This Row],[Switch_Status]]) -> Not Switched | H36: =VLOOKUP(Reason_to_switch[[#This Row],[Name]],SINGLE_RESPONSES[],8,FALSE) -> 6 | I36: =IF(Reason_to_switch[[#This Row],[Switch_Status]]="Not Switched",Reason_to_switch[[#This Row],[Switch_Status]],"TRUE") -> Not Switched | J36: Neutral | K36: Good Customer Service
A37: Mahnoor | B37: jazzcash | C37: jazzcash | D37: jazzcash | E37: Is it good for myself and working fastly | F37: Not Switched | G37: =IF(Reason_to_switch[[#This Row],[Switch_Status]]="Not Switched",Reason_to_switch[[#This Row],[Switch_Status]]) -> Not Switched | H37: =VLOOKUP(Reason_to_switch[[#This Row],[Name]],SINGLE_RESPONSES[],8,FALSE) -> 4 | I37: =IF(Reason_to_switch[[#This Row],[Switch_Status]]="Not Switched",Reason_to_switch[[#This Row],[Switch_Status]],"TRUE") -> Not Switched | J37: Neutral | K37: Performance
A38: Abdul hafeez | B38: jazzcash | C38: jazzcash | D38: jazzcash | E38: Its easy to me | F38: Not Switched | G38: =IF(Reason_to_switch[[#This Row],[Switch_Status]]="Not Switched",Reason_to_switch[[#This Row],[Switch_Status]]) -> Not Switched | H38: =VLOOKUP(Reason_to_switch[[#This Row],[Name]],SINGLE_RESPONSES[],8,FALSE) -> 7 | I38: =IF(Reason_to_switch[[#This Row],[Switch_Status]]="Not Switched",Reason_to_switch[[#This Row],[Switch_Status]],"TRUE") -> Not Switched | J38: Neutral | K38: Better UX
A39: Amna Zohaib | B39: jazzcash | C39: easypaisa | D39: jazzcash | E39: It's convenient for me | F39: It's convenient for me | G39: Ecosystem Advantage | H39: =VLOOKUP(Reason_to_switch[[#This Row],[Name]],SINGLE_RESPONSES[],8,FALSE) -> 6 | I39: =IF(Reason_to_switch[[#This Row],[Switch_Status]]="Not Switched",Reason_to_switch[[#This Row],[Switch_Status]],"TRUE") -> TRUE | J39: Pull | K39: Explore
A40: Sania | B40: jazzcash | C40: nayapay | D40: nayapay | E40: Didn’t switch | F40: Not Switched | G40: Explore | H40: =VLOOKUP(Reason_to_switch[[#This Row],[Name]],SINGLE_RESPONSES[],8,FALSE) -> 7 | I40: =IF(Reason_to_switch[[#This Row],[Switch_Status]]="Not Switched",Reason_to_switch[[#This Row],[Switch_Status]],"TRUE") -> Not Switched | J40: Pull | K40: Better UX
A41: Hozaifa Rashid | B41: nayapay | C41: nayapay | D41: nayapay | E41: Smooth UI | F41: Not Switched | G41: =IF(Reason_to_switch[[#This Row],[Switch_Status]]="Not Switched",Reason_to_switch[[#This Row],[Switch_Status]]) -> Not Switched | H41: =VLOOKUP(Reason_to_switch[[#This Row],[Name]],SINGLE_RESPONSES[],8,FALSE) -> 7 | I41: =IF(Reason_to_switch[[#This Row],[Switch_Status]]="Not Switched",Reason_to_switch[[#This Row],[Switch_Status]],"TRUE") -> Not Switched | J41: Neutral | K41: Better UX
A42: Ayesha | B42: easypaisa | C42: easypaisa | D42: easypaisa | E42: I didn't use any other app before | F42: Not Switched | G42: =IF(Reason_to_switch[[#This Row],[Switch_Status]]="Not Switched",Reason_to_switch[[#This Row],[Switch_Status]]) -> Not Switched | H42: =VLOOKUP(Reason_to_switch[[#This Row],[Name]],SINGLE_RESPONSES[],8,FALSE) -> 2 | I42: =IF(Reason_to_switch[[#This Row],[Switch_Status]]="Not Switched",Reason_to_switch[[#This Row],[Switch_Status]],"TRUE") -> Not Switched | J42: Neutral | K42: Better UX
A43: Muhammed Abdullah | B43: jazzcash | C43: sadapay | D43: jazzcash | E43: Better banking facilities and features | F43: Better banking facilities and features | G43: Better Features | H43: =VLOOKUP(Reason_to_switch[[#This Row],[Name]],SINGLE_RESPONSES[],8,FALSE) -> 7 | I43: =IF(Reason_to_switch[[#This Row],[Switch_Status]]="Not Switched",Reason_to_switch[[#This Row],[Switch_Status]],"TRUE") -> TRUE | J43: Pull | K43: Better Features
A44: Muhammad Tayyab | B44: jazzcash | C44: easypaisa | D44: jazzcash | E44: Nothing | F44: Explore | G44: Explore | H44: =VLOOKUP(Reason_to_switch[[#This Row],[Name]],SINGLE_RESPONSES[],8,FALSE) -> 7 | I44: =IF(Reason_to_switch[[#This Row],[Switch_Status]]="Not Switched",Reason_to_switch[[#This Row],[Switch_Status]],"TRUE") -> TRUE | J44: Pull | K44: Better UX
A45: Zohaib javaid | B45: jazzcash | C45: easypaisa | D45: jazzcash | E45: No specific reason | F45: No specific reason | G45: Explore | H45: =VLOOKUP(Reason_to_switch[[#This Row],[Name]],SINGLE_RESPONSES[],8,FALSE) -> 7 | I45: =IF(Reason_to_switch[[#This Row],[Switch_Status]]="Not Switched",Reason_to_switch[[#This Row],[Switch_Status]],"TRUE") -> TRUE | J45: Pull | K45: Better UX
A46: Aroona | B46: jazzcash | C46: jazzcash | D46: easypaisa | E46: Sometime app not responding | F46: Not Switched | G46: =IF(Reason_to_switch[[#This Row],[Switch_Status]]="Not Switched",Reason_to_switch[[#This Row],[Switch_Status]]) -> Not Switched | H46: =VLOOKUP(Reason_to_switch[[#This Row],[Name]],SINGLE_RESPONSES[],8,FALSE) -> 7 | I46: =IF(Reason_to_switch[[#This Row],[Switch_Status]]="Not Switched",Reason_to_switch[[#This Row],[Switch_Status]],"TRUE") -> Not Switched | J46: Neutral | K46: Ecosystem Advantage
A47: Muhammad Tayyab | B47: jazzcash | C47: easypaisa | D47: jazzcash | E47: Quickest | F47: Quickest | G47: Performance | H47: =VLOOKUP(Reason_to_switch[[#This Row],[Name]],SINGLE_RESPONSES[],8,FALSE) -> 7 | I47: =IF(Reason_to_switch[[#This Row],[Switch_Status]]="Not Switched",Reason_to_switch[[#This Row],[Switch_Status]],"TRUE") -> TRUE | J47: Pull | K47: Better Features
A48: Dawood humayuon | B48: jazzcash | C48: sadapay | D48: easypaisa | E48: Easy payment method / transaction | F48: Easy payment method / transaction | G48: Better UX | H48: =VLOOKUP(Reason_to_switch[[#This Row],[Name]],SINGLE_RESPONSES[],8,FALSE) -> 7 | I48: =IF(Reason_to_switch[[#This Row],[Switch_Status]]="Not Switched",Reason_to_switch[[#This Row],[Switch_Status]],"TRUE") -> TRUE | J48: Pull | K48: Greater Trust
A49: Muhammad Afzal Faheem | B49: jazzcash | C49: jazzcash | D49: easypaisa | E49: The make the payment process more convenient | F49: Not Switched | G49: =IF(Reason_to_switch[[#This Row],[Switch_Status]]="Not Switched",Reason_to_switch[[#This Row],[Switch_Status]]) -> Not Switched | H49: =VLOOKUP(Reason_to_switch[[#This Row],[Name]],SINGLE_RESPONSES[],8,FALSE) -> 7 | I49: =IF(Reason_to_switch[[#This Row],[Switch_Status]]="Not Switched",Reason_to_switch[[#This Row],[Switch_Status]],"TRUE") -> Not Switched | J49: Neutral | K49: Performance
A50: Muhammad Mohsin Akram | B50: jazzcash | C50: jazzcash | D50: easypaisa | E50: No extra features in this app | F50: Not Switched | G50: =IF(Reason_to_switch[[#This Row],[Switch_Status]]="Not Switched",Reason_to_switch[[#This Row],[Switch_Status]]) -> Not Switched | H50: =VLOOKUP(Reason_to_switch[[#This Row],[Name]],SINGLE_RESPONSES[],8,FALSE) -> 7 | I50: =IF(Reason_to_switch[[#This Row],[Switch_Status]]="Not Switched",Reason_to_switch[[#This Row],[Switch_Status]],"TRUE") -> Not Switched | J50: Neutral | K50: Better UX
A51: Aliza khan | B51: easypaisa | C51: sadapay | D51: easypaisa | E51: No specific reason | F51: No specific reason | G51: Explore | H51: =VLOOKUP(Reason_to_switch[[#This Row],[Name]],SINGLE_RESPONSES[],8,FALSE) -> 4 | I51: =IF(Reason_to_switch[[#This Row],[Switch_Status]]="Not Switched",Reason_to_switch[[#This Row],[Switch_Status]],"TRUE") -> TRUE | J51: Pull | K51: Better UX
A52: Ikram mir | B52: sadapay | C52: easypaisa | D52: sadapay | E52: Extra use | F52: Extra use | G52: Explore | H52: =VLOOKUP(Reason_to_switch[[#This Row],[Name]],SINGLE_RESPONSES[],8,FALSE) -> 5 | I52: =IF(Reason_to_switch[[#This Row],[Switch_Status]]="Not Switched",Reason_to_switch[[#This Row],[Switch_Status]],"TRUE") -> TRUE | J52: Pull | K52: Better UX
A53: Talha | B53: sadapay | C53: easypaisa | D53: sadapay | E53: Service | F53: Service | G53: Good Customer Services | H53: =VLOOKUP(Reason_to_switch[[#This Row],[Name]],SINGLE_RESPONSES[],8,FALSE) -> 4 | I53: =IF(Reason_to_switch[[#This Row],[Switch_Status]]="Not Switched",Reason_to_switch[[#This Row],[Switch_Status]],"TRUE") -> TRUE | J53: Pull | K53: Better UX
A54: jk | B54: jazzcash | C54: easypaisa | D54: jazzcash | E54: UI | F54: UI | G54: Better UX | H54: =VLOOKUP(Reason_to_switch[[#This Row],[Name]],SINGLE_RESPONSES[],8,FALSE) -> 6 | I54: =IF(Reason_to_switch[[#This Row],[Switch_Status]]="Not Switched",Reason_to_switch[[#This Row],[Switch_Status]],"TRUE") -> TRUE | J54: Pull | K54: Better UX
A55: Nasreen | B55: easypaisa | C55: easypaisa | D55: easypaisa | E55: Hight security | F55: Not Switched | G55: =IF(Reason_to_switch[[#This Row],[Switch_Status]]="Not Switched",Reason_to_switch[[#This Row],[Switch_Status]]) -> Not Switched | H55: =VLOOKUP(Reason_to_switch[[#This Row],[Name]],SINGLE_RESPONSES[],8,FALSE) -> 6 | I55: =IF(Reason_to_switch[[#This Row],[Switch_Status]]="Not Switched",Reason_to_switch[[#This Row],[Switch_Status]],"TRUE") -> Not Switched | J55: Neutral | K55: Good Customer Service
A56: Ashraf Ali | B56: jazzcash | C56: jazzcash | D56: jazzcash | E56: N A | F56: Not Switched | G56: =IF(Reason_to_switch[[#This Row],[Switch_Status]]="Not Switched",Reason_to_switch[[#This Row],[Switch_Status]]) -> Not Switched | H56: =VLOOKUP(Reason_to_switch[[#This Row],[Name]],SINGLE_RESPONSES[],8,FALSE) -> 5 | I56: =IF(Reason_to_switch[[#This Row],[Switch_Status]]="Not Switched",Reason_to_switch[[#This Row],[Switch_Status]],"TRUE") -> Not Switched | J56: Neutral | K56: Ecosystem Advantage
A57: Ramsha Ashfaq | B57: sadapay | C57: jazzcash | D57: sadapay | E57: None | F57: None | G57: Explore | H57: =VLOOKUP(Reason_to_switch[[#This Row],[Name]],SINGLE_RESPONSES[],8,FALSE) -> 1 | I57: =IF(Reason_to_switch[[#This Row],[Switch_Status]]="Not Switched",Reason_to_switch[[#This Row],[Switch_Status]],"TRUE") -> TRUE | J57: Pull | K57: Explore
A58: Arfa | B58: sadapay | C58: easypaisa | D58: sadapay | E58: Better application and process | F58: Better application and process | G58: Better UX | H58: =VLOOKUP(Reason_to_switch[[#This Row],[Name]],SINGLE_RESPONSES[],8,FALSE) -> 1 | I58: =IF(Reason_to_switch[[#This Row],[Switch_Status]]="Not Switched",Reason_to_switch[[#This Row],[Switch_Status]],"TRUE") -> TRUE | J58: Pull | K58: Better Features
A59: Raheel | B59: nayapay | C59: nayapay | D59: nayapay | E59: Rdx | F59: Not Switched | G59: =IF(Reason_to_switch[[#This Row],[Switch_Status]]="Not Switched",Reason_to_switch[[#This Row],[Switch_Status]]) -> Not Switched | H59: =VLOOKUP(Reason_to_switch[[#This Row],[Name]],SINGLE_RESPONSES[],8,FALSE) -> 7 | I59: =IF(Reason_to_switch[[#This Row],[Switch_Status]]="Not Switched",Reason_to_switch[[#This Row],[Switch_Status]],"TRUE") -> Not Switched | J59: Neutral | K59: Better Features
A60: Hina Shabbir | B60: jazzcash | C60: jazzcash | D60: jazzcash | E60: Transaction Problem | F60: Not Switched | G60: =IF(Reason_to_switch[[#This Row],[Switch_Status]]="Not Switched",Reason_to_switch[[#This Row],[Switch_Status]]) -> Not Switched | H60: =VLOOKUP(Reason_to_switch[[#This Row],[Name]],SINGLE_RESPONSES[],8,FALSE) -> 7 | I60: =IF(Reason_to_switch[[#This Row],[Switch_Status]]="Not Switched",Reason_to_switch[[#This Row],[Switch_Status]],"TRUE") -> Not Switched | J60: Neutral | K60: Performance
A61: Noor | B61: easypaisa | C61: jazzcash | D61: easypaisa | E61: Needed more limit | F61: Needed more limit | G61: Better Features | H61: =VLOOKUP(Reason_to_switch[[#This Row],[Name]],SINGLE_RESPONSES[],8,FALSE) -> 4 | I61: =IF(Reason_to_switch[[#This Row],[Switch_Status]]="Not Switched",Reason_to_switch[[#This Row],[Switch_Status]],"TRUE") -> TRUE | J61: Pull | K61: Performance
A62: tahir kazmi | B62: jazzcash | C62: easypaisa | D62: jazzcash | E62: bill payment | F62: bill payment | G62: Better Features | H62: =VLOOKUP(Reason_to_switch[[#This Row],[Name]],SINGLE_RESPONSES[],8,FALSE) -> 6 | I62: =IF(Reason_to_switch[[#This Row],[Switch_Status]]="Not Switched",Reason_to_switch[[#This Row],[Switch_Status]],"TRUE") -> TRUE | J62: Pull | K62: Better UX
A63: M. Zain Azhar | B63: jazzcash | C63: easypaisa | D63: nayapay | E63: No reason juat depends on my wish | F63: No reason juat depends on my wish | G63: Explore | H63: =VLOOKUP(Reason_to_switch[[#This Row],[Name]],SINGLE_RESPONSES[],8,FALSE) -> 7 | I63: =IF(Reason_to_switch[[#This Row],[Switch_Status]]="Not Switched",Reason_to_switch[[#This Row],[Switch_Status]],"TRUE") -> TRUE | J63: Pull | K63: Better UX
A64: Laiba | B64: easypaisa | C64: nayapay | D64: easypaisa | E64: Transaction problem | F64: Transaction problem | G64: Technical Failures | H64: =VLOOKUP(Reason_to_switch[[#This Row],[Name]],SINGLE_RESPONSES[],8,FALSE) -> 6 | I64: =IF(Reason_to_switch[[#This Row],[Switch_Status]]="Not Switched",Reason_to_switch[[#This Row],[Switch_Status]],"TRUE") -> TRUE | J64: Push | K64: Performance
A65: Mohammed | B65: easypaisa | C65: nayapay | D65: easypaisa | E65: the app design | F65: the app design | G65: Better UX | H65: =VLOOKUP(Reason_to_switch[[#This Row],[Name]],SINGLE_RESPONSES[],8,FALSE) -> 3 | I65: =IF(Reason_to_switch[[#This Row],[Switch_Status]]="Not Switched",Reason_to_switch[[#This Row],[Switch_Status]],"TRUE") -> TRUE | J65: Pull | K65: Better UX
A66: Faizan Abbas | B66: jazzcash | C66: easypaisa | D66: jazzcash | E66: Easy to use | F66: Easy to use | G66: Better UX | H66: =VLOOKUP(Reason_to_switch[[#This Row],[Name]],SINGLE_RESPONSES[],8,FALSE) -> 4 | I66: =IF(Reason_to_switch[[#This Row],[Switch_Status]]="Not Switched",Reason_to_switch[[#This Row],[Switch_Status]],"TRUE") -> TRUE | J66: Pull | K66: Performance
A67: Flynn | B67: jazzcash | C67: nayapay | D67: jazzcash | E67: better ui, better customer experience | F67: better ui, better customer experience | G67: Good Customer Services | H67: =VLOOKUP(Reason_to_switch[[#This Row],[Name]],SINGLE_RESPONSES[],8,FALSE) -> 7 | I67: =IF(Reason_to_switch[[#This Row],[Switch_Status]]="Not Switched",Reason_to_switch[[#This Row],[Switch_Status]],"TRUE") -> TRUE | J67: Pull | K67: Better UX
A68: Shahwaiz Niazi | B68: jazzcash | C68: jazzcash | D68: jazzcash | E68: Efficient services | F68: Not Switched | G68: =IF(Reason_to_switch[[#This Row],[Switch_Status]]="Not Switched",Reason_to_switch[[#This Row],[Switch_Status]]) -> Not Switched | H68: =VLOOKUP(Reason_to_switch[[#This Row],[Name]],SINGLE_RESPONSES[],8,FALSE) -> 2 | I68: =IF(Reason_to_switch[[#This Row],[Switch_Status]]="Not Switched",Reason_to_switch[[#This Row],[Switch_Status]],"TRUE") -> Not Switched | J68: Neutral | K68: Good Customer Service
A69: muneeb ahmed | B69: jazzcash | C69: easypaisa | D69: jazzcash | E69: jazzcash account ban | F69: jazzcash account ban | G69: Account Access Issues | H69: =VLOOKUP(Reason_to_switch[[#This Row],[Name]],SINGLE_RESPONSES[],8,FALSE) -> 6 | I69: =IF(Reason_to_switch[[#This Row],[Switch_Status]]="Not Switched",Reason_to_switch[[#This Row],[Switch_Status]],"TRUE") -> TRUE | J69: Push | K69: Better Features
A70: Muhammad Adil Ahmef | B70: easypaisa | C70: easypaisa | D70: easypaisa | E70: It was my first digi wallet | F70: Not Switched | G70: =IF(Reason_to_switch[[#This Row],[Switch_Status]]="Not Switched",Reason_to_switch[[#This Row],[Switch_Status]]) -> Not Switched | H70: =VLOOKUP(Reason_to_switch[[#This Row],[Name]],SINGLE_RESPONSES[],8,FALSE) -> 7 | I70: =IF(Reason_to_switch[[#This Row],[Switch_Status]]="Not Switched",Reason_to_switch[[#This Row],[Switch_Status]],"TRUE") -> Not Switched | J70: Neutral | K70: Other
A71: Haider Ali | B71: easypaisa | C71: sadapay | D71: easypaisa | E71: Some transaction issues | F71: Some transaction issues | G71: Technical Failures | H71: =VLOOKUP(Reason_to_switch[[#This Row],[Name]],SINGLE_RESPONSES[],8,FALSE) -> 5 | I71: =IF(Reason_to_switch[[#This Row],[Switch_Status]]="Not Switched",Reason_to_switch[[#This Row],[Switch_Status]],"TRUE") -> TRUE | J71: Push | K71: Performance
A72: Amanat Jahangir | B72: easypaisa | C72: easypaisa | D72: easypaisa | E72: I never switched | F72: Not Switched | G72: =IF(Reason_to_switch[[#This Row],[Switch_Status]]="Not Switched",Reason_to_switch[[#This Row],[Switch_Status]]) -> Not Switched | H72: =VLOOKUP(Reason_to_switch[[#This Row],[Name]],SINGLE_RESPONSES[],8,FALSE) -> 7 | I72: =IF(Reason_to_switch[[#This Row],[Switch_Status]]="Not Switched",Reason_to_switch[[#This Row],[Switch_Status]],"TRUE") -> Not Switched | J72: Neutral | K72: Better Features
A73: Hasan Butt | B73: jazzcash | C73: jazzcash | D73: sadapay | E73: Easier UI | F73: Not Switched | G73: =IF(Reason_to_switch[[#This Row],[Switch_Status]]="Not Switched",Reason_to_switch[[#This Row],[Switch_Status]]) -> Not Switched | H73: =VLOOKUP(Reason_to_switch[[#This Row],[Name]],SINGLE_RESPONSES[],8,FALSE) -> 7 | I73: =IF(Reason_to_switch[[#This Row],[Switch_Status]]="Not Switched",Reason_to_switch[[#This Row],[Switch_Status]],"TRUE") -> Not Switched | J73: Neutral | K73: Better UX
A74: ch hammad | B74: sadapay | C74: sadapay | D74: nayapay | E74: using in parallel | F74: Not Switched | G74: =IF(Reason_to_switch[[#This Row],[Switch_Status]]="Not Switched",Reason_to_switch[[#This Row],[Switch_Status]]) -> Not Switched | H74: =VLOOKUP(Reason_to_switch[[#This Row],[Name]],SINGLE_RESPONSES[],8,FALSE) -> 5 | I74: =IF(Reason_to_switch[[#This Row],[Switch_Status]]="Not Switched",Reason_to_switch[[#This Row],[Switch_Status]],"TRUE") -> Not Switched | J74: Neutral | K74: Better Features
A75: Chand Ashraf | B75: jazzcash | C75: sadapay | D75: jazzcash | E75: There is no helpline number of sadapay | F75: There is no helpline number of sadapay | G75: Poor Customer Services | H75: =VLOOKUP(Reason_to_switch[[#This Row],[Name]],SINGLE_RESPONSES[],8,FALSE) -> 7 | I75: =IF(Reason_to_switch[[#This Row],[Switch_Status]]="Not Switched",Reason_to_switch[[#This Row],[Switch_Status]],"TRUE") -> TRUE | J75: Push | K75: Good Customer Service
A76: Fahad Khawar | B76: jazzcash | C76: nayapay | D76: jazzcash | E76: User friendly interface | F76: User friendly interface | G76: Better UX | H76: =VLOOKUP(Reason_to_switch[[#This Row],[Name]],SINGLE_RESPONSES[],8,FALSE) -> 7 | I76: =IF(Reason_to_switch[[#This Row],[Switch_Status]]="Not Switched",Reason_to_switch[[#This Row],[Switch_Status]],"TRUE") -> TRUE | J76: Pull | K76: Better UX
A77: Haroon Arif | B77: sadapay | C77: jazzcash | D77: sadapay | E77: Some quality issues | F77: Some quality issues | G77: Technical Failures | H77: =VLOOKUP(Reason_to_switch[[#This Row],[Name]],SINGLE_RESPONSES[],8,FALSE) -> 5 | I77: =IF(Reason_to_switch[[#This Row],[Switch_Status]]="Not Switched",Reason_to_switch[[#This Row],[Switch_Status]],"TRUE") -> TRUE | J77: Push | K77: Good Customer Service
A78: Hanan | B78: jazzcash | C78: jazzcash | D78: jazzcash | E78: I am not switching right now | F78: Not Switched | G78: =IF(Reason_to_switch[[#This Row],[Switch_Status]]="Not Switched",Reason_to_switch[[#This Row],[Switch_Status]]) -> Not Switched | H78: =VLOOKUP(Reason_to_switch[[#This Row],[Name]],SINGLE_RESPONSES[],8,FALSE) -> 7 | I78: =IF(Reason_to_switch[[#This Row],[Switch_Status]]="Not Switched",Reason_to_switch[[#This Row],[Switch_Status]],"TRUE") -> Not Switched | J78: Neutral | K78: Ecosystem Advantage
A79: Maham | B79: jazzcash | C79: jazzcash | D79: jazzcash | E79: Convenience | F79: Not Switched | G79: =IF(Reason_to_switch[[#This Row],[Switch_Status]]="Not Switched",Reason_to_switch[[#This Row],[Switch_Status]]) -> Not Switched | H79: =VLOOKUP(Reason_to_switch[[#This Row],[Name]],SINGLE_RESPONSES[],8,FALSE) -> 4 | I79: =IF(Reason_to_switch[[#This Row],[Switch_Status]]="Not Switched",Reason_to_switch[[#This Row],[Switch_Status]],"TRUE") -> Not Switched | J79: Neutral | K79: Good Customer Service
A80: Mohammad Rameel waseem | B80: jazzcash | C80: jazzcash | D80: jazzcash | E80: JazzCash has a simple and user-friendly interface, making transactions quick and easy. | F80: Not Switched | G80: =IF(Reason_to_switch[[#This Row],[Switch_Status]]="Not Switched",Reason_to_switch[[#This Row],[Switch_Status]]) -> Not Switched | H80: =VLOOKUP(Reason_to_switch[[#This Row],[Name]],SINGLE_RESPONSES[],8,FALSE) -> 2 | I80: =IF(Reason_to_switch[[#This Row],[Switch_Status]]="Not Switched",Reason_to_switch[[#This Row],[Switch_Status]],"TRUE") -> Not Switched | J80: Neutral | K80: Better Features
A81: Ayesha Ahmed | B81: nayapay | C81: easypaisa | D81: nayapay | E81: Some issues | F81: Some issues | G81: Technical Failures | H81: =VLOOKUP(Reason_to_switch[[#This Row],[Name]],SINGLE_RESPONSES[],8,FALSE) -> 4 | I81: =IF(Reason_to_switch[[#This Row],[Switch_Status]]="Not Switched",Reason_to_switch[[#This Row],[Switch_Status]],"TRUE") -> TRUE | J81: Push | K81: Better Features
A82: Saad | B82: jazzcash | C82: easypaisa | D82: nayapay | E82: Better mobile app service | F82: Better mobile app service | G82: Better Features | H82: =VLOOKUP(Reason_to_switch[[#This Row],[Name]],SINGLE_RESPONSES[],8,FALSE) -> 7 | I82: =IF(Reason_to_switch[[#This Row],[Switch_Status]]="Not Switched",Reason_to_switch[[#This Row],[Switch_Status]],"TRUE") -> TRUE | J82: Pull | K82: Better UX
A83: Ali Abbas | B83: easypaisa | C83: jazzcash | D83: easypaisa | E83: Primary wallet | F83: Primary wallet | G83: Ecosystem Advantage | H83: =VLOOKUP(Reason_to_switch[[#This Row],[Name]],SINGLE_RESPONSES[],8,FALSE) -> 6 | I83: =IF(Reason_to_switch[[#This Row],[Switch_Status]]="Not Switched",Reason_to_switch[[#This Row],[Switch_Status]],"TRUE") -> TRUE | J83: Pull | K83: Better Features
A84: Hassan | B84: jazzcash | C84: easypaisa | D84: jazzcash | E84: Convenience | F84: Convenience | G84: Better UX | H84: =VLOOKUP(Reason_to_switch[[#This Row],[Name]],SINGLE_RESPONSES[],8,FALSE) -> 5 | I84: =IF(Reason_to_switch[[#This Row],[Switch_Status]]="Not Switched",Reason_to_switch[[#This Row],[Switch_Status]],"TRUE") -> TRUE | J84: Pull | K84: Better UX
A85: Dr. Ata Ul Musawir | B85: jazzcash | C85: easypaisa | D85: jazzcash | E85: User-friendly UI, app speed | F85: User-friendly UI, app speed | G85: Performance | H85: =VLOOKUP(Reason_to_switch[[#This Row],[Name]],SINGLE_RESPONSES[],8,FALSE) -> 2 | I85: =IF(Reason_to_switch[[#This Row],[Switch_Status]]="Not Switched",Reason_to_switch[[#This Row],[Switch_Status]],"TRUE") -> TRUE | J85: Pull | K85: Performance
A86: Zoha ashfaq | B86: sadapay | C86: jazzcash | D86: sadapay | E86: Wese hi | F86: Wese hi | G86: Explore | H86: =VLOOKUP(Reason_to_switch[[#This Row],[Name]],SINGLE_RESPONSES[],8,FALSE) -> 7 | I86: =IF(Reason_to_switch[[#This Row],[Switch_Status]]="Not Switched",Reason_to_switch[[#This Row],[Switch_Status]],"TRUE") -> TRUE | J86: Pull | K86: Explore
A87: noor fatima | B87: nayapay | C87: nayapay | D87: nayapay | E87: I did not switch to another app because I am satisfied with my current primary app. It is easy to use, reliable, and meets all my needs. I feel comfortable using it, so I don’t see any strong reason to switch. | F87: Not Switched | G87: =IF(Reason_to_switch[[#This Row],[Switch_Status]]="Not Switched",Reason_to_switch[[#This Row],[Switch_Status]]) -> Not Switched | H87: =VLOOKUP(Reason_to_switch[[#This Row],[Name]],SINGLE_RESPONSES[],8,FALSE) -> 7 | I87: =IF(Reason_to_switch[[#This Row],[Switch_Status]]="Not Switched",Reason_to_switch[[#This Row],[Switch_Status]],"TRUE") -> Not Switched | J87: Neutral | K87: Better UX
A88: Ahmer Amin | B88: jazzcash | C88: easypaisa | D88: jazzcash | E88: alternative app | F88: alternative app | G88: Explore | H88: =VLOOKUP(Reason_to_switch[[#This Row],[Name]],SINGLE_RESPONSES[],8,FALSE) -> 5 | I88: =IF(Reason_to_switch[[#This Row],[Switch_Status]]="Not Switched",Reason_to_switch[[#This Row],[Switch_Status]],"TRUE") -> TRUE | J88: Pull | K88: Other
A89: Minahil shahbaz | B89: jazzcash | C89: jazzcash | D89: jazzcash | E89: Reason for switching | F89: Not Switched | G89: =IF(Reason_to_switch[[#This Row],[Switch_Status]]="Not Switched",Reason_to_switch[[#This Row],[Switch_Status]]) -> Not Switched | H89: =VLOOKUP(Reason_to_switch[[#This Row],[Name]],SINGLE_RESPONSES[],8,FALSE) -> 1 | I89: =IF(Reason_to_switch[[#This Row],[Switch_Status]]="Not Switched",Reason_to_switch[[#This Row],[Switch_Status]],"TRUE") -> Not Switched | J89: Neutral | K89: Other
A90: Ruttaba Ashraf | B90: easypaisa | C90: easypaisa | D90: nayapay | E90: Nayapay have more features than easypaisa | F90: Not Switched | G90: =IF(Reason_to_switch[[#This Row],[Switch_Status]]="Not Switched",Reason_to_switch[[#This Row],[Switch_Status]]) -> Not Switched | H90: =VLOOKUP(Reason_to_switch[[#This Row],[Name]],SINGLE_RESPONSES[],8,FALSE) -> 7 | I90: =IF(Reason_to_switch[[#This Row],[Switch_Status]]="Not Switched",Reason_to_switch[[#This Row],[Switch_Status]],"TRUE") -> Not Switched | J90: Neutral | K90: Better Features
A91: Mian Asim | B91: jazzcash | C91: jazzcash | D91: easypaisa | E91: Fraud detection | F91: Not Switched | G91: =IF(Reason_to_switch[[#This Row],[Switch_Status]]="Not Switched",Reason_to_switch[[#This Row],[Switch_Status]]) -> Not Switched | H91: =VLOOKUP(Reason_to_switch[[#This Row],[Name]],SINGLE_RESPONSES[],8,FALSE) -> 7 | I91: =IF(Reason_to_switch[[#This Row],[Switch_Status]]="Not Switched",Reason_to_switch[[#This Row],[Switch_Status]],"TRUE") -> Not Switched | J91: Neutral | K91: Greater Trust
A92: Hafiz Irtaza Aslam | B92: jazzcash | C92: jazzcash | D92: jazzcash | E92: I haven’t switched to any single app. In fact, I use multiple apps because it allows me to handle payments from different wallets, making it easier and more convenient for my clients. This way, there’s no issue in receiving payments. | F92: Not Switched | G92: =IF(Reason_to_switch[[#This Row],[Switch_Status]]="Not Switched",Reason_to_switch[[#This Row],[Switch_Status]]) -> Not Switched | H92: =VLOOKUP(Reason_to_switch[[#This Row],[Name]],SINGLE_RESPONSES[],8,FALSE) -> 7 | I92: =IF(Reason_to_switch[[#This Row],[Switch_Status]]="Not Switched",Reason_to_switch[[#This Row],[Switch_Status]],"TRUE") -> Not Switched | J92: Neutral | K92: Other
A93: Raheeq Sharif | B93: jazzcash | C93: jazzcash | D93: nayapay | E93: Easy to use | F93: Not Switched | G93: =IF(Reason_to_switch[[#This Row],[Switch_Status]]="Not Switched",Reason_to_switch[[#This Row],[Switch_Status]]) -> Not Switched | H93: =VLOOKUP(Reason_to_switch[[#This Row],[Name]],SINGLE_RESPONSES[],8,FALSE) -> 7 | I93: =IF(Reason_to_switch[[#This Row],[Switch_Status]]="Not Switched",Reason_to_switch[[#This Row],[Switch_Status]],"TRUE") -> Not Switched | J93: Neutral | K93: Financial benefits
A94: Hamza | B94: jazzcash | C94: jazzcash | D94: jazzcash | E94: No switch | F94: Not Switched | G94: =IF(Reason_to_switch[[#This Row],[Switch_Status]]="Not Switched",Reason_to_switch[[#This Row],[Switch_Status]]) -> Not Switched | H94: =VLOOKUP(Reason_to_switch[[#This Row],[Name]],SINGLE_RESPONSES[],8,FALSE) -> 7 | I94: =IF(Reason_to_switch[[#This Row],[Switch_Status]]="Not Switched",Reason_to_switch[[#This Row],[Switch_Status]],"TRUE") -> Not Switched | J94: Neutral | K94: Performance
A95: esha | B95: jazzcash | C95: jazzcash | D95: jazzcash | E95: Never switched | F95: Not Switched | G95: =IF(Reason_to_switch[[#This Row],[Switch_Status]]="Not Switched",Reason_to_switch[[#This Row],[Switch_Status]]) -> Not Switched | H95: =VLOOKUP(Reason_to_switch[[#This Row],[Name]],SINGLE_RESPONSES[],8,FALSE) -> 6 | I95: =IF(Reason_to_switch[[#This Row],[Switch_Status]]="Not Switched",Reason_to_switch[[#This Row],[Switch_Status]],"TRUE") -> Not Switched | J95: Neutral | K95: Better Features
A96: Ali hussnain | B96: sadapay | C96: jazzcash | D96: nayapay | E96: Easy transfer and no chances of scam | F96: Easy transfer and no chances of scam | G96: Greater Trust | H96: =VLOOKUP(Reason_to_switch[[#This Row],[Name]],SINGLE_RESPONSES[],8,FALSE) -> 7 | I96: =IF(Reason_to_switch[[#This Row],[Switch_Status]]="Not Switched",Reason_to_switch[[#This Row],[Switch_Status]],"TRUE") -> TRUE | J96: Pull | K96: Better Features
A97: Muhammad Saqib Shoaib | B97: jazzcash | C97: jazzcash | D97: jazzcash | E97: Jazz cash | F97: Not Switched | G97: =IF(Reason_to_switch[[#This Row],[Switch_Status]]="Not Switched",Reason_to_switch[[#This Row],[Switch_Status]]) -> Not Switched | H97: =VLOOKUP(Reason_to_switch[[#This Row],[Name]],SINGLE_RESPONSES[],8,FALSE) -> 7 | I97: =IF(Reason_to_switch[[#This Row],[Switch_Status]]="Not Switched",Reason_to_switch[[#This Row],[Switch_Status]],"TRUE") -> Not Switched | J97: Neutral | K97: Good Customer Service
A98: Muhammad Burhan Ahmad | B98: jazzcash | C98: easypaisa | D98: jazzcash | E98: It is more fast and more trusted and popular | F98: It is more fast and more trusted and popular | G98: Performance | H98: =VLOOKUP(Reason_to_switch[[#This Row],[Name]],SINGLE_RESPONSES[],8,FALSE) -> 7 | I98: =IF(Reason_to_switch[[#This Row],[Switch_Status]]="Not Switched",Reason_to_switch[[#This Row],[Switch_Status]],"TRUE") -> TRUE | J98: Pull | K98: Greater Trust
A99: Abdullah Ahmad | B99: jazzcash | C99: easypaisa | D99: jazzcash | E99: This is more convenient | F99: This is more convenient | G99: Better UX | H99: =VLOOKUP(Reason_to_switch[[#This Row],[Name]],SINGLE_RESPONSES[],8,FALSE) -> 4 | I99: =IF(Reason_to_switch[[#This Row],[Switch_Status]]="Not Switched",Reason_to_switch[[#This Row],[Switch_Status]],"TRUE") -> TRUE | J99: Pull | K99: Better Features
A100: Musa | B100: jazzcash | C100: easypaisa | D100: jazzcash | E100: Just wanted to change | F100: Just wanted to change | G100: Explore | H100: =VLOOKUP(Reason_to_switch[[#This Row],[Name]],SINGLE_RESPONSES[],8,FALSE) -> 1 | I100: =IF(Reason_to_switch[[#This Row],[Switch_Status]]="Not Switched",Reason_to_switch[[#This Row],[Switch_Status]],"TRUE") -> TRUE | J100: Pull | K100: Better UX
...
